Workbook

Sheet Times City
A3: Week 4 | C3: Day | D3: Mon | G3: Tue | J3: Wed | M3: Thu | P3: Fri | S3: Sat | V3: Sun
C4: ITEM | D4: Hour | E4: Total Hr | F4: Salary/hr | G4: Hour | H4: Total Hr | I4: Salary/hr | J4: Hour | K4: Total Hr | L4: Salary/hr | M4: Hour | N4: Total Hr | O4: Salary/hr | P4: Hour | Q4: Total Hr | R4: Salary/hr | S4: Hour | T4: Total Hr | U4: Salary/hr | V4: Hour | W4: Total Hr | X4: Salary/hr
A5: TIMES CITY | B5: Morning | C5: Mngt | D5: 8 | E5: =8 -> 8 | F5: =E5*G18 -> 307692.31 | G5: 8 | H5: =8 -> 8 | I5: =H5*G18 -> 307692.31 | J5: 8 | K5: =8 -> 8 | L5: =K5*G18 -> 307692.31 | M5: 8 | N5: =8 -> 8 | O5: =N5*G18 -> 307692.31 | P5: 16 | Q5: =P5 -> 16 | R5: =Q5*G18 -> 615384.62 | S5: 16 | T5: =S5 -> 16 | U5: =T5*G18 -> 615384.62 | V5: 16 | W5: =V5 -> 16 | X5: =W5*G18 -> 615384.62
C6: FOH | D6: 15 | E6: =D6+D7 -> 35 | F6: =E6*G22 -> 735000 | G6: 15 | H6: =G6+G7 -> 35 | I6: =H6*G22 -> 735000 | J6: 15 | K6: =J6+J7 -> 35 | L6: =K6*G22 -> 735000 | M6: 15 | N6: =M6+M7 -> 35 | O6: =N6*G22 -> 735000 | P6: 16 | Q6: =P6+P7 -> 36 | R6: =Q6*G22 -> 756000 | S6: 35 | T6: =S6+S7 -> 70 | U6: =T6*G22 -> 1470000 | V6: 35 | W6: =V6+V7 -> 70 | X6: =W6*G22 -> 1470000
C7: BOH | D7: 20 | G7: 20 | J7: 20 | M7: 20 | P7: 20 | S7: 35 | V7: 35
B9: Afternoon | C9: Mngt | D9: 16 | E9: =D9 -> 16 | F9: =E9*G18 -> 615384.62 | G9: 16 | H9: =G9 -> 16 | I9: =H9*G18 -> 615384.62 | J9: 16 | K9: =J9 -> 16 | L9: =K9*G18 -> 615384.62 | M9: 16 | N9: =M9 -> 16 | O9: =N9*G18 -> 615384.62 | P9: 16 | Q9: =P9 -> 16 | R9: =Q9*G18 -> 615384.62 | S9: 16 | T9: =S9 -> 16 | U9: =T9*G18 -> 615384.62 | V9: 16 | W9: =V9 -> 16 | X9: =W9*G18 -> 615384.62
C10: FOH | D10: 16 | E10: =D10+D11 -> 36 | F10: =E10*G22 -> 756000 | G10: 16 | H10: =G10+G11 -> 36 | I10: =H10*G22 -> 756000 | J10: 16 | K10: =J10+J11 -> 36 | L10: =K10*G22 -> 756000 | M10: 20 | N10: =M10+M11 -> 40 | O10: =N10*G22 -> 840000 | P10: 20 | Q10: =P10+P11 -> 45 | R10: =Q10*G22 -> 945000 | S10: 35 | T10: =S10+S11 -> 70 | U10: =T10*G22 -> 1470000 | V10: 35 | W10: =V10+V11 -> 70 | X10: =W10*G22 -> 1470000
C11: BOH | D11: 20 | G11: 20 | J11: 20 | M11: 20 | P11: 25 | S11: 35 | V11: 35
B12: Total | E12: =E5+E6+E9+E10 -> 95 | F12: =F5+F6+F9+F10 -> 2414076.9 | H12: =H5+H6+H9+H10 -> 95 | I12: =I5+I6+I9+I10 -> 2414076.9 | K12: =K5+K6+K9+K10 -> 95 | L12: =L5+L6+L9+L10 -> 2414076.9 | N12: =N5+N6+N9+N10 -> 99 | O12: =O5+O6+O9+O10 -> 2498076.9 | Q12: =Q5+Q6+Q9+Q10 -> 113 | R12: =R5+R6+R9+R10 -> 2931769.2 | T12: =T5+T6+T9+T10 -> 172 | U12: =U5+U6+U9+U10 -> 4170769.2 | W12: =W5+W6+W9+W10 -> 172 | X12: =X5+X6+X9+X10 -> 4170769.2
C14: Lương | E14: Lương trung bình Mngt | F14: Lương Mngt /ngày | G14: Lương/giờ
B15: RGM | C15: 12000000
B16: ARM | C16: 8000000
B17: SL | C17: 6000000
B18: SL | C18: 6000000 | E18: =AVERAGE(C15:C18) -> 8000000 | F18: =E18/26 -> 307692.31 | G18: =F18/8 -> 38461.538
B20: 3* | C20: 22000
B21: 2* | C21: 21000
B22: 1* | C22: 20000 | G22: =AVERAGE(C20:C22) -> 21000
A24: Sale forcasting /Week | C24: =SUM(C26:C32) -> 179000000
B26: Mon | C26: 15000000
B27: Tue | C27: 15000000
B28: Wed | C28: 17000000
B29: Thu | C29: 20000000
B30: Fri | C30: 22000000
B31: Sat | C31: 45000000
B32: Sun | C32: 45000000

Sheet Savico
A3: Week 4 | C3: Day | D3: Mon | G3: Tue | J3: Wed | M3: Thu | P3: Fri | S3: Sat | V3: Sun
C4: ITEM | D4: Hour | E4: Total Hr | F4: Salary/hr | G4: Hour | H4: Total Hr | I4: Salary/hr | J4: Hour | K4: Total Hr | L4: Salary/hr | M4: Hour | N4: Total Hr | O4: Salary/hr | P4: Hour | Q4: Total Hr | R4: Salary/hr | S4: Hour | T4: Total Hr | U4: Salary/hr | V4: Hour | W4: Total Hr | X4: Salary/hr
A5: SAVICO | B5: Morning | C5: Mngt | D5: 8 | E5: =8 -> 8 | F5: =E5*G18 -> 352564.1 | G5: 8 | H5: =8 -> 8 | I5: =H5*G18 -> 352564.1 | J5: 8 | K5: =8 -> 8 | L5: =K5*G18 -> 352564.1 | M5: 8 | N5: =8 -> 8 | O5: =N5*G18 -> 352564.1 | P5: 8 | Q5: =P5 -> 8 | R5: =Q5*G18 -> 352564.1 | S5: 8 | T5: =S5 -> 8 | U5: =T5*G18 -> 352564.1 | V5: 8 | W5: =V5 -> 8 | X5: =W5*G18 -> 352564.1
C6: FOH | D6: 14 | E6: =D6+D7 -> 33 | F6: =E6*G22 -> 693000 | G6: 14 | H6: =G6+G7 -> 33 | I6: =H6*G22 -> 693000 | J6: 14 | K6: =J6+J7 -> 33 | L6: =K6*G22 -> 693000 | M6: 14 | N6: =M6+M7 -> 33 | O6: =N6*G22 -> 693000 | P6: 14 | Q6: =P6+P7 -> 33 | R6: =Q6*G22 -> 693000 | S6: 30 | T6: =S6+S7 -> 65 | U6: =T6*G22 -> 1365000 | V6: 30 | W6: =V6+V7 -> 65 | X6: =W6*G22 -> 1365000
C7: BOH | D7: 19 | G7: 19 | J7: 19 | M7: 19 | P7: 19 | S7: 35 | V7: 35
B9: Afternoon | C9: Mngt | D9: 8 | E9: =D9 -> 8 | F9: =E9*G18 -> 352564.1 | G9: 8 | H9: =G9 -> 8 | I9: =H9*G18 -> 352564.1 | J9: 8 | K9: =J9 -> 8 | L9: =K9*G18 -> 352564.1 | M9: 8 | N9: =M9 -> 8 | O9: =N9*G18 -> 352564.1 | P9: 16 | Q9: =P9 -> 16 | R9: =Q9*G18 -> 705128.21 | S9: 16 | T9: =S9 -> 16 | U9: =T9*G18 -> 705128.21 | V9: 16 | W9: =V9 -> 16 | X9: =W9*G18 -> 705128.21
C10: FOH | D10: 15 | E10: =D10+D11 -> 34 | F10: =E10*G22 -> 714000 | G10: 16 | H10: =G10+G11 -> 35 | I10: =H10*G22 -> 735000 | J10: 16 | K10: =J10+J11 -> 35 | L10: =K10*G22 -> 735000 | M10: 16 | N10: =M10+M11 -> 35 | O10: =N10*G22 -> 735000 | P10: 20 | Q10: =P10+P11 -> 41 | R10: =Q10*G22 -> 861000 | S10: 30 | T10: =S10+S11 -> 65 | U10: =T10*G22 -> 1365000 | V10: 30 | W10: =V10+V11 -> 65 | X10: =W10*G22 -> 1365000
C11: BOH | D11: 19 | G11: 19 | J11: 19 | M11: 19 | P11: 21 | S11: 35 | V11: 35
B12: Total | E12: =E5+E6+E9+E10 -> 83 | F12: =F5+F6+F9+F10 -> 2112128.2 | H12: =H5+H6+H9+H10 -> 84 | I12: =I5+I6+I9+I10 -> 2133128.2 | K12: =K5+K6+K9+K10 -> 84 | L12: =L5+L6+L9+L10 -> 2133128.2 | N12: =N5+N6+N9+N10 -> 84 | O12: =O5+O6+O9+O10 -> 2133128.2 | Q12: =Q5+Q6+Q9+Q10 -> 98 | R12: =R5+R6+R9+R10 -> 2611692.3 | T12: =T5+T6+T9+T10 -> 154 | U12: =U5+U6+U9+U10 -> 3787692.3 | W12: =W5+W6+W9+W10 -> 154 | X12: =X5+X6+X9+X10 -> 3787692.3
C14: Lương | E14: Lương trung bình Mngt | F14: Lương Mngt /ngày | G14: Lương/giờ
B15: RGM | C15: 13500000
B16: ARM | C16: 8000000
B17: SL | C17: 6000000
E18: =AVERAGE(C15:C18) -> 9166666.7 | F18: =E18/26 -> 352564.1 | G18: =F18/8 -> 44070.513
B20: 3* | C20: 22000
B21: 2* | C21: 21000
B22: 1* | C22: 20000 | G22: =AVERAGE(C20:C22) -> 21000
A24: Sale forcasting /Week | C24: =SUM(C26:C32) -> 146000000
B26: Mon | C26: 12000000
B27: Tue | C27: 12000000
B28: Wed | C28: 12000000
B29: Thu | C29: 13000000
B30: Fri | C30: 17000000
B31: Sat | C31: 40000000
B32: Sun | C32: 40000000

Sheet Pico
A3: Week 4 | C3: Day | D3: Mon | G3: Tue | J3: Wed | M3: Thu | P3: Fri | S3: Sat | V3: Sun
C4: ITEM | D4: Hour | E4: Total Hr | F4: Salary/hr | G4: Hour | H4: Total Hr | I4: Salary/hr | J4: Hour | K4: Total Hr | L4: Salary/hr | M4: Hour | N4: Total Hr | O4: Salary/hr | P4: Hour | Q4: Total Hr | R4: Salary/hr | S4: Hour | T4: Total Hr | U4: Salary/hr | V4: Hour | W4: Total Hr | X4: Salary/hr
A5: PICO | B5: Morning | C5: Mngt | D5: 8 | E5: =8 -> 8 | F5: =E5*G17 -> 307692.31 | G5: 8 | H5: =8 -> 8 | I5: =H5*G17 -> 307692.31 | J5: 8 | K5: =8 -> 8 | L5: =K5*G17 -> 307692.31 | M5: 8 | N5: =8 -> 8 | O5: =N5*G17 -> 307692.31 | P5: 8 | Q5: =P5 -> 8 | R5: =Q5*G17 -> 307692.31 | S5: 8 | T5: =S5 -> 8 | U5: =T5*G17 -> 307692.31 | V5: 8 | W5: =V5 -> 8 | X5: =W5*G17 -> 307692.31
C6: FOH | D6: 15 | E6: =D6+D7 -> 34 | F6: =E6*G21 -> 714000 | G6: 15 | H6: =G6+G7 -> 34 | I6: =H6*G21 -> 714000 | J6: 15 | K6: =J6+J7 -> 34 | L6: =K6*G21 -> 714000 | M6: 15 | N6: =M6+M7 -> 34 | O6: =N6*G21 -> 714000 | P6: 19 | Q6: =P6+P7 -> 39 | R6: =Q6*G21 -> 819000 | S6: 35 | T6: =S6+S7 -> 70 | U6: =T6*G21 -> 1470000 | V6: 35 | W6: =V6+V7 -> 70 | X6: =W6*G21 -> 1470000
C7: BOH | D7: 19 | G7: 19 | J7: 19 | M7: 19 | P7: 20 | S7: 35 | V7: 35
B9: Afternoon | C9: Mngt | D9: 8 | E9: =D9 -> 8 | F9: =E9*G17 -> 307692.31 | G9: 8 | H9: =G9 -> 8 | I9: =H9*G17 -> 307692.31 | J9: 16 | K9: =J9 -> 16 | L9: =K9*G17 -> 615384.62 | M9: 8 | N9: =M9 -> 8 | O9: =N9*G17 -> 307692.31 | P9: 8 | Q9: =P9 -> 8 | R9: =Q9*G17 -> 307692.31 | S9: 16 | T9: =S9 -> 16 | U9: =T9*G17 -> 615384.62 | V9: 16 | W9: =V9 -> 16 | X9: =W9*G17 -> 615384.62
C10: FOH | D10: 19 | E10: =D10+D11 -> 39 | F10: =E10*G21 -> 819000 | G10: 19 | H10: =G10+G11 -> 39 | I10: =H10*G21 -> 819000 | J10: 19 | K10: =J10+J11 -> 39 | L10: =K10*G21 -> 819000 | M10: 19 | N10: =M10+M11 -> 39 | O10: =N10*G21 -> 819000 | P10: 19 | Q10: =P10+P11 -> 44 | R10: =Q10*G21 -> 924000 | S10: 35 | T10: =S10+S11 -> 70 | U10: =T10*G21 -> 1470000 | V10: 35 | W10: =V10+V11 -> 70 | X10: =W10*G21 -> 1470000
C11: BOH | D11: 20 | G11: 20 | J11: 20 | M11: 20 | P11: 25 | S11: 35 | V11: 35
B12: Total | E12: =E5+E6+E9+E10 -> 89 | F12: =F5+F6+F9+F10 -> 2148384.6 | H12: =H5+H6+H9+H10 -> 89 | I12: =I5+I6+I9+I10 -> 2148384.6 | K12: =K5+K6+K9+K10 -> 97 | L12: =L5+L6+L9+L10 -> 2456076.9 | N12: =N5+N6+N9+N10 -> 89 | O12: =O5+O6+O9+O10 -> 2148384.6 | Q12: =Q5+Q6+Q9+Q10 -> 99 | R12: =R5+R6+R9+R10 -> 2358384.6 | T12: =T5+T6+T9+T10 -> 164 | U12: =U5+U6+U9+U10 -> 3863076.9 | W12: =W5+W6+W9+W10 -> 164 | X12: =X5+X6+X9+X10 -> 3863076.9
C14: Lương | E14: Lương trung bình Mngt | F14: Lương Mngt /ngày | G14: Lương/giờ
B15: RGM | C15: 12000000
B16: SL | C16: 6000000
B17: SL | C17: 6000000 | E17: =AVERAGE(C15:C17) -> 8000000 | F17: =E17/26 -> 307692.31 | G17: =F17/8 -> 38461.538
B19: 3* | C19: 22000
B20: 2* | C20: 21000
B21: 1* | C21: 20000 | G21: =AVERAGE(C19:C21) -> 21000
A23: Sale forcasting /Week | C23: =SUM(C25:C31) -> 159000000
B25: Mon | C25: 14000000
B26: Tue | C26: 15000000
B27: Wed | C27: 17000000
B28: Thu | C28: 15000000
B29: Fri | C29: 18000000
B30: Sat | C30: 40000000
B31: Sun | C31: 40000000

Sheet Routine task
A1: Position / Responsibilities | B1: tasks | C1: frequency | D1: TIME | E1: RGM | F1: MODs | G1: BOH TMs | H1: CSR | I1: FOH TMs | J1: Rider | K1: start_time | L1: time_out | M1: duration | N1: end_time | O1: 0.25 | P1: =O1+1/48 -> 0.27083333 | Q1: =P1+1/48 -> 0.29166667 | R1: =Q1+1/48 -> 0.3125 | S1: =R1+1/48 -> 0.33333333 | T1: =S1+1/48 -> 0.35416667 | U1: =T1+1/48 -> 0.375 | V1: =U1+1/48 -> 0.39583333 | W1: =V1+1/48 -> 0.41666667 | ... AY1: =AX1+1/48 -> 1 | BB1: Total Minutes | BC1: Total Hours | BD1: Total Minutes | BE1: Total Minutes | BF1: Total Minutes | BG1: Total Minutes | BH1: Total Minutes | BI1: Total Minutes | BJ1: Total Minutes | BK1: Total Minutes | BL1: Total Minutes | BM1: Total Minutes | BN1: Total Minutes | BO1: Total Minutes | BP1: Total Minutes | BQ1: Total Minutes | BR1: Total Minutes | BS1: Total Minutes | BT1: Total Minutes | BU1: Total Minutes | BV1: Total Minutes | BW1: Total Minutes | BX1: Total Minutes | BY1: Total Minutes | BZ1: Total Minutes | CA1: Total Minutes | CB1: Total Minutes | CC1: Total Minutes | CD1: Total Minutes | CE1: Total Minutes | CF1: Total Minutes | CG1: Total Minutes | CH1: Total Minutes | CI1: Total Minutes | CJ1: Total Minutes | CK1: Total Minutes | CL1: Total Minutes | CM1: Total Minutes | CN1: Total Minutes | CO1: Total Minutes | CP1: Total Minutes | CQ1: Total Minutes | CR1: Total Minutes | CS1: Total Minutes | CT1: Total Minutes | CU1: Total Minutes | CV1: Total Minutes | CW1: Total Minutes | CX1: Total Minutes | CY1: Total Minutes | CZ1: Total Minutes | DA1: Total Minutes | DB1: Total Minutes | DC1: Total Minutes | DD1: Total Minutes | DE1: Total Minutes | DF1: Total Minutes | DG1: Total Minutes | DH1: Total Minutes | DI1: Total Minutes | DJ1: Total Minutes | DK1: Total Minutes | DL1: Total Minutes | DM1: Total Minutes | DN1: Total Minutes | DO1: Total Minutes | DP1: Total Minutes | DQ1: Total Minutes | DR1: Total Minutes | DS1: Total Minutes | DT1: Total Minutes | DU1: Total Minutes | DV1: Total Minutes | DW1: Total Minutes | DX1: Total Minutes | DY1: Total Minutes | DZ1: Total Minutes | EA1: Total Minutes | EB1: Total Minutes | EC1: Total Minutes | ED1: Total Minutes | EE1: Total Minutes | EF1: Total Minutes | EG1: Total Minutes | EH1: Total Minutes | EI1: Total Minutes | EJ1: Total Minutes | EK1: Total Minutes | EL1: Total Minutes | EM1: Total Minutes | EN1: Total Minutes | EO1: Total Minutes | EP1: Total Minutes | EQ1: Total Minutes | ER1: Total Minutes | ES1: Total Minutes | ET1: Total Minutes | EU1: Total Minutes | EV1: Total Minutes | EW1: Total Minutes | EX1: Total Minutes | EY1: Total Minutes | EZ1: Total Minutes | FA1: Total Minutes | FB1: Total Minutes | FC1: Total Minutes | FD1: Total Minutes | FE1: Total Minutes | FF1: Total Minutes | FG1: Total Minutes | FH1: Total Minutes | FI1: Total Minutes | FJ1: Total Minutes | FK1: Total Minutes | FL1: Total Minutes | FM1: Total Minutes | FN1: Total Minutes | FO1: Total Minutes | FP1: Total Minutes | FQ1: Total Minutes | FR1: Total Minutes | FS1: Total Minutes | FT1: Total Minutes | FU1: Total Minutes | FV1: Total Minutes | FW1: Total Minutes | FX1: Total Minutes | FY1: Total Minutes | FZ1: Total Minutes | GA1: Total Minutes | GB1: Total Minutes | GC1: Total Minutes | GD1: Total Minutes | GE1: Total Minutes | GF1: Total Minutes | GG1: Total Minutes | GH1: Total Minutes | GI1: Total Minutes | GJ1: Total Minutes | GK1: Total Minutes | GL1: Total Minutes | GM1: Total Minutes | GN1: Total Minutes | GO1: Total Minutes | GP1: Total Minutes | GQ1: Total Minutes | GR1: Total Minutes | GS1: Total Minutes | GT1: Total Minutes | GU1: Total Minutes | GV1: Total Minutes | GW1: Total Minutes | GX1: Total Minutes | GY1: Total Minutes | GZ1: Total Minutes | HA1: Total Minutes | HB1: Total Minutes | HC1: Total Minutes | HD1: Total Minutes | HE1: Total Minutes | HF1: Total Minutes | HG1: Total Minutes | HH1: Total Minutes | HI1: Total Minutes | HJ1: Total Minutes | HK1: Total Minutes | HL1: Total Minutes | HM1: Total Minutes | HN1: Total Minutes | HO1: Total Minutes | HP1: Total Minutes | HQ1: Total Minutes | HR1: Total Minutes | HS1: Total Minutes | HT1: Total Minutes | HU1: Total Minutes | HV1: Total Minutes | HW1: Total Minutes | HX1: Total Minutes | HY1: Total Minutes | HZ1: Total Minutes | IA1: Total Minutes | IB1: Total Minutes | IC1: Total Minutes | ID1: Total Minutes | IE1: Total Minutes | IF1: Total Minutes | IG1: Total Minutes | IH1: Total Minutes
A2: MOD | B2: RGS / OPENING SHIFT / CHECK-IN | C2: Daily | D2: Fixed | F2: 1 | J2: 1 | K2: 0.33333333 | L2: 0 | M2: =BB2 -> 5 | N2: 0.33680556 | S2: 5 | BB2: =SUM(O2:BA2) -> 5 | BC2: =BB2/60 -> 0.083333333
A3: BOH | B3: PAN DOUGH MAKING (morning) | C3: Daily | D3: Fixed | F3: 1 | J3: 1 | K3: 0.33333333 | L3: =K3-K2 -> 0 | M3: =BB3 -> 100 | N3: 0.40277778 | S3: 30 | T3: 50 | U3: 10 | V3: 5 | W3: 5 | BB3: =SUM(O3:BA3) -> 100 | BC3: =BB3/60 -> 1.6666667
A4: BOH | B4: OPENING CLEANING BOH | C4: Daily | D4: Fixed | F4: 1 | G4: 1 | J4: 1 | K4: 0.33680556 | L4: =(K4-K3)*48*30 -> 5 | M4: =BB4 -> 15 | N4: 0.34722222 | S4: 15 | BB4: =SUM(O4:BA4) -> 15 | BC4: =BB4/60 -> 0.25
A5: MOD | B5: ADMIN WORKS (morning) | C5: Daily | D5: Fixed | F5: 1 | K5: 0.34722222 | L5: =(K5-K4)*48*30 -> 15 | M5: =BB5 -> 10 | N5: 0.35416667 | S5: 10 | BB5: =SUM(O5:BA5) -> 10 | BC5: =BB5/60 -> 0.16666667
A6: MGNT | B6: Receive Vegieterian | C6: 3/week | D6: Flexible | E6: 1 | F6: 1 | G6: 1 | K6: 0.35416667 | L6: =(K6-K5)*48*30 -> 10 | M6: =BB6 -> 10 | N6: 0.36111111 | T6: 10 | BB6: =SUM(O6:BA6) -> 10 | BC6: =BB6/60 -> 0.16666667
A7: MOD | B7: Banking | C7: Daily | D7: Flexible | F7: 1 | H7: 1 | K7: 0.375 | L7: =(K7-K6)*48*30 -> 30 | M7: =BB7 -> 30 | N7: 0.39583333 | U7: 30 | BB7: =SUM(O7:BA7) -> 30 | BC7: =BB7/60 -> 0.5
A8: MOD | B8: Check Chiller/freezer/ FS Checklist (morning) | C8: Daily | D8: Flexible | F8: 1 | G8: 1 | K8: 0.375 | L8: =(K8-K7)*48*30 -> 0 | M8: =BB8 -> 10 | N8: 0.38194444 | U8: 10 | BB8: =SUM(O8:BA8) -> 10 | BC8: =BB8/60 -> 0.16666667
A9: FOH | B9: Cleaning glasses / Signage | C9: Daily | D9: Fixed | G9: 1 | H9: 1 | K9: 0.375 | L9: =(K9-K8)*48*30 -> 0 | M9: =BB9 -> 10 | N9: 0.38194444 | U9: 10 | BB9: =SUM(O9:BA9) -> 10 | BC9: =BB9/60 -> 0.16666667
A10: BOH | B10: MAKE /AUX TABLE SET-UP (morning) | D10: Fixed | F10: 1 | G10: 1 | K10: 0.37847222 | L10: =(K10-K9)*48*30 -> 5 | M10: =BB10 -> 50 | N10: 0.41319444 | U10: 25 | V10: 25 | BB10: =SUM(O10:BA10) -> 50 | BC10: =BB10/60 -> 0.83333333
A11: BOH | B11: CUT/BAR TABLE SET-UP (morning) | D11: Fixed | F11: 1 | J11: 1 | K11: 0.38541667 | L11: =(K11-K10)*48*30 -> 10 | M11: =BB11 -> 30 | N11: 0.40625 | U11: 15 | V11: 15 | BB11: =SUM(O11:BA11) -> 30 | BC11: =BB11/60 -> 0.5
A12: BOH | B12: Cutting of ingredients (morning) | C12: Daily | D12: Flexible | F12: 1 | G12: 1 | J12: 1 | K12: 0.38541667 | L12: =(K12-K11)*48*30 -> 0 | M12: =BB12 -> 35 | N12: 0.40972222 | U12: 15 | V12: 10 | X12: 10 | BB12: =SUM(O12:BA12) -> 35 | BC12: =BB12/60 -> 0.58333333
A13: ALL | B13: Rest room Clearning (morning) | C13: Daily | D13: Flexible | K13: 0.38888889 | L13: =(K13-K12)*48*30 -> 5 | M13: =BB13 -> 10 | N13: 0.39583333 | V13: 10 | BB13: =SUM(O13:BA13) -> 10 | BC13: =BB13/60 -> 0.16666667
A14: ALL | B14: DELIVERY MOTOR BIKES CHECKING | C14: Daily | D14: Flexible | F14: 1 | J14: 1 | K14: 0.39583333 | L14: =(K14-K13)*48*30 -> 10 | M14: =BB14 -> 20 | N14: 0.40972222 | V14: 15 | W14: 5 | BB14: =SUM(O14:BA14) -> 20 | BC14: =BB14/60 -> 0.33333333
A15: MOD | B15: Approved working hours on Cadena | C15: Daily | D15: Flexible | F15: 1 | K15: 0.39583333 | L15: =(K15-K14)*48*30 -> 0 | M15: =BB15 -> 5 | N15: 0.39930556 | V15: 5 | BB15: =SUM(O15:BA15) -> 5 | BC15: =BB15/60 -> 0.083333333
A16: MOD | B16: Follow up MRD Labels (morning) | C16: Daily | D16: Flexible | F16: 1 | G16: 1 | K16: 0.39583333 | L16: =(K16-K15)*48*30 -> 0 | M16: =BB16 -> 10 | N16: 0.38194444 | V16: 10 | BB16: =SUM(O16:BA16) -> 10 | BC16: =BB16/60 -> 0.16666667
A17: FOH | B17: Sweep / Mop Floor (morning) | C17: Daily | D17: Flexible | G17: 1 | H17: 1 | K17: 0.39583333 | L17: =(K17-K16)*48*30 -> 0 | M17: =BB17 -> 15 | N17: 0.40625 | U17: 15 | BB17: =SUM(O17:BA17) -> 15 | BC17: =BB17/60 -> 0.25
A18: FOH | B18: Cashier check cashflow before opening | C18: Daily | D18: Fixed | F18: 1 | H18: 1 | K18: 0.39583333 | L18: =(K18-K17)*48*30 -> 0 | M18: =BB18 -> 5 | N18: 0.39930556 | V18: 5 | BB18: =SUM(O18:BA18) -> 5 | BC18: =BB18/60 -> 0.083333333
A19: FOH | B19: Set-up table & Prepare dine-in condiments | C19: Daily | D19: Fixed | H19: 1 | K19: 0.40972222 | L19: =(K19-K18)*48*30 -> 20 | M19: =BB19 -> 20 | N19: 0.42361111 | V19: 10 | W19: 10 | BB19: =SUM(O19:BA19) -> 20 | BC19: =BB19/60 -> 0.33333333
A20: BOH | B20: R4R (Make. Aux, Bar) (morning) | C20: Daily | D20: Flexible | G20: 1 | K20: 0.41666667 | L20: =(K20-K19)*48*30 -> 10 | M20: =BB20 -> 40 | N20: 0.44444444 | W20: 30 | X20: 10 | BB20: =SUM(O20:BA20) -> 40 | BC20: =BB20/60 -> 0.66666667
A21: MGNT | B21: Breifing (morning) | C21: Daily | D21: Flexible | E21: 1 | F21: 1 | G21: 1 | H21: 1 | I21: 1 | J21: 1 | K21: 0.41666667 | L21: =(K21-K20)*48*30 -> 0 | M21: =BB21 -> 20 | N21: 0.43055556 | W21: 20 | BB21: =SUM(O21:BA21) -> 20 | BC21: =BB21/60 -> 0.33333333
A22: FOH | B22: Prepare Delievery & Take aways condiments | C22: Daily | D22: Fixed | H22: 1 | K22: 0.43402778 | L22: =(K22-K21)*48*30 -> 25 | M22: =BB22 -> 15 | N22: 0.44444444 | W22: 5 | X22: 10 | BB22: =SUM(O22:BA22) -> 15 | BC22: =BB22/60 -> 0.25
A23: ALL | B23: Fold Pizza Boxes | C23: Daily | D23: Flexible | E23: 1 | F23: 1 | G23: 1 | H23: 1 | I23: 1 | J23: 1 | K23: 0.4375 | L23: =(K23-K22)*48*30 -> 5 | M23: =BB23 -> 10 | N23: 0.44444444 | X23: 10 | BB23: =SUM(O23:BA23) -> 10 | BC23: =BB23/60 -> 0.16666667
A24: BOH | B24: Dish washing (morning) | C24: Daily | D24: Flexible | F24: 1 | G24: 1 | H24: 1 | I24: 1 | J24: 1 | K24: 0.55555556 | L24: =(K24-K23)*48*30 -> 170 | M24: =BB24 -> 60 | N24: 0.59722222 | AC24: 10 | AD24: 30 | AE24: 20 | BB24: =SUM(O24:BA24) -> 60 | BC24: =BB24/60 -> 1
A25: FOH | B25: Dry up culteries, cups and plates (afternoon) | C25: Daily | D25: Flexible | G25: 1 | H25: 1 | I25: 1 | J25: 1 | K25: 0.55555556 | L25: =(K25-K24)*48*30 -> 0 | M25: =BB25 -> 15 | N25: 0.56597222 | AC25: 10 | AD25: 5 | BB25: =SUM(O25:BA25) -> 15 | BC25: =BB25/60 -> 0.25
A26: FOH | B26: Fill culteries, cups and plates (afternoon) | C26: Daily | D26: Flexible | G26: 1 | H26: 1 | I26: 1 | J26: 1 | K26: 0.56597222 | L26: =(K26-K25)*48*30 -> 15 | M26: =BB26 -> 10 | N26: 0.57986111 | AE26: 10 | BB26: =SUM(O26:BA26) -> 10 | BC26: =BB26/60 -> 0.16666667
A27: ALL | B27: Rest room Clearning (after lunch) | C27: Daily | D27: Flexible | K27: 0.58333333 | L27: =(K27-K26)*48*30 -> 25 | M27: =BB27 -> 10 | N27: 0.59027778 | AF27: 10 | BB27: =SUM(O27:BA27) -> 10 | BC27: =BB27/60 -> 0.16666667
A28: BOH | B28: Cutting of ingredients (afternoon) | C28: Daily | D28: Flexible | F28: 1 | G28: 1 | J28: 1 | K28: 0.60416667 | L28: =(K28-K27)*48*30 -> 30 | M28: =BB28 -> 70 | N28: 0.65277778 | AF28: 30 | AG28: 10 | AI28: 10 | AJ28: 20 | BB28: =SUM(O28:BA28) -> 70 | BC28: =BB28/60 -> 1.1666667
A29: FOH | B29: Sweep / Mop Floor (afternoon) | C29: Daily | D29: Flexible | G29: 1 | H29: 1 | K29: 0.60416667 | L29: =(K29-K28)*48*30 -> 0 | M29: =BB29 -> 15 | N29: 0.61458333 | AF29: 15 | BB29: =SUM(O29:BA29) -> 15 | BC29: =BB29/60 -> 0.25
A30: FOH | B30: Prepare Delievery & Take aways condiments | C30: Daily | D30: Fixed | H30: 1 | K30: 0.61805556 | L30: =(K30-K29)*48*30 -> 20 | M30: =BB30 -> 25 | N30: 0.64583333 | AF30: 10 | AG30: 15 | BB30: =SUM(O30:BA30) -> 25 | BC30: =BB30/60 -> 0.41666667
A31: BOH | B31: Make Soup and Sauces | C31: Daily | D31: Flexible | F31: 1 | G31: 1 | K31: 0.625 | L31: =(K31-K30)*48*30 -> 10 | M31: =BB31 -> 30 | N31: 0.64583333 | AG31: 30 | BB31: =SUM(O31:BA31) -> 30 | BC31: =BB31/60 -> 0.5
A32: BOH | B32: Prepare Appertizer | C32: Daily | D32: Flexible | F32: 1 | G32: 1 | K32: 0.625 | L32: =(K32-K31)*48*30 -> 0 | M32: =BB32 -> 10 | N32: 0.63194444 | AG32: 10 | BB32: =SUM(O32:BA32) -> 10 | BC32: =BB32/60 -> 0.16666667
A33: BOH | B33: Frozen foods Defrosting | C33: Daily | D33: Flexible | F33: 1 | K33: 0.625 | L33: =(K33-K32)*48*30 -> 0 | M33: =BB33 -> 5 | N33: 0.62847222 | AG33: 5 | BB33: =SUM(O33:BA33) -> 5 | BC33: =BB33/60 -> 0.083333333
A34: MOD | B34: ADMIN WORKS (afternoon) | C34: Daily | D34: Fixed | F34: 1 | K34: 0.64583333 | L34: =(K34-K33)*48*30 -> 30 | M34: =BB34 -> 15 | N34: 0.35416667 | AH34: 15 | BB34: =SUM(O34:BA34) -> 15 | BC34: =BB34/60 -> 0.25
A35: BOH | B35: PAND DOUGH MAKING (afternoon) | C35: Daily | D35: Fixed | F35: 1 | J35: 1 | K35: 0.64583333 | L35: =(K35-K34)*48*30 -> 0 | M35: =BB35 -> 50 | N35: 0.68055556 | AH35: 50 | BB35: =SUM(O35:BA35) -> 50 | BC35: =BB35/60 -> 0.83333333
A36: MGNT | B36: Order Vegieterian | C36: 3/week | D36: Flexible | E36: 1 | F36: 1 | K36: 0.64583333 | L36: =(K36-K35)*48*30 -> 0 | M36: =BB36 -> 5 | N36: 0.64930556 | AH36: 5 | BB36: =SUM(O36:BA36) -> 5 | BC36: =BB36/60 -> 0.083333333
A37: BOH | B37: Prepare Spaghetti & Rice | C37: Daily | D37: Flexible | F37: 1 | G37: 1 | K37: 0.66666667 | L37: =(K37-K36)*48*30 -> 30 | M37: =BB37 -> 20 | N37: 0.68055556 | AI37: 20 | BB37: =SUM(O37:BA37) -> 20 | BC37: =BB37/60 -> 0.33333333
A38: BOH | B38: Prepare HT Dough | C38: 2-3/Week | D38: Flexible | G38: 1 | K38: 0.66666667 | L38: =(K38-K37)*48*30 -> 0 | M38: =BB38 -> 30 | N38: 0.6875 | AI38: 30 | BB38: =SUM(O38:BA38) -> 30 | BC38: =BB38/60 -> 0.5
A39: MOD | B39: Check Chiller/freezer/ FS Checklist (afternoon) | C39: Daily | D39: Flexible | F39: 1 | G39: 1 | K39: 0.66666667 | L39: =(K39-K38)*48*30 -> 0 | M39: =BB39 -> 5 | N39: 0.67013889 | AI39: 5 | BB39: =SUM(O39:BA39) -> 5 | BC39: =BB39/60 -> 0.083333333
A40: MOD | B40: Follow up MRD Labels (afternoon) | C40: Daily | D40: Flexible | F40: 1 | G40: 1 | K40: 0.66666667 | L40: =(K40-K39)*48*30 -> 0 | M40: =BB40 -> 5 | N40: 0.67013889 | AI40: 5 | BB40: =SUM(O40:BA40) -> 5 | BC40: =BB40/60 -> 0.083333333
A41: BOH | B41: Dish washing (afternoon) | C41: Daily | D41: Flexible | F41: 1 | G41: 1 | H41: 1 | I41: 1 | J41: 1 | K41: 0.66666667 | L41: =(K41-K40)*48*30 -> 0 | M41: =BB41 -> 30 | N41: 0.6875 | AJ41: 30 | BB41: =SUM(O41:BA41) -> 30 | BC41: =BB41/60 -> 0.5
A42: ALL | B42: Fold Pizza Boxes | C42: Daily | D42: Flexible | E42: 1 | F42: 1 | G42: 1 | H42: 1 | I42: 1 | J42: 1 | K42: 0.66666667 | L42: =(K42-K41)*48*30 -> 0 | M42: =BB42 -> 20 | N42: 0.68055556 | AH42: 20 | BB42: =SUM(O42:BA42) -> 20 | BC42: =BB42/60 -> 0.33333333
A43: BOH | B43: Prepare T&C Dough | C43: 2-3/Week | D43: Flexible | G43: 1 | K43: 0.6875 | L43: =(K43-K42)*48*30 -> 30 | M43: =BB43 -> 20 | N43: 0.70138889 | AJ43: 20 | BB43: =SUM(O43:BA43) -> 20 | BC43: =BB43/60 -> 0.33333333
A44: BOH | B44: MAKE /AUX TABLE SET-UP (afternoon) | D44: Fixed | F44: 1 | G44: 1 | K44: 0.70833333 | L44: =(K44-K43)*48*30 -> 30 | M44: =BB44 -> 35 | N44: 0.73263889 | AK44: 20 | AL44: 15 | BB44: =SUM(O44:BA44) -> 35 | BC44: =BB44/60 -> 0.58333333
A45: BOH | B45: CUT/BAR TABLE SET-UP (afternoon) | D45: Fixed | F45: 1 | J45: 1 | K45: 0.70833333 | L45: =(K45-K44)*48*30 -> 0 | M45: =BB45 -> 35 | N45: 0.73263889 | AK45: 20 | AL45: 15 | BB45: =SUM(O45:BA45) -> 35 | BC45: =BB45/60 -> 0.58333333
A46: BOH | B46: R4R (Make. Aux, Bar) (afternoon) | C46: Daily | D46: Flexible | G46: 1 | K46: 0.70833333 | L46: =(K46-K45)*48*30 -> 0 | M46: =BB46 -> 30 | N46: 0.72916667 | AK46: 15 | AL46: 15 | BB46: =SUM(O46:BA46) -> 30 | BC46: =BB46/60 -> 0.5
A47: MGNT | B47: Breifing (afternoon) | C47: Daily | D47: Flexible | E47: 1 | F47: 1 | G47: 1 | H47: 1 | I47: 1 | J47: 1 | K47: 0.70833333 | L47: =(K47-K46)*48*30 -> 0 | M47: =BB47 -> 20 | N47: 0.72222222 | AK47: 20 | BB47: =SUM(O47:BA47) -> 20 | BC47: =BB47/60 -> 0.33333333
A48: ALL | B48: Rest room Clearning (after tea) | C48: Daily | D48: Flexible | K48: 0.72916667 | L48: =(K48-K47)*48*30 -> 30 | M48: =BB48 -> 10 | N48: 0.73611111 | AL48: 10 | BB48: =SUM(O48:BA48) -> 10 | BC48: =BB48/60 -> 0.16666667
A49: BOH | B49: Dish washing (evening) | C49: Daily | D49: Flexible | F49: 1 | G49: 1 | H49: 1 | I49: 1 | J49: 1 | K49: 0.84027778 | L49: =(K49-K48)*48*30 -> 160 | M49: =BB49 -> 70 | N49: 0.88888889 | AQ49: 20 | AR49: 30 | AS49: 20 | BB49: =SUM(O49:BA49) -> 70 | BC49: =BB49/60 -> 1.1666667
A50: FOH | B50: Dry up culteries, cups and plates (evening) | C50: Daily | D50: Flexible | G50: 1 | H50: 1 | I50: 1 | J50: 1 | K50: 0.84375 | L50: =(K50-K49)*48*30 -> 5 | M50: =BB50 -> 25 | N50: 0.86111111 | AR50: 15 | AS50: 10 | BB50: =SUM(O50:BA50) -> 25 | BC50: =BB50/60 -> 0.41666667
A51: FOH | B51: Fill culteries, cups and plates (evening) | C51: Daily | D51: Flexible | G51: 1 | H51: 1 | I51: 1 | J51: 1 | K51: 0.86111111 | L51: =(K51-K50)*48*30 -> 25 | M51: =BB51 -> 10 | N51: 0.86805556 | AS51: 10 | BB51: =SUM(O51:BA51) -> 10 | BC51: =BB51/60 -> 0.16666667
A52: ALL | B52: Rest room Clearning (after dinner) | C52: Daily | D52: Flexible | K52: 0.89583333 | L52: =(K52-K51)*48*30 -> 50 | M52: =BB52 -> 10 | N52: 0.90277778 | AT52: 10 | BB52: =SUM(O52:BA52) -> 10 | BC52: =BB52/60 -> 0.16666667
A53: FOH | B53: Sweep / Mop Floor (evening) | C53: Daily | D53: Flexible | G53: 1 | H53: 1 | K53: 0.89583333 | L53: =(K53-K52)*48*30 -> 0 | M53: =BB53 -> 15 | N53: 0.90625 | AT53: 15 | BB53: =SUM(O53:BA53) -> 15 | BC53: =BB53/60 -> 0.25
A54: BOH | B54: Pans Pre-Oil for the next morning | C54: Daily | D54: Flexible | F54: 1 | G54: 1 | J54: 1 | K54: 0.89583333 | L54: =(K54-K53)*48*30 -> 0 | M54: =BB54 -> 30 | N54: 0.91666667 | AT54: 30 | BB54: =SUM(O54:BA54) -> 30 | BC54: =BB54/60 -> 0.5
A55: FOH | B55: Closing FOH Clearning (Clean up dust，clean Station counter，clean tables, sofa) | C55: Daily | D55: Flexible | F55: 1 | H55: 1 | I55: 1 | K55: 0.89583333 | L55: =(K55-K54)*48*30 -> 0 | M55: =BB55 -> 15 | N55: 0.90625 | AT55: 15 | BB55: =SUM(O55:BA55) -> 15 | BC55: =BB55/60 -> 0.25
A56: MGNT | B56: Finalize sales and cash，check credit card bills and total transaction bills，check tips | C56: Daily | D56: Flexible | E56: 1 | F56: 1 | H56: 1 | K56: 0.89583333 | L56: =(K56-K55)*48*30 -> 0 | M56: =BB56 -> 15 | N56: 0.90625 | AT56: 15 | BB56: =SUM(O56:BA56) -> 15 | BC56: =BB56/60 -> 0.25
A57: FOH | B57: Clean service trays, fill up sauces botles | D57: Flexible | F57: 1 | G57: 1 | H57: 1 | I57: 1 | J57: 1 | K57: 0.90625 | L57: =(K57-K56)*48*30 -> 15 | M57: =BB57 -> 10 | N57: 0.91319444 | AT57: 10 | BB57: =SUM(O57:BA57) -> 10 | BC57: =BB57/60 -> 0.16666667
A58: BOH | B58: Cooking utensils and Oven cleaning | C58: Daily | D58: Flexible | E58: 1 | F58: 1 | G58: 1 | J58: 1 | K58: 0.91666667 | L58: =(K58-K57)*48*30 -> 15 | M58: =BB58 -> 20 | N58: 0.93055556 | AU58: 20 | BB58: =SUM(O58:BA58) -> 20 | BC58: =BB58/60 -> 0.33333333
A59: BOH | B59: Closing BOH Cleaning (Oven, Fryers,… ) | C59: Daily | D59: Flexible | F59: 1 | G59: 1 | J59: 1 | K59: 0.91666667 | L59: =(K59-K58)*48*30 -> 0 | M59: =BB59 -> 50 | N59: 0.95138889 | AU59: 30 | AV59: 20 | BB59: =SUM(O59:BA59) -> 50 | BC59: =BB59/60 -> 0.83333333
A60: BOH | B60: Clean Deep Fryer | C60: Daily | D60: Flexible | F60: 1 | G60: 1 | J60: 1 | K60: 0.93055556 | L60: =(K60-K59)*48*30 -> 20 | M60: =BB60 -> 10 | N60: 0.9375 | AU60: 10 | BB60: =SUM(O60:BA60) -> 10 | BC60: =BB60/60 -> 0.16666667
A61: MOD | B61: ADMIN WORKS (evening) | C61: Daily | D61: Fixed | F61: 1 | K61: 0.9375 | L61: =(K61-K60)*48*30 -> 10 | M61: =BB61 -> 10 | N61: 0.94444444 | AV61: 10 | BB61: =SUM(O61:BA61) -> 10 | BC61: =BB61/60 -> 0.16666667
A62: MGNT | B62: Daily Report | C62: Daily | D62: Flexible | E62: 1 | F62: 1 | K62: 0.9375 | L62: =(K62-K61)*48*30 -> 0 | M62: =BB62 -> 15 | N62: 0.94791667 | AV62: 15 | BB62: =SUM(O62:BA62) -> 15 | BC62: =BB62/60 -> 0.25
A63: MGNT | B63: RGS / CLOSING SHIFT | C63: Daily | D63: Fixed | E63: 1 | F63: 1 | G63: 1 | H63: 1 | I63: 1 | J63: 1 | K63: 0.94791667 | L63: =(K63-K62)*48*30 -> 15 | M63: =BB63 -> 10 | N63: 0.95486111 | AV63: 10 | BB63: =SUM(O63:BA63) -> 10 | BC63: =BB63/60 -> 0.16666667

Sheet Daily task
A1: Type the title of this Excel model into this cell | J1: Sales mixed | L1: Trans. | M1: =SUM(M2:M4) -> 41 | N1: =I2/(SUM(M2:M4)) -> 243902.44
A2: Sheet "Activities input" | H2: Sales Forecast (maximize) | I2: 10000000 | J2: DI | K2: 0.3 | L2: =$I$2*K2 -> 3000000 | M2: =L2/N2 -> 15 | N2: 200000
A3: Update 100421 | H3: Baline working hours (minimize) | I3: =BQ66 -> 70.25 | J3: TA | K3: 0.4 | L3: =$I$2*K3 -> 4000000 | M3: =L3/N3 -> 16 | N3: 250000
H4: Productivity | I4: =I2/I3 -> 142348.75 | J4: DE | K4: 0.3 | L4: =$I$2*K4 -> 3000000 | M4: =L4/N4 -> 10 | N4: 300000 | Y4: 1 | Z4: 2 | AA4: 3 | AB4: 4
B5: Task List | I5: Human Resources Requirements | O5: PT/FT Responsibility | Q5: Driving Factor | R5: Frequency by Day | Y5: Frequency by Week | AC5: Time Slot（mins required for every time slot）
B6: Position / Responsibilities | C6: TASKS | D6: Training Requirement | E6: Frequency | F6: TIME | G6: THỜI GIAN | H6: GHI CHÚ | I6: RGM | J6: MODs | K6: BOH TMs | L6: CSR | M6: FOH TMs | N6: Dough/Rider | O6: FT | P6: PT | Q6: Driving of the required time | R6: Mondy | S6: Tuesday | T6: Wednesday | U6: Thursday | V6: Friday | W6: Saturday | X6: Sunday | Y6: Week 1 | Z6: Week 2 | AA6: Week 3 | AB6: Week 4 | AC6: 0.25 | AD6: =AC6+1/48 -> 0.27083333 | AE6: =AD6+1/48 -> 0.29166667 | AF6: =AE6+1/48 -> 0.3125 | AG6: =AF6+1/48 -> 0.33333333 | AH6: =AG6+1/48 -> 0.35416667 | AI6: =AH6+1/48 -> 0.375 | AJ6: =AI6+1/48 -> 0.39583333 | AK6: =AJ6+1/48 -> 0.41666667 | ... BM6: =BL6+1/48 -> 1 | BP6: Total Minutes | BQ6: Total Hours | BR6: Total Minutes | BS6: Total Minutes | BT6: Total Minutes | BU6: Total Minutes | BV6: Total Minutes | BW6: Total Minutes | BX6: Total Minutes | BY6: Total Minutes | BZ6: Total Minutes | CA6: Total Minutes | CB6: Total Minutes | CC6: Total Minutes | CD6: Total Minutes | CE6: Total Minutes | CF6: Total Minutes | CG6: Total Minutes | CH6: Total Minutes | CI6: Total Minutes | CJ6: Total Minutes | CK6: Total Minutes | CL6: Total Minutes | CM6: Total Minutes | CN6: Total Minutes | CO6: Total Minutes | CP6: Total Minutes | CQ6: Total Minutes | CR6: Total Minutes | CS6: Total Minutes | CT6: Total Minutes | CU6: Total Minutes | CV6: Total Minutes | CW6: Total Minutes | CX6: Total Minutes | CY6: Total Minutes | CZ6: Total Minutes | DA6: Total Minutes | DB6: Total Minutes | DC6: Total Minutes | DD6: Total Minutes | DE6: Total Minutes | DF6: Total Minutes | DG6: Total Minutes | DH6: Total Minutes | DI6: Total Minutes | DJ6: Total Minutes | DK6: Total Minutes | DL6: Total Minutes | DM6: Total Minutes | DN6: Total Minutes | DO6: Total Minutes | DP6: Total Minutes | DQ6: Total Minutes | DR6: Total Minutes | DS6: Total Minutes | DT6: Total Minutes | DU6: Total Minutes | DV6: Total Minutes | DW6: Total Minutes | DX6: Total Minutes | DY6: Total Minutes | DZ6: Total Minutes | EA6: Total Minutes | EB6: Total Minutes | EC6: Total Minutes | ED6: Total Minutes | EE6: Total Minutes | EF6: Total Minutes | EG6: Total Minutes | EH6: Total Minutes | EI6: Total Minutes | EJ6: Total Minutes | EK6: Total Minutes | EL6: Total Minutes | EM6: Total Minutes | EN6: Total Minutes | EO6: Total Minutes | EP6: Total Minutes | EQ6: Total Minutes | ER6: Total Minutes | ES6: Total Minutes | ET6: Total Minutes | EU6: Total Minutes | EV6: Total Minutes | EW6: Total Minutes | EX6: Total Minutes | EY6: Total Minutes | EZ6: Total Minutes | FA6: Total Minutes | FB6: Total Minutes | FC6: Total Minutes | FD6: Total Minutes | FE6: Total Minutes | FF6: Total Minutes | FG6: Total Minutes | FH6: Total Minutes | FI6: Total Minutes | FJ6: Total Minutes | FK6: Total Minutes | FL6: Total Minutes | FM6: Total Minutes | FN6: Total Minutes | FO6: Total Minutes | FP6: Total Minutes | FQ6: Total Minutes | FR6: Total Minutes | FS6: Total Minutes | FT6: Total Minutes | FU6: Total Minutes | FV6: Total Minutes | FW6: Total Minutes | FX6: Total Minutes | FY6: Total Minutes | FZ6: Total Minutes | GA6: Total Minutes | GB6: Total Minutes | GC6: Total Minutes | GD6: Total Minutes | GE6: Total Minutes | GF6: Total Minutes | GG6: Total Minutes | GH6: Total Minutes | GI6: Total Minutes | GJ6: Total Minutes | GK6: Total Minutes | GL6: Total Minutes | GM6: Total Minutes | GN6: Total Minutes | GO6: Total Minutes | GP6: Total Minutes | GQ6: Total Minutes | GR6: Total Minutes | GS6: Total Minutes | GT6: Total Minutes | GU6: Total Minutes | GV6: Total Minutes | GW6: Total Minutes | GX6: Total Minutes | GY6: Total Minutes | GZ6: Total Minutes | HA6: Total Minutes | HB6: Total Minutes | HC6: Total Minutes | HD6: Total Minutes | HE6: Total Minutes | HF6: Total Minutes | HG6: Total Minutes | HH6: Total Minutes | HI6: Total Minutes | HJ6: Total Minutes | HK6: Total Minutes | HL6: Total Minutes | HM6: Total Minutes | HN6: Total Minutes | HO6: Total Minutes | HP6: Total Minutes | HQ6: Total Minutes | HR6: Total Minutes | HS6: Total Minutes | HT6: Total Minutes | HU6: Total Minutes | HV6: Total Minutes | HW6: Total Minutes | HX6: Total Minutes | HY6: Total Minutes | HZ6: Total Minutes | IA6: Total Minutes | IB6: Total Minutes | IC6: Total Minutes | ID6: Total Minutes | IE6: Total Minutes | IF6: Total Minutes | IG6: Total Minutes | IH6: Total Minutes | II6: Total Minutes | IJ6: Total Minutes | IK6: Total Minutes | IL6: Total Minutes | IM6: Total Minutes | IN6: Total Minutes | IO6: Total Minutes | IP6: Total Minutes | IQ6: Total Minutes | IR6: Total Minutes | IS6: Total Minutes | IT6: Total Minutes | IU6: Total Minutes | IV6: Total Minutes
A7: 1 | B7: MOD | C7: RGS / OPENING SHIFT / CHECK-IN | D7: Specific | E7: Daily | F7: Fixed | G7: Morning | H7: Mở cửa cùng 1 nhân viên; thực hiện security & safety check | J7: x | N7: x | O7: x | P7: x | Q7: TC | R7: x | S7: x | T7: x | U7: x | V7: x | W7: x | X7: x | Y7: x | Z7: x | AA7: x | AB7: x | AG7: 5 | BP7: =SUM(AC7:BO7) -> 5 | BQ7: =BP7/60 -> 0.083333333
A8: 2 | B8: MOD | C8: ADMIN WORKS | D8: Specific | E8: Daily | F8: Fixed | G8: Morning | H8: Check mail, đọc logbook, kế hoạch chuẩn bị hàng hóa | J8: x | O8: x | P8: x | Q8: TC | R8: x | S8: x | T8: x | U8: x | V8: x | W8: x | X8: x | Y8: x | Z8: x | AA8: x | AB8: x | AG8: 10 | AV8: 15 | BJ8: 10 | BP8: =SUM(AC8:BO8) -> 35 | BQ8: =BP8/60 -> 0.58333333
A9: 3 | B9: BOH | C9: OPENING CLEANING BOH | D9: Basic | E9: Daily | F9: Fixed | G9: Morning | J9: x | K9: x | N9: x | O9: x | P9: x | Q9: TC | R9: x | S9: x | T9: x | U9: x | V9: x | W9: x | X9: x | Y9: x | Z9: x | AA9: x | AB9: x | AG9: 15 | BP9: =SUM(AC9:BO9) -> 15 | BQ9: =BP9/60 -> 0.25
A10: 4 | B10: BOH | C10: PAN DOUGH MAKING | D10: Specific | E10: Daily | F10: Fixed | G10: Morning/Afternoon | H10: 1. Ca sáng: 08.10 làm Dough với sự hỗ trợ của MOD. 8.10-8.35: 1/2 mẻ Pan; 8.35-9.00: 1/2 mẻ (1/4 Pan & 1/4 SCP); Sau khi hoàn thành, follow-up Dough theo quy trình đồng thời support bộ phận khác. 2. Ca chiều: Linh hoạt thời gian thực tế, làm bổ sung 1/2 mẻ Pan dough. | J10: x | N10: x | O10: x | P10: x | Q10: TC | R10: x | S10: x | T10: x | U10: x | V10: x | W10: x | X10: x | Y10: x | Z10: x | AA10: x | AB10: x | AG10: 30 | AH10: 50 | AI10: 10 | AJ10: 5 | AK10: 5 | AV10: 50 | BP10: =SUM(AC10:BO10) -> 150 | BQ10: =BP10/60 -> 2.5
A11: 5 | B11: BOH | C11: MAKE /AUX / CUT/BAR TABLE SET-UP | F11: Fixed | H11: 80% nguyên liệu đã được chuẩn bị từ ngày hôm trước | J11: x | K11: x | N11: x | AI11: 30 | AJ11: 45 | AY11: 20 | AZ11: 15 | BP11: =SUM(AC11:BO11) -> 110 | BQ11: =BP11/60 -> 1.8333333
A12: 6 | B12: BOH | C12: Cutting of ingredients | D12: Basic | E12: Daily | F12: Flexible | G12: Morning/Afternoon | H12: - Ca sáng cắt thái chuẩn bị 1 số nguyên liệu AC: Hành, ớt qua lò, Bacon qua lò, Đồ rau củ cho cơm trong menu 39k, Cheesy pop, … - Ca chiều cắt thái đồ chuẩn bị cho ngày hôm sau (có thể fix thời gian theo preplan) | J12: x | K12: x | N12: x | O12: x | P12: x | Q12: TC | R12: x | S12: x | T12: x | U12: x | V12: x | W12: x | X12: x | Y12: x | Z12: x | AA12: x | AB12: x | AI12: 15 | AJ12: 10 | AL12: 10 | AT12: 30 | AU12: 10 | AW12: 10 | AX12: 20 | BP12: =SUM(AC12:BO12) -> 105 | BQ12: =BP12/60 -> 1.75
A13: 7 | B13: BOH | C13: Make Soup and Sauces | D13: Basic | E13: Daily | F13: Flexible | G13: Morning/Afternoon | J13: x | K13: x | AU13: 30 | BP13: =SUM(AC13:BO13) -> 30 | BQ13: =BP13/60 -> 0.5
A14: 8 | B14: BOH | C14: Prepare Spaghetti & Rice | D14: Basic | E14: Daily | F14: Flexible | G14: Morning/Afternoon | J14: x | K14: x | AW14: 20 | BP14: =SUM(AC14:BO14) -> 20 | BQ14: =BP14/60 -> 0.33333333
A15: 9 | B15: BOH | C15: Prepare Appertizer | D15: Basic | E15: Daily | F15: Flexible | G15: Morning/Afternoon | J15: x | K15: x | AU15: 10 | BP15: =SUM(AC15:BO15) -> 10 | BQ15: =BP15/60 -> 0.16666667
A16: 10 | B16: BOH | C16: Frozen foods Defrosting | D16: Specific/Basic | E16: Daily | F16: Flexible | J16: x | AU16: 5 | BP16: =SUM(AC16:BO16) -> 5 | BQ16: =BP16/60 -> 0.083333333
A17: 11 | B17: BOH | C17: Prepare T&C Dough | D17: Specific | E17: 2-3/Week | F17: Flexible | G17: Afternoon | H17: Thời gian làm TnC Dough 15'/0.5 batch trong 10' (shelflife 8h); thời gian cán dough vào chảo trong 30' (shelflife 60h); khoảng 2-3 lần/tuần. | K17: x | O17: x | P17: x | Q17: TC | R17: x | S17: x | T17: x | U17: x | V17: x | W17: x | X17: x | Y17: x | Z17: x | AA17: x | AB17: x | AX17: 20 | BP17: =SUM(AC17:BO17) -> 20 | BQ17: =BP17/60 -> 0.33333333
A18: 12 | B18: BOH | C18: Prepare HT Dough | D18: Specific | E18: 2-3/Week | F18: Flexible | G18: Afternoon | H18: Thời gian làm HT Dough 30'/0.5 batch, thời gian thực hiện linh hoạt theo (selflife 40h); khoảng 2-3 lần/tuần. | K18: x | O18: x | P18: x | Q18: TC | R18: x | S18: x | T18: x | U18: x | V18: x | W18: x | X18: x | Y18: x | Z18: x | AA18: x | AB18: x | AW18: 30 | BP18: =SUM(AC18:BO18) -> 30 | BQ18: =BP18/60 -> 0.5
A19: 13 | B19: BOH | C19: R4R (Make. Aux, Bar) | D19: Basic | E19: Daily | F19: Flexible | G19: Morning/Afternoon | H19: Cuộn viền dough (2 CCP, 1 CBR, 1 half&half, 2 viền LTO, Pre Top, Pre sauce, … trước giờ cao điểm | K19: x | O19: x | P19: x | Q19: TC | R19: x | S19: x | T19: x | U19: x | V19: x | W19: x | X19: x | Y19: x | Z19: x | AA19: x | AB19: x | AK19: 30 | AL19: 10 | AY19: 15 | AZ19: 15 | BP19: =SUM(AC19:BO19) -> 70 | BQ19: =BP19/60 -> 1.1666667
A20: 14 | B20: ALL | C20: DELIVERY MOTOR BIKES CHECKING | D20: Specific/Basic | E20: Daily | F20: Flexible | G20: Morning | H20: Kiểm tra xe giao hàng theo check list trước giờ hoạt động | J20: X | N20: X | AJ20: 15 | AK20: 5 | BP20: =SUM(AC20:BO20) -> 20 | BQ20: =BP20/60 -> 0.33333333
A21: 15 | B21: MOD | C21: Banking | D21: Specific | E21: Daily | F21: Flexible | G21: Morning | H21: 1 quản lý và 1 nhân viên CSR đi banking di chuyển ~20p mỗi chiều) => đi trước 10h | J21: x | L21: X | O21: x | P21: x | Q21: TC | R21: x | S21: x | T21: x | U21: x | V21: x | W21: x | X21: x | Y21: x | Z21: x | AA21: x | AB21: x | AI21: 30 | BP21: =SUM(AC21:BO21) -> 30 | BQ21: =BP21/60 -> 0.5
A22: 16 | B22: MOD | C22: Approved working hours on Cadena | D22: Specific | E22: Daily | F22: Flexible | G22: Morning | H22: Hoàn thành trước 10h sáng | J22: x | O22: x | P22: x | Q22: TC | R22: x | S22: x | T22: x | U22: x | V22: x | W22: x | X22: x | Y22: x | Z22: x | AA22: x | AB22: x | AJ22: 5 | BP22: =SUM(AC22:BO22) -> 5 | BQ22: =BP22/60 -> 0.083333333
A23: 17 | B23: MOD | C23: Check Chiller/freezer/ FS Checklist | D23: Specific | E23: Daily | F23: Flexible | G23: Morning/Afternoon | H23: MIC Kiểm tra nhiệt độ các tủ và ghi chép sổ trước 10h sáng | J23: x | K23: x | O23: x | P23: x | Q23: TC | R23: x | S23: x | T23: x | U23: x | V23: x | W23: x | X23: x | Y23: x | Z23: x | AA23: x | AB23: x | AI23: 10 | AW23: 5 | BP23: =SUM(AC23:BO23) -> 15 | BQ23: =BP23/60 -> 0.25
A24: 18 | B24: MOD | C24: Follow up MRD Labels | D24: Specific | E24: Daily | F24: Flexible | G24: Morning | H24: MIC Kiểm tra MRD các sản phẩm trong các tủ trước 10h sáng | J24: x | K24: x | O24: x | P24: x | Q24: Fixed | R24: x | S24: x | T24: x | U24: x | V24: x | W24: x | X24: x | Y24: x | Z24: x | AA24: x | AB24: x | AJ24: 10 | AW24: 5 | BP24: =SUM(AC24:BO24) -> 15 | BQ24: =BP24/60 -> 0.25
A25: 19 | B25: BOH | C25: Make Station | D25: Specific | E25: Daily | G25: Morning/Afternoon | H25: Trong giờ cao điểm cầ 1 nhân viên đứng độc lập 1 mình, giờ thấp điểm in-charge khu vực BOH. | K25: x | O25: x | P25: x | Q25: TC | R25: x | S25: x | T25: x | U25: x | V25: x | W25: x | X25: x | Y25: x | Z25: x | AA25: x | AB25: x | AK25: 10 | AL25: 10 | AM25: 15 | AN25: 30 | AO25: 30 | AP25: 30 | AQ25: 20 | AR25: 10 | AS25: 10 | AT25: 10 | AU25: 10 | AV25: 10 | AW25: 15 | AX25: 15 | AY25: 15 | AZ25: 30 | BA25: 30 | BB25: 30 | BC25: 30 | BD25: 30 | BE25: 30 | BF25: 20 | BG25: 10 | BH25: 10 | BP25: =SUM(AC25:BO25) -> 460 | BQ25: =BP25/60 -> 7.6666667
A26: 20 | B26: BOH | C26: Aux Station | D26: Specific | E26: Daily | G26: Morning/Afternoon | H26: Kết hợp nhân viên quầy Aux | K26: x | O26: x | P26: x | Q26: TC | R26: x | S26: x | T26: x | U26: x | V26: x | W26: x | X26: x | Y26: x | Z26: x | AA26: x | AB26: x | AK26: 5 | AL26: 10 | AM26: 15 | AN26: 15 | AO26: 15 | AP26: 15 | AQ26: 10 | AR26: 10 | AS26: 10 | AY26: 5 | AZ26: 15 | BA26: 30 | BB26: 30 | BC26: 30 | BD26: 30 | BE26: 30 | BF26: 20 | BG26: 10 | BH26: 5 | BP26: =SUM(AC26:BO26) -> 310 | BQ26: =BP26/60 -> 5.1666667
A27: 21 | B27: BOH | C27: Cut Station | D27: Specific | E27: Daily | G27: Morning/Afternoon | H27: Các quầy chia sẻ công việc của vị trí này | K27: x | O27: x | P27: x | Q27: TC | R27: x | S27: x | T27: x | U27: x | V27: x | W27: x | X27: x | Y27: x | Z27: x | AA27: x | AB27: x | AK27: 5 | AL27: 5 | AM27: 10 | AN27: 15 | AO27: 15 | AP27: 15 | AQ27: 15 | AR27: 5 | AS27: 5 | AT27: 5 | AU27: 5 | AV27: 5 | AW27: 5 | AX27: 5 | AY27: 5 | AZ27: 10 | BA27: 15 | BB27: 15 | BC27: 15 | BD27: 15 | BE27: 15 | BF27: 10 | BG27: 10 | BH27: 5 | BP27: =SUM(AC27:BO27) -> 230 | BQ27: =BP27/60 -> 3.8333333
A28: 22 | B28: BOH | C28: Bar - Drinks | D28: Specific | E28: Daily | G28: Morning/Afternoon | H28: Các quầy chia sẻ công việc của vị trí này | K28: x | O28: x | P28: x | Q28: TC | R28: x | S28: x | T28: x | U28: x | V28: x | W28: x | X28: x | Y28: x | Z28: x | AA28: x | AB28: x | AK28: 5 | AL28: 5 | AM28: 5 | AN28: 5 | AO28: 10 | AP28: 10 | AQ28: 10 | AY28: 5 | AZ28: 5 | BA28: 15 | BB28: 15 | BC28: 15 | BD28: 15 | BE28: 15 | BF28: 15 | BP28: =SUM(AC28:BO28) -> 150 | BQ28: =BP28/60 -> 2.5
A29: 23 | B29: BOH | C29: Pack Delivery and Take out Order, Dispatch | D29: Specific | E29: Daily | G29: Morning/Afternoon | H29: Trong giờ cao điểm, Leader BOH sẽ đảm nhiệm vị trí này để kiểm soát chất lượng và thời gian | L29: x | O29: x | P29: x | Q29: TC | R29: x | S29: x | T29: x | U29: x | V29: x | W29: x | X29: x | Y29: x | Z29: x | AA29: x | AB29: x | AM29: 5 | AN29: 5 | AO29: 10 | AP29: 10 | AQ29: 10 | BA29: 15 | BB29: 15 | BC29: 15 | BD29: 15 | BE29: 10 | BF29: 10 | BP29: =SUM(AC29:BO29) -> 120 | BQ29: =BP29/60 -> 2
A30: 24 | B30: BOH | C30: Dish washing | D30: Basic | E30: Daily | F30: Flexible | G30: Morning/Afternoon | H30: Thời gian thấp điểm MOD phân công 1 nhân viên | J30: x | K30: x | L30: x | M30: x | N30: x | O30: x | P30: x | Q30: TC | R30: x | S30: x | T30: x | U30: x | V30: x | W30: x | X30: x | Y30: x | Z30: x | AA30: x | AB30: x | AQ30: 10 | AR30: 30 | AS30: 20 | AX30: 30 | BE30: 20 | BF30: 30 | BG30: 20 | BP30: =SUM(AC30:BO30) -> 160 | BQ30: =BP30/60 -> 2.6666667
A31: 25 | B31: ALL | C31: Rest room Clearning | D31: Basic | E31: Daily | F31: Flexible | G31: Morning/Afternoon | H31: Linh hoạt thời gian và PIC | AJ31: 10 | AT31: 10 | AZ31: 10 | BH31: 10
A32: 26 | B32: FOH | C32: OPENING CLEANING FOH | D32: Basic | E32: Daily | F32: Fixed | G32: Morning | N32: x | O32: x | P32: x | Q32: TC | R32: x | S32: x | T32: x | U32: x | V32: x | W32: x | X32: x | Y32: x | Z32: x | AA32: x | AB32: x | BP32: =SUM(AC32:BO32) -> 0 | BQ32: =BP32/60 -> 0
A33: 27 | B33: FOH | C33: Cleaning glasses / Signage | D33: Basic | E33: Daily | F33: Fixed | G33: Morning | H33: Nhân viên CSR sau khi đi bank với quản lý về sẽ vệ sinh kính từ 9h20 đến 9h40 | K33: x | L33: x | O33: x | P33: x | Q33: Store Area | R33: x | S33: x | T33: x | U33: x | V33: x | W33: x | X33: x | Y33: x | Z33: x | AA33: x | AB33: x | AI33: 10 | BP33: =SUM(AC33:BO33) -> 10 | BQ33: =BP33/60 -> 0.16666667
A34: 28 | B34: FOH | C34: Sweep / Mop Floor | D34: Basic | E34: Daily | F34: Flexible | G34: Morning/Afternoon | H34: Quét và lau sàn FOH đầu ca, giữa ca và đóng ca | K34: x | L34: x | O34: x | P34: x | Q34: Store Area | R34: x | S34: x | T34: x | U34: x | V34: x | W34: x | X34: x | Y34: x | Z34: x | AA34: x | AB34: x | AI34: 15 | AT34: 15 | BH34: 15 | BP34: =SUM(AC34:BO34) -> 45 | BQ34: =BP34/60 -> 0.75
A35: 29 | B35: FOH | C35: Cleaning tables, sofas, chairs,… | D35: Basic | E35: Daily | F35: Fixed | G35: Morning | H35: Nhân viên CSR sau khi đi bank với quản lý về sẽ vệ sinh kính từ 9h20 đến 9h40 | BP35: =SUM(AC35:BO35) -> 0 | BQ35: =BP35/60 -> 0
A36: 30 | B36: FOH | C36: Set-up table & Prepare dine-in condiments | D36: Basic | E36: Daily | F36: Fixed | G36: Morning | H36: Set-up theo khu vực riêng trước 10h sáng, các khu vực khác có thể hoàn thiện sau theo thực tế lượng khách buổi trưa. | L36: x | AJ36: 10 | AK36: 10 | BP36: =SUM(AC36:BO36) -> 20 | BQ36: =BP36/60 -> 0.33333333
A37: 31 | B37: FOH | C37: Prepare Delievery & Take aways condiments | D37: Basic | E37: Daily | F37: Fixed | G37: Morning | H37: Theo kế hoạch chuẩn bị hàng hóa | L37: x | AJ37: 5 | AL37: 10 | AS37: 10 | AU37: 15 | BP37: =SUM(AC37:BO37) -> 40 | BQ37: =BP37/60 -> 0.66666667
A38: 32 | B38: FOH | C38: Cashier check cashflow before opening | D38: Specific | E38: Daily | F38: Fixed | G38: Morning | H38: Quản lý bàn giao tiền cho CSR và túi bao tử, chìa khóa xe giao hàng Ký bàn gian sổ sách => hoàn thành trước 10h | J38: x | L38: x | Q38: No. of Cashier Counter | R38: x | S38: x | T38: x | U38: x | V38: x | W38: x | X38: x | Y38: x | Z38: x | AA38: x | AB38: x | AJ38: 5 | BP38: =SUM(AC38:BO38) -> 5 | BQ38: =BP38/60 -> 0.083333333
A39: 33 | B39: MGNT | C39: Breifing | D39: Specific | E39: Daily | F39: Flexible | G39: Morning/Afternoon | H39: Họp đầu thực hiện trước giờ bán hàng gồm 1 quản lý và 4-5 nhân viên (thời gian họp 5p x 6 = 30p) | I39: x | J39: x | K39: x | L39: x | M39: x | N39: x | O39: x | P39: x | Q39: TC | R39: x | S39: x | T39: x | U39: x | V39: x | W39: x | X39: x | Y39: x | Z39: x | AA39: x | AB39: x | AK39: 20 | AY39: 20 | BP39: =SUM(AC39:BO39) -> 40 | BQ39: =BP39/60 -> 0.66666667
A40: 34 | B40: FOH | C40: CSR/Cashier | D40: Specific | E40: Daily | F40: Fixed | G40: Morning/Afternoon | H40: Giờ cao điểm cần 1 nhân viên đứng độc lập 1 quầy, giờ thấp điểm kết hợp Server và Hostess | L40: x | O40: x | P40: x | Q40: TC | R40: x | S40: x | T40: x | U40: x | V40: x | W40: x | X40: x | Y40: x | Z40: x | AA40: x | AB40: x | AK40: 15 | AL40: 10 | AM40: 30 | AN40: 30 | AO40: 30 | AP40: 30 | AQ40: 30 | AR40: 30 | AS40: 20 | AT40: 20 | AU40: 15 | AV40: 15 | AW40: 15 | AX40: 15 | AY40: 30 | AZ40: 30 | BA40: 30 | BB40: 30 | BC40: 30 | BD40: 30 | BE40: 30 | BF40: 30 | BG40: 30 | BH40: 5 | BP40: =SUM(AC40:BO40) -> 580 | BQ40: =BP40/60 -> 9.6666667
A41: 35 | B41: FOH | C41: FOH TMs (Hostess, Server, Table Cleaning,...) | D41: Specific | E41: Daily | F41: Flexible | G41: Morning/Afternoon | H41: 1 Nhân viên Server kết hợp đi đồ và take care khách hàng => giờ thấp điểm CSR thay | M41: x | O41: x | P41: x | Q41: TC | R41: x | S41: x | T41: x | U41: x | V41: x | W41: x | X41: x | Y41: x | Z41: x | AA41: x | AB41: x | AK41: 10 | AL41: 10 | AM41: 20 | AN41: 20 | AO41: 30 | AP41: 30 | AQ41: 15 | AR41: 10 | AW41: 15 | AX41: 15 | AY41: 15 | AZ41: 20 | BA41: 30 | BB41: 30 | BC41: 30 | BD41: 30 | BE41: 10 | BF41: 10 | BG41: 15 | BP41: =SUM(AC41:BO41) -> 365 | BQ41: =BP41/60 -> 6.0833333
A42: 36 | B42: ALL | C42: Food runner | D42: Basic | E42: Daily | F42: Flexibel | G42: Morning/Afternoon | H42: Linh hoạt sắp xếp nhân sự kiêm nhiệm | K42: x | M42: x | O42: x | P42: x | Q42: TC | R42: x | S42: x | T42: x | U42: x | V42: x | W42: x | X42: x | Y42: x | Z42: x | AA42: x | AB42: x | BA42: 10 | BB42: 10 | BC42: 10 | BD42: 10 | BP42: =SUM(AC42:BO42) -> 40 | BQ42: =BP42/60 -> 0.66666667
A43: 37 | B43: ALL | C43: RIDERS DELIVERY | D43: Specific | E43: Daily | F43: Fixed | G43: Morning/Afternoon | H43: Giờ cao điểm cần ít nhất 2 Rider đi đơn Thời gian không có đơn hàng hỗ trợ đi đồ và DW và làm lịch vệ sinh Giờ thấp điểm 1 rider+DW | N43: x | O43: x | P43: x | Q43: Delivery TC | R43: x | S43: x | T43: x | U43: x | V43: x | W43: x | X43: x | Y43: x | Z43: x | AA43: x | AB43: x | AM43: 20 | AN43: 30 | AO43: 40 | AP43: 40 | AQ43: 20 | AR43: 20 | AY43: 20 | AZ43: 30 | BA43: 60 | BB43: 60 | BC43: 60 | BD43: 60 | BE43: 20 | BF43: 20 | BP43: =SUM(AC43:BO43) -> 500 | BQ43: =BP43/60 -> 8.3333333
A44: 38 | B44: MGNT | C44: Shift Hand over | D44: Specific | E44: Daily | F44: Flexible | G44: Afternoon | H44: 2 quản lý bàn giao ca (doanh thu, vấn đề trong ca, thẻ, sổ sách,…) thơi gian 5p x 2 = 10p | I44: x | J44: x | O44: x | P44: x | Q44: No. of Staff | R44: x | S44: x | T44: x | U44: x | V44: x | W44: x | X44: x | Y44: x | Z44: x | AA44: x | AB44: x | AU44: 20 | BP44: =SUM(AC44:BO44) -> 20 | BQ44: =BP44/60 -> 0.33333333
A45: 39 | B45: ALL | C45: Fold Pizza Boxes | D45: Specific | E45: Daily | F45: Flexible | G45: Afternoon | H45: 1 nhân viên gấp - 30 hộp L: 9p - 50 hộp R: 12p - 30 hộp P: 9p => Thời gian gấp không cố định | I45: x | J45: x | K45: x | L45: x | M45: x | N45: x | O45: x | P45: x | Q45: TC | R45: x | S45: x | T45: x | U45: x | V45: x | W45: x | X45: x | Y45: x | Z45: x | AA45: x | AB45: x | AL45: 10 | AV45: 20 | BP45: =SUM(AC45:BO45) -> 30 | BQ45: =BP45/60 -> 0.5
A46: 40 | B46: ALL | C46: Fold / Prepare leaflets | D46: No | E46: Daily | F46: Flexible | G46: Afternoon | H46: Chuẩn bị 200 tờ rơi ~ 10p (có thể bỏ qua do có sự kiện hoặc thời tiết không thể LSM) | I46: x | J46: x | K46: x | L46: x | M46: x | N46: x | O46: x | P46: x | Q46: TC | R46: x | S46: x | T46: x | U46: x | V46: x | W46: x | X46: x | Y46: x | Z46: x | AA46: x | AB46: x | BP46: =SUM(AC46:BO46) -> 0 | BQ46: =BP46/60 -> 0
A47: 41 | B47: ALL | C47: Leafleting | D47: No | E47: Daily | F47: Flexible | G47: Afternoon | H47: Tối thiểu 2 nhân viên phát 200 tờ rơi (có thể bỏ qua do có sự kiện hoặc thời tiết không thể LSM) - thời gian dự kiến 1h và thay đổi thời gian theo khu vực phát xa gần | I47: x | J47: x | K47: x | L47: x | M47: x | N47: x | O47: x | P47: x | Q47: Weather | R47: x | S47: x | T47: x | U47: x | V47: x | W47: x | X47: x | Y47: x | Z47: x | AA47: x | AB47: x | AM47: 30 | AN47: 30 | BP47: =SUM(AC47:BO47) -> 60 | BQ47: =BP47/60 -> 1
A48: 42 | B48: BOH | C48: Pans Pre-Oil for the next morning | D48: Basic | E48: Daily | F48: Flexible | G48: Evening | H48: Oil 3/4 mẻ Pan và 1/4 mẻ SCP | J48: x | K48: x | N48: x | BH48: 30 | BP48: =SUM(AC48:BO48) -> 30 | BQ48: =BP48/60 -> 0.5
A49: 43 | B49: BOH | C49: Cooking utensils and Oven cleaning | D49: Basic | E49: Daily | F49: Flexible | I49: x | J49: x | K49: x | N49: x | O49: x | P49: x | Q49: Store Area | R49: x | S49: x | T49: x | U49: x | V49: x | W49: x | X49: x | Y49: x | Z49: x | AA49: x | AB49: x | BI49: 20 | BP49: =SUM(AC49:BO49) -> 20 | BQ49: =BP49/60 -> 0.33333333
A50: 44 | B50: BOH | C50: Clean Deep Fryer | D50: Basic | E50: Daily | F50: Flexible | G50: Evening | H50: Thực hiện cuối ca, xả và lọc dầu | J50: x | K50: x | N50: x | O50: X | P50: X | Q50: Fixed | R50: x | Y50: x | BI50: 10 | BP50: =SUM(AC50:BO50) -> 10 | BQ50: =BP50/60 -> 0.16666667
A51: 45 | B51: BOH | C51: Closing BOH Cleaning (Oven, Fryers,… ) | D51: Basic | E51: Daily | F51: Flexible | G51: Evening | H51: Dọn quầy và vệ sinh quầy, bắt đầu từ 21h - Make: 20p - Auxi 20p - Cut 15p - Bar 15p - dough+dispath 20p | J51: x | K51: x | N51: x | O51: x | P51: x | Q51: Store Area | R51: x | S51: x | T51: x | U51: x | V51: x | W51: x | X51: x | Y51: x | Z51: x | AA51: x | AB51: x | BI51: 30 | BJ51: 20 | BP51: =SUM(AC51:BO51) -> 50 | BQ51: =BP51/60 -> 0.83333333
A52: 46 | B52: ALL | C52: Dust removing | BP52: =SUM(AC52:BO52) -> 0 | BQ52: =BP52/60 -> 0
A53: 47 | B53: FOH | C53: Dry up culteries, cups and plates | D53: No | E53: Daily | F53: Flexible | G53: Morning/Afternoon | H53: Lau kho các dụng cụ sau khi nhân viên rửa đồ xong => thời gian không cố định hàng ca | K53: x | L53: x | M53: x | N53: x | O53: x | P53: x | Q53: TC | R53: x | S53: x | T53: x | U53: x | V53: x | W53: x | X53: x | Y53: x | Z53: x | AA53: x | AB53: x | AQ53: 10 | AR53: 5 | BF53: 15 | BG53: 10 | BP53: =SUM(AC53:BO53) -> 40 | BQ53: =BP53/60 -> 0.66666667
A54: 48 | B54: FOH | C54: Fill culteries, cups and plates | D54: No | E54: Daily | F54: Flexible | G54: Morning/Afternoon | H54: Úp cất các dụng cụ về vị trí => thời gian không cố định hàng ca | K54: x | L54: x | M54: x | N54: x | O54: x | P54: x | Q54: TC | R54: x | S54: x | T54: x | U54: x | V54: x | W54: x | X54: x | Y54: x | Z54: x | AA54: x | AB54: x | AS54: 10 | BG54: 10 | BP54: =SUM(AC54:BO54) -> 20 | BQ54: =BP54/60 -> 0.33333333
A55: 49 | B55: FOH | C55: Closing FOH Clearning (Clean up dust，clean Station counter，clean tables, sofa) | D55: Basic | E55: Daily | F55: Flexible | G55: Evening | H55: Lau bàn ghế, vệ sinh sắp xếp quầy Cash | J55: x | L55: x | M55: x | O55: x | P55: x | Q55: Store Area | R55: x | S55: x | T55: x | U55: x | V55: x | W55: x | X55: x | Y55: x | Z55: x | AA55: x | AB55: x | BH55: 15 | BP55: =SUM(AC55:BO55) -> 15 | BQ55: =BP55/60 -> 0.25
A56: 50 | B56: FOH | C56: Clean service trays, fill up sauces botles | F56: Flexible | J56: x | K56: x | L56: x | M56: x | N56: x | BH56: 10 | BP56: =SUM(AC56:BO56) -> 10 | BQ56: =BP56/60 -> 0.16666667
A57: 51 | B57: FOH | C57: Turning chairs before sweep/mop floor | D57: No | E57: Daily | F57: Flexible | G57: Evening | H57: Úp ghế và kê bàn cho k bị ấm thấp mốc | J57: x | L57: x | M57: x | N57: x | O57: x | P57: x | Q57: Store Area | R57: x | S57: x | T57: x | U57: x | V57: x | W57: x | X57: x | Y57: x | Z57: x | AA57: x | AB57: x | BP57: =SUM(AC57:BO57) -> 0 | BQ57: =BP57/60 -> 0
A58: 52 | B58: ALL | C58: Meal time 30' for TMs whom work over 6h | D58: No | E58: Daily | F58: Flexible | G58: Morning/Afternoon | H58: Giờ nghỉ giữa ca => không cố định hàng ca và thời gian tùy tình hình hàng ca | I58: x | J58: x | K58: x | L58: x | M58: x | N58: x | O58: x | P58: x | Q58: No. of Staff | R58: x | S58: x | T58: x | U58: x | V58: x | W58: x | X58: x | Y58: x | Z58: x | AA58: x | AB58: x | AL58: 30 | AM58: 30 | AY58: 30 | BP58: =SUM(AC58:BO58) -> 90 | BQ58: =BP58/60 -> 1.5
A59: 53 | B59: MGNT | C59: Finalize sales and cash，check credit card bills and total transaction bills，check tips | D59: Specific | E59: Daily | F59: Flexible | G59: Evening | H59: MIC và CSR kiểm tra trước giấy tờ trước khi đóng ca (thẻ, Aligator,…) từ 21h40 pick tiền và ký bàn giao hoàn thành trước 22h | I59: x | J59: x | L59: x | O59: x | P59: x | Q59: TC | R59: x | S59: x | T59: x | U59: x | V59: x | W59: x | X59: x | Y59: x | Z59: x | AA59: x | AB59: x | BH59: 15 | BP59: =SUM(AC59:BO59) -> 15 | BQ59: =BP59/60 -> 0.25
A60: 54 | B60: MGNT | C60: Daily Report | D60: Specific | E60: Daily | F60: Flexible | G60: Evening | H60: MIC làm báo cáo cuối ngày - daily report - Wastage discard - Xuất VAT - Confirm sale | I60: x | J60: x | O60: x | P60: x | Q60: No. of Staff | R60: x | S60: x | T60: x | U60: x | V60: x | W60: x | X60: x | Y60: x | Z60: x | AA60: x | AB60: x | BJ60: 15 | BP60: =SUM(AC60:BO60) -> 15 | BQ60: =BP60/60 -> 0.25
A61: 55 | B61: MGNT | C61: Order Vegieterian | D61: Specific | E61: 3/week | F61: Flexible | G61: Morning | H61: Đặt hàng rau 2 ngày 1 lần trước 12h thứ 3 5 7, CN | I61: x | J61: x | O61: x | Q61: Fixed | R61: x | S61: x | T61: x | U61: x | V61: x | W61: x | Y61: x | Z61: x | AA61: x | AB61: x | AV61: 5 | BP61: =SUM(AC61:BO61) -> 5 | BQ61: =BP61/60 -> 0.083333333
A62: 56 | B62: MGNT | C62: Receive Vegieterian | D62: Specific | E62: 3/week | F62: Flexible | G62: Morning | H62: Nhận hàng rau 2 ngày 1 lần trước 11h thứ 2 4 6 CN | I62: x | J62: x | K62: x | O62: x | P62: x | Q62: TC | S62: x | X62: x | Y62: x | Z62: x | AA62: x | AB62: x | AH62: 10 | BP62: =SUM(AC62:BO62) -> 10 | BQ62: =BP62/60 -> 0.16666667
A63: 57 | B63: MGNT | C63: RGS / CLOSING SHIFT | D63: Specific | E63: Daily | F63: Fixed | G63: Morning | H63: Đóng cửa cùng 1 nhân viên; thực hiện security & safety check | I63: x | J63: x | K63: x | L63: x | M63: x | N63: x | O63: x | P63: x | Q63: TC | R63: x | S63: x | T63: x | U63: x | V63: x | W63: x | X63: x | Y63: x | Z63: x | AA63: x | AB63: x | BJ63: 10 | BP63: =SUM(AC63:BO63) -> 10 | BQ63: =BP63/60 -> 0.16666667
BP64: =SUM(AC64:BO64) -> 0 | BQ64: =BP64/60 -> 0
N66: Times | AC66: =SUM(AC7:AC65) -> 0 | AD66: =SUM(AD7:AD65) -> 0 | AE66: =SUM(AE7:AE65) -> 0 | AF66: =SUM(AF7:AF65) -> 0 | AG66: =SUM(AG7:AG65) -> 60 | AH66: =SUM(AH7:AH65) -> 60 | AI66: =SUM(AI7:AI65) -> 120 | AJ66: =SUM(AJ7:AJ65) -> 120 | ... BQ66: =SUM(BQ7:BQ65) -> 70.25
N68: People | AG68: =AG66/30 -> 2 | AH68: =AH66/30 -> 2 | AI68: =AI66/30 -> 4 | AJ68: =AJ66/30 -> 4 | AK68: =AK66/30 -> 4 | AL68: =AL66/30 -> 4 | AM68: =AM66/30 -> 6 | AN68: =AN66/30 -> 6 | ... BM68: =BM66/30 -> 0
AF69: BL | AG69: ='Base Line COL'!O5 -> 2 | AH69: ='Base Line COL'!P5 -> 2 | AI69: ='Base Line COL'!Q5 -> 4 | AJ69: ='Base Line COL'!R5 -> 4 | AK69: ='Base Line COL'!S5 -> 4 | AL69: ='Base Line COL'!T5 -> 4 | AM69: ='Base Line COL'!U5 -> 5 | AN69: ='Base Line COL'!V5 -> 5 | ... BO69: ='Base Line COL'!AW5 -> 0

Sheet Base Line COL
K1: AVERAGE DAY PART | O1: Trans | P1: 3 | Q1: Sales | R1: 717426 | U1: Trans | V1: 8 | X1: 2057641 | AA1: Trans | AB1: 5 | AC1: Sales | AD1: 1080194 | AG1: Trans | AH1: 22 | AI1: Sales | AJ1: 5580035 | AM1: Trans | AN1: 6 | AO1: Sales | AP1: 1445381
M2: EARLY LUNCH | U2: LUNCH | AA2: TEA | AG2: DINNER | AM2: LATE DINNER
A3: Store Name | B3: Day | C3: Base line Labor hours | D3: Estimate Sale (Maximize) | E3: Productivity | F3: Estimate COL | H3: Level | I3: Counter | J3: From | K3: To | L3: Total Hr | M3: 700 | N3: 730 | O3: 800 | P3: 830 | Q3: 900 | R3: 930 | S3: 1000 | T3: 1030 | U3: 1100 | V3: 1130 | W3: 1200 | X3: 1230 | Y3: 1300 | Z3: 1330 | AA3: 1400 | AB3: =AA4 -> 1430 | AC3: =AB4 -> 1500 | AD3: =AC4 -> 1530 | AE3: =AD4 -> 1600 | AF3: =AE4 -> 1630 | AG3: =AF4 -> 1700 | AH3: =AG4 -> 1730 | AI3: =AH4 -> 1800 | ... AS3: =AR4 -> 2300 | AT3: 2300 | AU3: NOTE
A4: Concept | M4: 730 | N4: 800 | O4: 830 | P4: 900 | Q4: 930 | R4: 1000 | S4: 1030 | T4: 1100 | U4: 1130 | V4: 1200 | W4: 1230 | X4: 1300 | Y4: 1330 | Z4: 1400 | AA4: 1430 | AB4: 1500 | AC4: 1530 | AD4: 1600 | AE4: 1630 | AF4: 1700 | AG4: 1730 | AH4: 1800 | AI4: 1830 | AJ4: 1900 | AK4: 1930 | AL4: 2000 | AM4: 2030 | AN4: 2100 | AO4: 2130 | AP4: 2200 | AQ4: 2230 | AR4: 2300 | AS4: 2330 | AT4: 2400
A5: DEMO | B5: Mon | C5: =L5 -> 70 | D5: 10000000 | E5: =+D5/C5 -> 142857.14 | H5: Total | L5: =(SUM(M5:AT5))/2 -> 70 | M5: =COUNTA(M6:M36)-COUNTIF(M6:M36,"") -> 0 | N5: =COUNTA(N6:N36)-COUNTIF(N6:N36,"") -> 0 | O5: =COUNTA(O6:O36)-COUNTIF(O6:O36,"") -> 2 | P5: =COUNTA(P6:P36)-COUNTIF(P6:P36,"") -> 2 | Q5: =COUNTA(Q6:Q36)-COUNTIF(Q6:Q36,"") -> 4 | R5: =COUNTA(R6:R36)-COUNTIF(R6:R36,"") -> 4 | S5: =COUNTA(S6:S36)-COUNTIF(S6:S36,"") -> 4 | T5: =COUNTA(T6:T36)-COUNTIF(T6:T36,"") -> 4 | ... AT5: =COUNTA(AT6:AT36)-COUNTIF(AT6:AT36,"") -> 0
A6: FCD | H6: MGNT | I6: Mngt 1 | J6: 800 | K6: 1600 | L6: =(COUNTA(M6:AT6)-COUNTIF(M6:AT6,""))/2 -> 8 | M6: =IF(AND(M$3>$J6,M$4<$K6),"-------",IF(M$3=$J6,"<-----",IF(M$4=$K6,"----->",""))) | N6: =IF(AND(N$3>$J6,N$4<$K6),"-------",IF(N$3=$J6,"<-----",IF(N$4=$K6,"----->",""))) | O6: =IF(AND(O$3>$J6,O$4<$K6),"---------",IF(O$3=$J6,"<-----",IF(O$4=$K6,"----->",""))) -> <----- | P6: =IF(AND(P$3>$J6,P$4<$K6),"-------",IF(P$3=$J6,"<-----",IF(P$4=$K6,"----->",""))) -> ------- | Q6: =IF(AND(Q$3>$J6,Q$4<$K6),"-------",IF(Q$3=$J6,"<-----",IF(Q$4=$K6,"----->",""))) -> ------- | R6: =IF(AND(R$3>$J6,R$4<$K6),"-----------",IF(R$3=$J6,"<-----",IF(R$4=$K6,"----->",""))) -> ----------- | S6: =IF(AND(S$3>$J6,S$4<$K6),"-------",IF(S$3=$J6,"<-----",IF(S$4=$K6,"----->",""))) -> ------- | T6: =IF(AND(T$3>$J6,T$4<$K6),"-------",IF(T$3=$J6,"<-----",IF(T$4=$K6,"----->",""))) -> ------- | U6: =IF(AND(U$3>$J6,U$4<$K6),"-------",IF(U$3=$J6,"<-----",IF(U$4=$K6,"----->",""))) -> ------- | V6: =IF(AND(V$3>$J6,V$4<$K6),"-------",IF(V$3=$J6,"<-----",IF(V$4=$K6,"----->",""))) -> ------- | W6: =IF(AND(W$3>$J6,W$4<$K6),"-------",IF(W$3=$J6,"<-----",IF(W$4=$K6,"----->",""))) -> ------- | X6: =IF(AND(X$3>$J6,X$4<$K6),"-----------",IF(X$3=$J6,"<-----",IF(X$4=$K6,"----->",""))) -> ----------- | Y6: =IF(AND(Y$3>$J6,Y$4<$K6),"-------",IF(Y$3=$J6,"<-----",IF(Y$4=$K6,"----->",""))) -> ------- | Z6: =IF(AND(Z$3>$J6,Z$4<$K6),"-------",IF(Z$3=$J6,"<-----",IF(Z$4=$K6,"----->",""))) -> ------- | AA6: =IF(AND(AA$3>$J6,AA$4<$K6),"-------",IF(AA$3=$J6,"<-----",IF(AA$4=$K6,"----->",""))) -> ------- | AB6: =IF(AND(AB$3>$J6,AB$4<$K6),"-------",IF(AB$3=$J6,"<-----",IF(AB$4=$K6,"----->",""))) -> ------- | AC6: =IF(AND(AC$3>$J6,AC$4<$K6),"-------",IF(AC$3=$J6,"<-----",IF(AC$4=$K6,"----->",""))) -> ------- | AD6: =IF(AND(AD$3>$J6,AD$4<$K6),"-------",IF(AD$3=$J6,"<-----",IF(AD$4=$K6,"---------->",""))) -> ----------> | AE6: =IF(AND(AE$3>$J6,AE$4<$K6),"-------",IF(AE$3=$J6,"<-----",IF(AE$4=$K6,"----->",""))) | AF6: =IF(AND(AF$3>$J6,AF$4<$K6),"-------",IF(AF$3=$J6,"<-----",IF(AF$4=$K6,"----->",""))) | AG6: =IF(AND(AG$3>$J6,AG$4<$K6),"-------",IF(AG$3=$J6,"<-----",IF(AG$4=$K6,"----->",""))) | AH6: =IF(AND(AH$3>$J6,AH$4<$K6),"-------",IF(AH$3=$J6,"<-----",IF(AH$4=$K6,"----->",""))) | AI6: =IF(AND(AI$3>$J6,AI$4<$K6),"-------",IF(AI$3=$J6,"<-----",IF(AI$4=$K6,"----->",""))) | AJ6: =IF(AND(AJ$3>$J6,AJ$4<$K6),"-------",IF(AJ$3=$J6,"<-----",IF(AJ$4=$K6,"----->",""))) | AK6: =IF(AND(AK$3>$J6,AK$4<$K6),"-------",IF(AK$3=$J6,"<-----",IF(AK$4=$K6,"----->",""))) | AL6: =IF(AND(AL$3>$J6,AL$4<$K6),"-------",IF(AL$3=$J6,"<-----",IF(AL$4=$K6,"----->",""))) | ... AT6: =IF(AND(AT$3>$J6,AT$4<$K6),"-------",IF(AT$3=$J6,"<-----",IF(AT$4=$K6,"----->","")))
A7: Grand Total | C7: =SUM(P1,V1,AB1,AG1,AN1) -> 22 | D7: =SUM(R1,X1,AD1,AJ1,AP1) -> 10880677 | I7: Mngt 2 | J7: 1500 | K7: 2300 | L7: =(COUNTA(M7:AT7)-COUNTIF(M7:AT7,""))/2 -> 8 | M7: =IF(AND(M$3>$J7,M$4<$K7),"-------",IF(M$3=$J7,"<-----",IF(M$4=$K7,"----->",""))) | N7: =IF(AND(N$3>$J7,N$4<$K7),"-------",IF(N$3=$J7,"<-----",IF(N$4=$K7,"----->",""))) | O7: =IF(AND(O$3>$J7,O$4<$K7),"-------",IF(O$3=$J7,"<-----",IF(O$4=$K7,"----->",""))) | P7: =IF(AND(P$3>$J7,P$4<$K7),"-------",IF(P$3=$J7,"<-----",IF(P$4=$K7,"----->",""))) | Q7: =IF(AND(Q$3>$J7,Q$4<$K7),"-------",IF(Q$3=$J7,"<-----",IF(Q$4=$K7,"----->",""))) | R7: =IF(AND(R$3>$J7,R$4<$K7),"-------",IF(R$3=$J7,"<-----",IF(R$4=$K7,"----->",""))) | S7: =IF(AND(S$3>$J7,S$4<$K7),"-------",IF(S$3=$J7,"<-----",IF(S$4=$K7,"----->",""))) | T7: =IF(AND(T$3>$J7,T$4<$K7),"-------",IF(T$3=$J7,"<-----",IF(T$4=$K7,"----->",""))) | ... AC7: =IF(AND(AC$3>$J7,AC$4<$K7),"-------",IF(AC$3=$J7,"<-----",IF(AC$4=$K7,"----->",""))) -> <----- | AD7: =IF(AND(AD$3>$J7,AD$4<$K7),"------------",IF(AD$3=$J7,"<-----",IF(AD$4=$K7,"----->",""))) -> ------------ | AE7: =IF(AND(AE$3>$J7,AE$4<$K7),"-------",IF(AE$3=$J7,"<-----",IF(AE$4=$K7,"----->",""))) -> ------- | AF7: =IF(AND(AF$3>$J7,AF$4<$K7),"-------",IF(AF$3=$J7,"<-----",IF(AF$4=$K7,"----->",""))) -> ------- | AG7: =IF(AND(AG$3>$J7,AG$4<$K7),"-------",IF(AG$3=$J7,"<-----",IF(AG$4=$K7,"----->",""))) -> ------- | AH7: =IF(AND(AH$3>$J7,AH$4<$K7),"-------",IF(AH$3=$J7,"<-----",IF(AH$4=$K7,"----->",""))) -> ------- | AI7: =IF(AND(AI$3>$J7,AI$4<$K7),"-------",IF(AI$3=$J7,"<-----",IF(AI$4=$K7,"----->",""))) -> ------- | AJ7: =IF(AND(AJ$3>$J7,AJ$4<$K7),"-------------",IF(AJ$3=$J7,"<-----",IF(AJ$4=$K7,"----->",""))) -> ------------- | AK7: =IF(AND(AK$3>$J7,AK$4<$K7),"-------",IF(AK$3=$J7,"<-----",IF(AK$4=$K7,"----->",""))) -> ------- | AL7: =IF(AND(AL$3>$J7,AL$4<$K7),"-------",IF(AL$3=$J7,"<-----",IF(AL$4=$K7,"----->",""))) -> ------- | AM7: =IF(AND(AM$3>$J7,AM$4<$K7),"-------",IF(AM$3=$J7,"<-----",IF(AM$4=$K7,"----->",""))) -> ------- | AN7: =IF(AND(AN$3>$J7,AN$4<$K7),"-------",IF(AN$3=$J7,"<-----",IF(AN$4=$K7,"----->",""))) -> ------- | AO7: =IF(AND(AO$3>$J7,AO$4<$K7),"-------",IF(AO$3=$J7,"<-----",IF(AO$4=$K7,"----->",""))) -> ------- | AP7: =IF(AND(AP$3>$J7,AP$4<$K7),"-------------",IF(AP$3=$J7,"<-----",IF(AP$4=$K7,"----->",""))) -> ------------- | AQ7: =IF(AND(AQ$3>$J7,AQ$4<$K7),"---------",IF(AQ$3=$J7,"<-----",IF(AQ$4=$K7,"---------->",""))) -> --------- | AR7: =IF(AND(AR$3>$J7,AR$4<$K7),"-------",IF(AR$3=$J7,"<-----",IF(AR$4=$K7,"----->",""))) -> -----> | AS7: =IF(AND(AS$3>$J7,AS$4<$K7),"-------",IF(AS$3=$J7,"<-----",IF(AS$4=$K7,"----->",""))) | AT7: =IF(AND(AT$3>$J7,AT$4<$K7),"-------",IF(AT$3=$J7,"<-----",IF(AT$4=$K7,"----->","")))
A8: Cập nhật thực tế Sales mix của store vào ô xanh dưới đây | I8: Mgnt 3 | L8: =(COUNTA(M8:AT8)-COUNTIF(M8:AT8,""))/2 -> 0 | M8: =IF(AND(M$3>$J8,M$4<$K8),"-------",IF(M$3=$J8,"<-----",IF(M$4=$K8,"----->",""))) | N8: =IF(AND(N$3>$J8,N$4<$K8),"-------",IF(N$3=$J8,"<-----",IF(N$4=$K8,"----->",""))) | O8: =IF(AND(O$3>$J8,O$4<$K8),"-------",IF(O$3=$J8,"<-----",IF(O$4=$K8,"----->",""))) | P8: =IF(AND(P$3>$J8,P$4<$K8),"-------",IF(P$3=$J8,"<-----",IF(P$4=$K8,"----->",""))) | Q8: =IF(AND(Q$3>$J8,Q$4<$K8),"-------",IF(Q$3=$J8,"<-----",IF(Q$4=$K8,"----->",""))) | R8: =IF(AND(R$3>$J8,R$4<$K8),"-------",IF(R$3=$J8,"<-----",IF(R$4=$K8,"----->",""))) | S8: =IF(AND(S$3>$J8,S$4<$K8),"-------",IF(S$3=$J8,"<-----",IF(S$4=$K8,"----->",""))) | T8: =IF(AND(T$3>$J8,T$4<$K8),"-------",IF(T$3=$J8,"<-----",IF(T$4=$K8,"----->",""))) | ... AT8: =IF(AND(AT$3>$J8,AT$4<$K8),"-------",IF(AT$3=$J8,"<-----",IF(AT$4=$K8,"----->","")))
A9: Sales mix | C9: DI | D9: TA | E9: DELI | F9: Grand Total | L9: =(COUNTA(M9:AT9)-COUNTIF(M9:AT9,""))/2 -> 0 | M9: =IF(AND(M$3>$J9,M$4<$K9),"-------",IF(M$3=$J9,"<-----",IF(M$4=$K9,"----->",""))) | N9: =IF(AND(N$3>$J9,N$4<$K9),"-------",IF(N$3=$J9,"<-----",IF(N$4=$K9,"----->",""))) | O9: =IF(AND(O$3>$J9,O$4<$K9),"-------",IF(O$3=$J9,"<-----",IF(O$4=$K9,"----->",""))) | P9: =IF(AND(P$3>$J9,P$4<$K9),"-------",IF(P$3=$J9,"<-----",IF(P$4=$K9,"----->",""))) | Q9: =IF(AND(Q$3>$J9,Q$4<$K9),"-------",IF(Q$3=$J9,"<-----",IF(Q$4=$K9,"----->",""))) | R9: =IF(AND(R$3>$J9,R$4<$K9),"-------",IF(R$3=$J9,"<-----",IF(R$4=$K9,"----->",""))) | S9: =IF(AND(S$3>$J9,S$4<$K9),"-------",IF(S$3=$J9,"<-----",IF(S$4=$K9,"----->",""))) | T9: =IF(AND(T$3>$J9,T$4<$K9),"-------",IF(T$3=$J9,"<-----",IF(T$4=$K9,"----->",""))) | ... AT9: =IF(AND(AT$3>$J9,AT$4<$K9),"-------",IF(AT$3=$J9,"<-----",IF(AT$4=$K9,"----->","")))
C10: 0.33 | D10: 0.42 | E10: 0.25 | H10: BOH | I10: Auxi/Bar 1 | J10: 1100 | K10: 1530 | L10: =(COUNTA(M10:AT10)-COUNTIF(M10:AT10,""))/2 -> 4.5 | M10: =IF(AND(M$3>$J10,M$4<$K10),"-------",IF(M$3=$J10,"<-----",IF(M$4=$K10,"----->",""))) | N10: =IF(AND(N$3>$J10,N$4<$K10),"-------",IF(N$3=$J10,"<-----",IF(N$4=$K10,"----->",""))) | O10: =IF(AND(O$3>$J10,O$4<$K10),"-------",IF(O$3=$J10,"<-----",IF(O$4=$K10,"----->",""))) | P10: =IF(AND(P$3>$J10,P$4<$K10),"-------",IF(P$3=$J10,"<-----",IF(P$4=$K10,"----->",""))) | Q10: =IF(AND(Q$3>$J10,Q$4<$K10),"-------",IF(Q$3=$J10,"<-----",IF(Q$4=$K10,"----->",""))) | R10: =IF(AND(R$3>$J10,R$4<$K10),"-------",IF(R$3=$J10,"<-----",IF(R$4=$K10,"----->",""))) | S10: =IF(AND(S$3>$J10,S$4<$K10),"-------",IF(S$3=$J10,"<-----",IF(S$4=$K10,"----->",""))) | T10: =IF(AND(T$3>$J10,T$4<$K10),"-------",IF(T$3=$J10,"<-----",IF(T$4=$K10,"----->",""))) | ... W10: =IF(AND(W$3>$J10,W$4<$K10),"-------",IF(W$3=$J10,"<-----",IF(W$4=$K10,"----->",""))) -> ------- | X10: =IF(AND(X$3>$J10,X$4<$K10),"------------",IF(X$3=$J10,"<-----",IF(X$4=$K10,"----->",""))) -> ------------ | Y10: =IF(AND(Y$3>$J10,Y$4<$K10),"-------",IF(Y$3=$J10,"<-----",IF(Y$4=$K10,"----->",""))) -> ------- | Z10: =IF(AND(Z$3>$J10,Z$4<$K10),"-------",IF(Z$3=$J10,"<-----",IF(Z$4=$K10,"----->",""))) -> ------- | AA10: =IF(AND(AA$3>$J10,AA$4<$K10),"-------",IF(AA$3=$J10,"<-----",IF(AA$4=$K10,"----->",""))) -> ------- | AB10: =IF(AND(AB$3>$J10,AB$4<$K10),"-------",IF(AB$3=$J10,"<-----",IF(AB$4=$K10,"----->",""))) -> ------- | AC10: =IF(AND(AC$3>$J10,AC$4<$K10),"-------",IF(AC$3=$J10,"<-----",IF(AC$4=$K10,"----->",""))) -> -----> | AD10: =IF(AND(AD$3>$J10,AD$4<$K10),"-------",IF(AD$3=$J10,"<-----",IF(AD$4=$K10,"----->",""))) | AE10: =IF(AND(AE$3>$J10,AE$4<$K10),"-------",IF(AE$3=$J10,"<-----",IF(AE$4=$K10,"----->",""))) | AF10: =IF(AND(AF$3>$J10,AF$4<$K10),"-------",IF(AF$3=$J10,"<-----",IF(AF$4=$K10,"----->",""))) | ... AT10: =IF(AND(AT$3>$J10,AT$4<$K10),"-------",IF(AT$3=$J10,"<-----",IF(AT$4=$K10,"----->","")))
A11: Early Lunch | B11: 0.188 | C11: =+$D$5*C$10*$B11 -> 620400 | D11: =+$D$5*D$10*$B11 -> 789600 | E11: =+$D$5*E$10*$B11 -> 470000 | F11: =SUM(C11:E11) -> 1880000 | I11: Auxi/Bar 2 | L11: =(COUNTA(M11:AT11)-COUNTIF(M11:AT11,""))/2 -> 0 | M11: =IF(AND(M$3>$J11,M$4<$K11),"-------",IF(M$3=$J11,"<-----",IF(M$4=$K11,"----->",""))) | N11: =IF(AND(N$3>$J11,N$4<$K11),"-------",IF(N$3=$J11,"<-----",IF(N$4=$K11,"----->",""))) | O11: =IF(AND(O$3>$J11,O$4<$K11),"-------",IF(O$3=$J11,"<-----",IF(O$4=$K11,"----->",""))) | P11: =IF(AND(P$3>$J11,P$4<$K11),"-------",IF(P$3=$J11,"<-----",IF(P$4=$K11,"----->",""))) | Q11: =IF(AND(Q$3>$J11,Q$4<$K11),"-------",IF(Q$3=$J11,"<-----",IF(Q$4=$K11,"----->",""))) | R11: =IF(AND(R$3>$J11,R$4<$K11),"-------",IF(R$3=$J11,"<-----",IF(R$4=$K11,"----->",""))) | S11: =IF(AND(S$3>$J11,S$4<$K11),"-------",IF(S$3=$J11,"<-----",IF(S$4=$K11,"----->",""))) | T11: =IF(AND(T$3>$J11,T$4<$K11),"-------",IF(T$3=$J11,"<-----",IF(T$4=$K11,"----->",""))) | ... AT11: =IF(AND(AT$3>$J11,AT$4<$K11),"-------",IF(AT$3=$J11,"<-----",IF(AT$4=$K11,"----->","")))
A12: Lunch | B12: 0.179 | C12: =+$D$5*C$10*$B12 -> 590700 | D12: =+$D$5*D$10*$B12 -> 751800 | E12: =+$D$5*E$10*$B12 -> 447500 | F12: =SUM(C12:E12) -> 1790000 | I12: Auxi/Bar 3 | J12: 1700 | K12: 2100 | L12: =(COUNTA(M12:AT12)-COUNTIF(M12:AT12,""))/2 -> 4 | M12: =IF(AND(M$3>$J12,M$4<$K12),"-------",IF(M$3=$J12,"<-----",IF(M$4=$K12,"----->",""))) | N12: =IF(AND(N$3>$J12,N$4<$K12),"-------",IF(N$3=$J12,"<-----",IF(N$4=$K12,"----->",""))) | O12: =IF(AND(O$3>$J12,O$4<$K12),"-------",IF(O$3=$J12,"<-----",IF(O$4=$K12,"----->",""))) | P12: =IF(AND(P$3>$J12,P$4<$K12),"-------",IF(P$3=$J12,"<-----",IF(P$4=$K12,"----->",""))) | Q12: =IF(AND(Q$3>$J12,Q$4<$K12),"-------",IF(Q$3=$J12,"<-----",IF(Q$4=$K12,"----->",""))) | R12: =IF(AND(R$3>$J12,R$4<$K12),"-------",IF(R$3=$J12,"<-----",IF(R$4=$K12,"----->",""))) | S12: =IF(AND(S$3>$J12,S$4<$K12),"-------",IF(S$3=$J12,"<-----",IF(S$4=$K12,"----->",""))) | T12: =IF(AND(T$3>$J12,T$4<$K12),"-------",IF(T$3=$J12,"<-----",IF(T$4=$K12,"----->",""))) | ... AI12: =IF(AND(AI$3>$J12,AI$4<$K12),"-------",IF(AI$3=$J12,"<-----",IF(AI$4=$K12,"----->",""))) -> ------- | AJ12: =IF(AND(AJ$3>$J12,AJ$4<$K12),"--------------",IF(AJ$3=$J12,"<-----",IF(AJ$4=$K12,"----->",""))) -> -------------- | AK12: =IF(AND(AK$3>$J12,AK$4<$K12),"-------",IF(AK$3=$J12,"<-----",IF(AK$4=$K12,"----->",""))) -> ------- | AL12: =IF(AND(AL$3>$J12,AL$4<$K12),"-------",IF(AL$3=$J12,"<-----",IF(AL$4=$K12,"----->",""))) -> ------- | AM12: =IF(AND(AM$3>$J12,AM$4<$K12),"-------",IF(AM$3=$J12,"<-----",IF(AM$4=$K12,"----->",""))) -> ------- | AN12: =IF(AND(AN$3>$J12,AN$4<$K12),"-------",IF(AN$3=$J12,"<-----",IF(AN$4=$K12,"----->",""))) -> -----> | AO12: =IF(AND(AO$3>$J12,AO$4<$K12),"-------",IF(AO$3=$J12,"<-----",IF(AO$4=$K12,"----->",""))) | AP12: =IF(AND(AP$3>$J12,AP$4<$K12),"-------",IF(AP$3=$J12,"<-----",IF(AP$4=$K12,"----->",""))) | AQ12: =IF(AND(AQ$3>$J12,AQ$4<$K12),"-------",IF(AQ$3=$J12,"<-----",IF(AQ$4=$K12,"----->",""))) | AR12: =IF(AND(AR$3>$J12,AR$4<$K12),"-------",IF(AR$3=$J12,"<-----",IF(AR$4=$K12,"----->",""))) | ... AT12: =IF(AND(AT$3>$J12,AT$4<$K12),"-------",IF(AT$3=$J12,"<-----",IF(AT$4=$K12,"----->","")))
A13: Tea | B13: 0.264 | C13: =+$D$5*C$10*$B13 -> 871200 | D13: =+$D$5*D$10*$B13 -> 1108800 | E13: =+$D$5*E$10*$B13 -> 660000 | F13: =SUM(C13:E13) -> 2640000 | I13: Make 1 | J13: 900 | K13: 1400 | L13: =(COUNTA(M13:AT13)-COUNTIF(M13:AT13,""))/2 -> 5 | M13: =IF(AND(M$3>$J13,M$4<$K13),"-------",IF(M$3=$J13,"<-----",IF(M$4=$K13,"----->",""))) | N13: =IF(AND(N$3>$J13,N$4<$K13),"-------",IF(N$3=$J13,"<-----",IF(N$4=$K13,"----->",""))) | O13: =IF(AND(O$3>$J13,O$4<$K13),"-------",IF(O$3=$J13,"<-----",IF(O$4=$K13,"----->",""))) | P13: =IF(AND(P$3>$J13,P$4<$K13),"-------",IF(P$3=$J13,"<-----",IF(P$4=$K13,"----->",""))) | Q13: =IF(AND(Q$3>$J13,Q$4<$K13),"-------",IF(Q$3=$J13,"<-----",IF(Q$4=$K13,"----->",""))) -> <----- | R13: =IF(AND(R$3>$J13,R$4<$K13),"------------",IF(R$3=$J13,"<-----",IF(R$4=$K13,"----->",""))) -> ------------ | S13: =IF(AND(S$3>$J13,S$4<$K13),"-------",IF(S$3=$J13,"<-----",IF(S$4=$K13,"----->",""))) -> ------- | T13: =IF(AND(T$3>$J13,T$4<$K13),"-------",IF(T$3=$J13,"<-----",IF(T$4=$K13,"----->",""))) -> ------- | U13: =IF(AND(U$3>$J13,U$4<$K13),"-------",IF(U$3=$J13,"<-----",IF(U$4=$K13,"----->",""))) -> ------- | V13: =IF(AND(V$3>$J13,V$4<$K13),"-------",IF(V$3=$J13,"<-----",IF(V$4=$K13,"----->",""))) -> ------- | W13: =IF(AND(W$3>$J13,W$4<$K13),"-------",IF(W$3=$J13,"<-----",IF(W$4=$K13,"----->",""))) -> ------- | X13: =IF(AND(X$3>$J13,X$4<$K13),"------------",IF(X$3=$J13,"<-----",IF(X$4=$K13,"----->",""))) -> ------------ | Y13: =IF(AND(Y$3>$J13,Y$4<$K13),"-------",IF(Y$3=$J13,"<-----",IF(Y$4=$K13,"----->",""))) -> ------- | Z13: =IF(AND(Z$3>$J13,Z$4<$K13),"-------",IF(Z$3=$J13,"<-----",IF(Z$4=$K13,"----->",""))) -> -----> | AA13: =IF(AND(AA$3>$J13,AA$4<$K13),"-------",IF(AA$3=$J13,"<-----",IF(AA$4=$K13,"----->",""))) | AB13: =IF(AND(AB$3>$J13,AB$4<$K13),"-------",IF(AB$3=$J13,"<-----",IF(AB$4=$K13,"----->",""))) | AC13: =IF(AND(AC$3>$J13,AC$4<$K13),"-------",IF(AC$3=$J13,"<-----",IF(AC$4=$K13,"----->",""))) | AD13: =IF(AND(AD$3>$J13,AD$4<$K13),"-------",IF(AD$3=$J13,"<-----",IF(AD$4=$K13,"----->",""))) | AE13: =IF(AND(AE$3>$J13,AE$4<$K13),"-------",IF(AE$3=$J13,"<-----",IF(AE$4=$K13,"----->",""))) | AF13: =IF(AND(AF$3>$J13,AF$4<$K13),"-------",IF(AF$3=$J13,"<-----",IF(AF$4=$K13,"----->",""))) | ... AT13: =IF(AND(AT$3>$J13,AT$4<$K13),"-------",IF(AT$3=$J13,"<-----",IF(AT$4=$K13,"----->","")))
A14: Dinner | B14: 0.369 | C14: =+$D$5*C$10*$B14 -> 1217700 | D14: =+$D$5*D$10*$B14 -> 1549800 | E14: =+$D$5*E$10*$B14 -> 922500 | F14: =SUM(C14:E14) -> 3690000 | I14: Make 2 | J14: 1600 | K14: 2000 | L14: =(COUNTA(M14:AT14)-COUNTIF(M14:AT14,""))/2 -> 4 | M14: =IF(AND(M$3>$J14,M$4<$K14),"-------",IF(M$3=$J14,"<-----",IF(M$4=$K14,"----->",""))) | N14: =IF(AND(N$3>$J14,N$4<$K14),"-------",IF(N$3=$J14,"<-----",IF(N$4=$K14,"----->",""))) | O14: =IF(AND(O$3>$J14,O$4<$K14),"-------",IF(O$3=$J14,"<-----",IF(O$4=$K14,"----->",""))) | P14: =IF(AND(P$3>$J14,P$4<$K14),"-------",IF(P$3=$J14,"<-----",IF(P$4=$K14,"----->",""))) | Q14: =IF(AND(Q$3>$J14,Q$4<$K14),"-------",IF(Q$3=$J14,"<-----",IF(Q$4=$K14,"----->",""))) | R14: =IF(AND(R$3>$J14,R$4<$K14),"-------",IF(R$3=$J14,"<-----",IF(R$4=$K14,"----->",""))) | S14: =IF(AND(S$3>$J14,S$4<$K14),"-------",IF(S$3=$J14,"<-----",IF(S$4=$K14,"----->",""))) | T14: =IF(AND(T$3>$J14,T$4<$K14),"-------",IF(T$3=$J14,"<-----",IF(T$4=$K14,"----->",""))) | ... AC14: =IF(AND(AC$3>$J14,AC$4<$K14),"-------",IF(AC$3=$J14,"<-----",IF(AC$4=$K14,"----->",""))) | AD14: =IF(AND(AD$3>$J14,AD$4<$K14),"-----------",IF(AD$3=$J14,"<-----",IF(AD$4=$K14,"----->",""))) | AE14: =IF(AND(AE$3>$J14,AE$4<$K14),"-------",IF(AE$3=$J14,"<-----",IF(AE$4=$K14,"----->",""))) -> <----- | AF14: =IF(AND(AF$3>$J14,AF$4<$K14),"-------",IF(AF$3=$J14,"<-----",IF(AF$4=$K14,"----->",""))) -> ------- | AG14: =IF(AND(AG$3>$J14,AG$4<$K14),"-------",IF(AG$3=$J14,"<-----",IF(AG$4=$K14,"----->",""))) -> ------- | AH14: =IF(AND(AH$3>$J14,AH$4<$K14),"-------",IF(AH$3=$J14,"<-----",IF(AH$4=$K14,"----->",""))) -> ------- | AI14: =IF(AND(AI$3>$J14,AI$4<$K14),"-------",IF(AI$3=$J14,"<-----",IF(AI$4=$K14,"----->",""))) -> ------- | AJ14: =IF(AND(AJ$3>$J14,AJ$4<$K14),"-------------",IF(AJ$3=$J14,"<-----",IF(AJ$4=$K14,"----->",""))) -> ------------- | AK14: =IF(AND(AK$3>$J14,AK$4<$K14),"-------",IF(AK$3=$J14,"<-----",IF(AK$4=$K14,"----->",""))) -> ------- | AL14: =IF(AND(AL$3>$J14,AL$4<$K14),"-------",IF(AL$3=$J14,"<-----",IF(AL$4=$K14,"----->",""))) -> -----> | AM14: =IF(AND(AM$3>$J14,AM$4<$K14),"-------",IF(AM$3=$J14,"<-----",IF(AM$4=$K14,"----->",""))) | AN14: =IF(AND(AN$3>$J14,AN$4<$K14),"-------",IF(AN$3=$J14,"<-----",IF(AN$4=$K14,"----->",""))) | AO14: =IF(AND(AO$3>$J14,AO$4<$K14),"-------",IF(AO$3=$J14,"<-----",IF(AO$4=$K14,"----->",""))) | AP14: =IF(AND(AP$3>$J14,AP$4<$K14),"-------",IF(AP$3=$J14,"<-----",IF(AP$4=$K14,"----->",""))) | AQ14: =IF(AND(AQ$3>$J14,AQ$4<$K14),"-------",IF(AQ$3=$J14,"<-----",IF(AQ$4=$K14,"----->",""))) | AR14: =IF(AND(AR$3>$J14,AR$4<$K14),"-------",IF(AR$3=$J14,"<-----",IF(AR$4=$K14,"----->",""))) | ... AT14: =IF(AND(AT$3>$J14,AT$4<$K14),"-------",IF(AT$3=$J14,"<-----",IF(AT$4=$K14,"----->","")))
A15: Late Dinner | C15: =+$D$5*C$10*$B15 -> 0 | D15: =+$D$5*D$10*$B15 -> 0 | E15: =+$D$5*E$10*$B15 -> 0 | F15: =SUM(C15:E15) -> 0 | I15: Make 3 | J15: 1800 | K15: 2300 | L15: =(COUNTA(M15:AT15)-COUNTIF(M15:AT15,""))/2 -> 5 | M15: =IF(AND(M$3>$J15,M$4<$K15),"-------",IF(M$3=$J15,"<-----",IF(M$4=$K15,"----->",""))) | N15: =IF(AND(N$3>$J15,N$4<$K15),"-------",IF(N$3=$J15,"<-----",IF(N$4=$K15,"----->",""))) | O15: =IF(AND(O$3>$J15,O$4<$K15),"-------",IF(O$3=$J15,"<-----",IF(O$4=$K15,"----->",""))) | P15: =IF(AND(P$3>$J15,P$4<$K15),"-------",IF(P$3=$J15,"<-----",IF(P$4=$K15,"----->",""))) | Q15: =IF(AND(Q$3>$J15,Q$4<$K15),"-------",IF(Q$3=$J15,"<-----",IF(Q$4=$K15,"----->",""))) | R15: =IF(AND(R$3>$J15,R$4<$K15),"-------",IF(R$3=$J15,"<-----",IF(R$4=$K15,"----->",""))) | S15: =IF(AND(S$3>$J15,S$4<$K15),"-------",IF(S$3=$J15,"<-----",IF(S$4=$K15,"----->",""))) | T15: =IF(AND(T$3>$J15,T$4<$K15),"-------",IF(T$3=$J15,"<-----",IF(T$4=$K15,"----->",""))) | ... AI15: =IF(AND(AI$3>$J15,AI$4<$K15),"-------",IF(AI$3=$J15,"<-----",IF(AI$4=$K15,"----->",""))) -> <----- | AJ15: =IF(AND(AJ$3>$J15,AJ$4<$K15),"-------------",IF(AJ$3=$J15,"<-----",IF(AJ$4=$K15,"----->",""))) -> ------------- | AK15: =IF(AND(AK$3>$J15,AK$4<$K15),"-------",IF(AK$3=$J15,"<-----",IF(AK$4=$K15,"----->",""))) -> ------- | AL15: =IF(AND(AL$3>$J15,AL$4<$K15),"-------",IF(AL$3=$J15,"<-----",IF(AL$4=$K15,"----->",""))) -> ------- | AM15: =IF(AND(AM$3>$J15,AM$4<$K15),"-------",IF(AM$3=$J15,"<-----",IF(AM$4=$K15,"----->",""))) -> ------- | AN15: =IF(AND(AN$3>$J15,AN$4<$K15),"-------",IF(AN$3=$J15,"<-----",IF(AN$4=$K15,"----->",""))) -> ------- | AO15: =IF(AND(AO$3>$J15,AO$4<$K15),"-------",IF(AO$3=$J15,"<-----",IF(AO$4=$K15,"----->",""))) -> ------- | AP15: =IF(AND(AP$3>$J15,AP$4<$K15),"-------------",IF(AP$3=$J15,"<-----",IF(AP$4=$K15,"----->",""))) -> ------------- | AQ15: =IF(AND(AQ$3>$J15,AQ$4<$K15),"---------",IF(AQ$3=$J15,"<-----",IF(AQ$4=$K15,"--------->",""))) -> --------- | AR15: =IF(AND(AR$3>$J15,AR$4<$K15),"-------",IF(AR$3=$J15,"<-----",IF(AR$4=$K15,"----->",""))) -> -----> | AS15: =IF(AND(AS$3>$J15,AS$4<$K15),"-------",IF(AS$3=$J15,"<-----",IF(AS$4=$K15,"----->",""))) | AT15: =IF(AND(AT$3>$J15,AT$4<$K15),"-------",IF(AT$3=$J15,"<-----",IF(AT$4=$K15,"----->","")))
A16: Grand Total | B16: =SUM(B11:B15) -> 1 | C16: =SUM(C11:C15) -> 3300000 | D16: =SUM(D11:D15) -> 4200000 | E16: =SUM(E11:E15) -> 2500000 | F16: =SUM(F11:F15) -> 10000000 | I16: Make 4 | L16: =(COUNTA(M16:AT16)-COUNTIF(M16:AT16,""))/2 -> 0 | M16: =IF(AND(M$3>$J16,M$4<$K16),"-------",IF(M$3=$J16,"<-----",IF(M$4=$K16,"----->",""))) | N16: =IF(AND(N$3>$J16,N$4<$K16),"-------",IF(N$3=$J16,"<-----",IF(N$4=$K16,"----->",""))) | O16: =IF(AND(O$3>$J16,O$4<$K16),"-------",IF(O$3=$J16,"<-----",IF(O$4=$K16,"----->",""))) | P16: =IF(AND(P$3>$J16,P$4<$K16),"-------",IF(P$3=$J16,"<-----",IF(P$4=$K16,"----->",""))) | Q16: =IF(AND(Q$3>$J16,Q$4<$K16),"-------",IF(Q$3=$J16,"<-----",IF(Q$4=$K16,"----->",""))) | R16: =IF(AND(R$3>$J16,R$4<$K16),"-------",IF(R$3=$J16,"<-----",IF(R$4=$K16,"----->",""))) | S16: =IF(AND(S$3>$J16,S$4<$K16),"-------",IF(S$3=$J16,"<-----",IF(S$4=$K16,"----->",""))) | T16: =IF(AND(T$3>$J16,T$4<$K16),"-------",IF(T$3=$J16,"<-----",IF(T$4=$K16,"----->",""))) | ... AT16: =IF(AND(AT$3>$J16,AT$4<$K16),"-------",IF(AT$3=$J16,"<-----",IF(AT$4=$K16,"----->","")))
L17: =(COUNTA(M17:AT17)-COUNTIF(M17:AT17,""))/2 -> 0 | M17: =IF(AND(M$3>$J17,M$4<$K17),"-------",IF(M$3=$J17,"<-----",IF(M$4=$K17,"----->",""))) | N17: =IF(AND(N$3>$J17,N$4<$K17),"-------",IF(N$3=$J17,"<-----",IF(N$4=$K17,"----->",""))) | O17: =IF(AND(O$3>$J17,O$4<$K17),"-------",IF(O$3=$J17,"<-----",IF(O$4=$K17,"----->",""))) | P17: =IF(AND(P$3>$J17,P$4<$K17),"-------",IF(P$3=$J17,"<-----",IF(P$4=$K17,"----->",""))) | Q17: =IF(AND(Q$3>$J17,Q$4<$K17),"-------",IF(Q$3=$J17,"<-----",IF(Q$4=$K17,"----->",""))) | R17: =IF(AND(R$3>$J17,R$4<$K17),"-------",IF(R$3=$J17,"<-----",IF(R$4=$K17,"----->",""))) | S17: =IF(AND(S$3>$J17,S$4<$K17),"-------",IF(S$3=$J17,"<-----",IF(S$4=$K17,"----->",""))) | T17: =IF(AND(T$3>$J17,T$4<$K17),"-------",IF(T$3=$J17,"<-----",IF(T$4=$K17,"----->",""))) | ... AT17: =IF(AND(AT$3>$J17,AT$4<$K17),"-------",IF(AT$3=$J17,"<-----",IF(AT$4=$K17,"----->","")))
A18: Labor Hours | C18: Suggestion working hour | E18: Actual schedule | L18: =(COUNTA(M18:AT18)-COUNTIF(M18:AT18,""))/2 -> 0 | M18: =IF(AND(M$3>$J18,M$4<$K18),"-------",IF(M$3=$J18,"<-----",IF(M$4=$K18,"----->",""))) | N18: =IF(AND(N$3>$J18,N$4<$K18),"-------",IF(N$3=$J18,"<-----",IF(N$4=$K18,"----->",""))) | O18: =IF(AND(O$3>$J18,O$4<$K18),"-------",IF(O$3=$J18,"<-----",IF(O$4=$K18,"----->",""))) | P18: =IF(AND(P$3>$J18,P$4<$K18),"-------",IF(P$3=$J18,"<-----",IF(P$4=$K18,"----->",""))) | Q18: =IF(AND(Q$3>$J18,Q$4<$K18),"-------",IF(Q$3=$J18,"<-----",IF(Q$4=$K18,"----->",""))) | R18: =IF(AND(R$3>$J18,R$4<$K18),"-------",IF(R$3=$J18,"<-----",IF(R$4=$K18,"----->",""))) | S18: =IF(AND(S$3>$J18,S$4<$K18),"-------",IF(S$3=$J18,"<-----",IF(S$4=$K18,"----->",""))) | T18: =IF(AND(T$3>$J18,T$4<$K18),"-------",IF(T$3=$J18,"<-----",IF(T$4=$K18,"----->",""))) | ... AT18: =IF(AND(AT$3>$J18,AT$4<$K18),"-------",IF(AT$3=$J18,"<-----",IF(AT$4=$K18,"----->","")))
C19: by day part | D19: by shift | E19: by day part | F19: by shift | L19: =(COUNTA(M19:AT19)-COUNTIF(M19:AT19,""))/2 -> 0 | M19: =IF(AND(M$3>$J19,M$4<$K19),"-------",IF(M$3=$J19,"<-----",IF(M$4=$K19,"----->",""))) | N19: =IF(AND(N$3>$J19,N$4<$K19),"-------",IF(N$3=$J19,"<-----",IF(N$4=$K19,"----->",""))) | O19: =IF(AND(O$3>$J19,O$4<$K19),"-------",IF(O$3=$J19,"<-----",IF(O$4=$K19,"----->",""))) | P19: =IF(AND(P$3>$J19,P$4<$K19),"-------",IF(P$3=$J19,"<-----",IF(P$4=$K19,"----->",""))) | Q19: =IF(AND(Q$3>$J19,Q$4<$K19),"-------",IF(Q$3=$J19,"<-----",IF(Q$4=$K19,"----->",""))) | R19: =IF(AND(R$3>$J19,R$4<$K19),"-------",IF(R$3=$J19,"<-----",IF(R$4=$K19,"----->",""))) | S19: =IF(AND(S$3>$J19,S$4<$K19),"-------",IF(S$3=$J19,"<-----",IF(S$4=$K19,"----->",""))) | T19: =IF(AND(T$3>$J19,T$4<$K19),"-------",IF(T$3=$J19,"<-----",IF(T$4=$K19,"----->",""))) | ... AT19: =IF(AND(AT$3>$J19,AT$4<$K19),"-------",IF(AT$3=$J19,"<-----",IF(AT$4=$K19,"----->","")))
A20: Early Lunch | B20: =B11 -> 0.188 | C20: =($C$5*B20)*3 -> 39.48 | D20: =C20+C21 -> 52.01 | E20: =(SUM(M5:T5))/2 -> 10 | F20: =E20+E21 -> 25 | H20: RIDERS | I20: Dough/Rider 1 | J20: 800 | K20: 1300 | L20: =(COUNTA(M20:AT20)-COUNTIF(M20:AT20,""))/2 -> 5 | M20: =IF(AND(M$3>$J20,M$4<$K20),"-------",IF(M$3=$J20,"<-----",IF(M$4=$K20,"----->",""))) | N20: =IF(AND(N$3>$J20,N$4<$K20),"-------",IF(N$3=$J20,"<-----",IF(N$4=$K20,"----->",""))) | O20: =IF(AND(O$3>$J20,O$4<$K20),"-------",IF(O$3=$J20,"<-----",IF(O$4=$K20,"----->",""))) -> <----- | P20: =IF(AND(P$3>$J20,P$4<$K20),"-------",IF(P$3=$J20,"<-----",IF(P$4=$K20,"----->",""))) -> ------- | Q20: =IF(AND(Q$3>$J20,Q$4<$K20),"-------",IF(Q$3=$J20,"<-----",IF(Q$4=$K20,"----->",""))) -> ------- | R20: =IF(AND(R$3>$J20,R$4<$K20),"------------",IF(R$3=$J20,"<-----",IF(R$4=$K20,"----->",""))) -> ------------ | S20: =IF(AND(S$3>$J20,S$4<$K20),"-------",IF(S$3=$J20,"<-----",IF(S$4=$K20,"----->",""))) -> ------- | T20: =IF(AND(T$3>$J20,T$4<$K20),"-------",IF(T$3=$J20,"<-----",IF(T$4=$K20,"----->",""))) -> ------- | U20: =IF(AND(U$3>$J20,U$4<$K20),"-------",IF(U$3=$J20,"<-----",IF(U$4=$K20,"----->",""))) -> ------- | V20: =IF(AND(V$3>$J20,V$4<$K20),"-------",IF(V$3=$J20,"<-----",IF(V$4=$K20,"----->",""))) -> ------- | W20: =IF(AND(W$3>$J20,W$4<$K20),"-------",IF(W$3=$J20,"<-----",IF(W$4=$K20,"----->",""))) -> ------- | X20: =IF(AND(X$3>$J20,X$4<$K20),"-------",IF(X$3=$J20,"<-----",IF(X$4=$K20,"---------->",""))) -> ----------> | Y20: =IF(AND(Y$3>$J20,Y$4<$K20),"-------",IF(Y$3=$J20,"<-----",IF(Y$4=$K20,"----->",""))) | Z20: =IF(AND(Z$3>$J20,Z$4<$K20),"-------",IF(Z$3=$J20,"<-----",IF(Z$4=$K20,"----->",""))) | AA20: =IF(AND(AA$3>$J20,AA$4<$K20),"-------",IF(AA$3=$J20,"<-----",IF(AA$4=$K20,"----->",""))) | AB20: =IF(AND(AB$3>$J20,AB$4<$K20),"-------",IF(AB$3=$J20,"<-----",IF(AB$4=$K20,"----->",""))) | AC20: =IF(AND(AC$3>$J20,AC$4<$K20),"-------",IF(AC$3=$J20,"<-----",IF(AC$4=$K20,"----->",""))) | AD20: =IF(AND(AD$3>$J20,AD$4<$K20),"-------",IF(AD$3=$J20,"<-----",IF(AD$4=$K20,"----->",""))) | AE20: =IF(AND(AE$3>$J20,AE$4<$K20),"-------",IF(AE$3=$J20,"<-----",IF(AE$4=$K20,"----->",""))) | AF20: =IF(AND(AF$3>$J20,AF$4<$K20),"-------",IF(AF$3=$J20,"<-----",IF(AF$4=$K20,"----->",""))) | ... AT20: =IF(AND(AT$3>$J20,AT$4<$K20),"-------",IF(AT$3=$J20,"<-----",IF(AT$4=$K20,"----->","")))
A21: Lunch | B21: =B12 -> 0.179 | C21: =$C$5*B21 -> 12.53 | E21: =(SUM(U5:Z5))/2 -> 15 | I21: Dough/Rider 2 | J21: 1530 | K21: 2000 | L21: =(COUNTA(M21:AT21)-COUNTIF(M21:AT21,""))/2 -> 4.5 | M21: =IF(AND(M$3>$J21,M$4<$K21),"-------",IF(M$3=$J21,"<-----",IF(M$4=$K21,"----->",""))) | N21: =IF(AND(N$3>$J21,N$4<$K21),"-------",IF(N$3=$J21,"<-----",IF(N$4=$K21,"----->",""))) | O21: =IF(AND(O$3>$J21,O$4<$K21),"-------",IF(O$3=$J21,"<-----",IF(O$4=$K21,"----->",""))) | P21: =IF(AND(P$3>$J21,P$4<$K21),"-------",IF(P$3=$J21,"<-----",IF(P$4=$K21,"----->",""))) | Q21: =IF(AND(Q$3>$J21,Q$4<$K21),"-------",IF(Q$3=$J21,"<-----",IF(Q$4=$K21,"----->",""))) | R21: =IF(AND(R$3>$J21,R$4<$K21),"-------",IF(R$3=$J21,"<-----",IF(R$4=$K21,"----->",""))) | S21: =IF(AND(S$3>$J21,S$4<$K21),"-------",IF(S$3=$J21,"<-----",IF(S$4=$K21,"----->",""))) | T21: =IF(AND(T$3>$J21,T$4<$K21),"-------",IF(T$3=$J21,"<-----",IF(T$4=$K21,"----->",""))) | ... AC21: =IF(AND(AC$3>$J21,AC$4<$K21),"-------",IF(AC$3=$J21,"<-----",IF(AC$4=$K21,"----->",""))) | AD21: =IF(AND(AD$3>$J21,AD$4<$K21),"-------",IF(AD$3=$J21,"<----------",IF(AD$4=$K21,"----->",""))) -> <---------- | AE21: =IF(AND(AE$3>$J21,AE$4<$K21),"-------",IF(AE$3=$J21,"<-----",IF(AE$4=$K21,"----->",""))) -> ------- | AF21: =IF(AND(AF$3>$J21,AF$4<$K21),"-------",IF(AF$3=$J21,"<-----",IF(AF$4=$K21,"----->",""))) -> ------- | AG21: =IF(AND(AG$3>$J21,AG$4<$K21),"-------",IF(AG$3=$J21,"<-----",IF(AG$4=$K21,"----->",""))) -> ------- | AH21: =IF(AND(AH$3>$J21,AH$4<$K21),"-------",IF(AH$3=$J21,"<-----",IF(AH$4=$K21,"----->",""))) -> ------- | AI21: =IF(AND(AI$3>$J21,AI$4<$K21),"-------",IF(AI$3=$J21,"<-----",IF(AI$4=$K21,"----->",""))) -> ------- | AJ21: =IF(AND(AJ$3>$J21,AJ$4<$K21),"-------------",IF(AJ$3=$J21,"<-----",IF(AJ$4=$K21,"----->",""))) -> ------------- | AK21: =IF(AND(AK$3>$J21,AK$4<$K21),"-------",IF(AK$3=$J21,"<-----",IF(AK$4=$K21,"----->",""))) -> ------- | AL21: =IF(AND(AL$3>$J21,AL$4<$K21),"-------",IF(AL$3=$J21,"<-----",IF(AL$4=$K21,"----->",""))) -> -----> | AM21: =IF(AND(AM$3>$J21,AM$4<$K21),"-------",IF(AM$3=$J21,"<-----",IF(AM$4=$K21,"----->",""))) | AN21: =IF(AND(AN$3>$J21,AN$4<$K21),"-------",IF(AN$3=$J21,"<-----",IF(AN$4=$K21,"----->",""))) | AO21: =IF(AND(AO$3>$J21,AO$4<$K21),"-------",IF(AO$3=$J21,"<-----",IF(AO$4=$K21,"----->",""))) | AP21: =IF(AND(AP$3>$J21,AP$4<$K21),"-------",IF(AP$3=$J21,"<-----",IF(AP$4=$K21,"----->",""))) | AQ21: =IF(AND(AQ$3>$J21,AQ$4<$K21),"-------",IF(AQ$3=$J21,"<-----",IF(AQ$4=$K21,"----->",""))) | AR21: =IF(AND(AR$3>$J21,AR$4<$K21),"-------",IF(AR$3=$J21,"<-----",IF(AR$4=$K21,"----->",""))) | ... AT21: =IF(AND(AT$3>$J21,AT$4<$K21),"-------",IF(AT$3=$J21,"<-----",IF(AT$4=$K21,"----->","")))
A22: Tea | B22: =B13 -> 0.264 | C22: =$C$5*B22 -> 18.48 | E22: =(SUM(AA5:AF5))/2 -> 11 | F22: =E22 -> 11 | I22: Dough/Rider 3 | L22: =(COUNTA(M22:AT22)-COUNTIF(M22:AT22,""))/2 -> 0 | M22: =IF(AND(M$3>$J22,M$4<$K22),"-------",IF(M$3=$J22,"<-----",IF(M$4=$K22,"----->",""))) | N22: =IF(AND(N$3>$J22,N$4<$K22),"-------",IF(N$3=$J22,"<-----",IF(N$4=$K22,"----->",""))) | O22: =IF(AND(O$3>$J22,O$4<$K22),"-------",IF(O$3=$J22,"<-----",IF(O$4=$K22,"----->",""))) | P22: =IF(AND(P$3>$J22,P$4<$K22),"-------",IF(P$3=$J22,"<-----",IF(P$4=$K22,"----->",""))) | Q22: =IF(AND(Q$3>$J22,Q$4<$K22),"-------",IF(Q$3=$J22,"<-----",IF(Q$4=$K22,"----->",""))) | R22: =IF(AND(R$3>$J22,R$4<$K22),"-------",IF(R$3=$J22,"<-----",IF(R$4=$K22,"----->",""))) | S22: =IF(AND(S$3>$J22,S$4<$K22),"-------",IF(S$3=$J22,"<-----",IF(S$4=$K22,"----->",""))) | T22: =IF(AND(T$3>$J22,T$4<$K22),"-------",IF(T$3=$J22,"<-----",IF(T$4=$K22,"----->",""))) | ... AT22: =IF(AND(AT$3>$J22,AT$4<$K22),"-------",IF(AT$3=$J22,"<-----",IF(AT$4=$K22,"----->","")))
A23: Dinner | B23: =B14 -> 0.369 | C23: =($C$5*B23)/1.5 -> 17.22 | D23: =SUM(C22:C24) -> 17.99 | E23: =(SUM(AG5:AL5))/2 -> 22 | F23: =SUM(E23:E24) -> 34 | L23: =(COUNTA(M23:AT23)-COUNTIF(M23:AT23,""))/2 -> 0 | M23: =IF(AND(M$3>$J23,M$4<$K23),"-------",IF(M$3=$J23,"<-----",IF(M$4=$K23,"----->",""))) | N23: =IF(AND(N$3>$J23,N$4<$K23),"-------",IF(N$3=$J23,"<-----",IF(N$4=$K23,"----->",""))) | O23: =IF(AND(O$3>$J23,O$4<$K23),"-------",IF(O$3=$J23,"<-----",IF(O$4=$K23,"----->",""))) | P23: =IF(AND(P$3>$J23,P$4<$K23),"-------",IF(P$3=$J23,"<-----",IF(P$4=$K23,"----->",""))) | Q23: =IF(AND(Q$3>$J23,Q$4<$K23),"-------",IF(Q$3=$J23,"<-----",IF(Q$4=$K23,"----->",""))) | R23: =IF(AND(R$3>$J23,R$4<$K23),"-------",IF(R$3=$J23,"<-----",IF(R$4=$K23,"----->",""))) | S23: =IF(AND(S$3>$J23,S$4<$K23),"-------",IF(S$3=$J23,"<-----",IF(S$4=$K23,"----->",""))) | T23: =IF(AND(T$3>$J23,T$4<$K23),"-------",IF(T$3=$J23,"<-----",IF(T$4=$K23,"----->",""))) | ... AT23: =IF(AND(AT$3>$J23,AT$4<$K23),"-------",IF(AT$3=$J23,"<-----",IF(AT$4=$K23,"----->","")))
A24: Late Dinner | B24: =B15 -> 0 | C24: =C5-C20-C21-C22-C23 -> -17.71 | E24: =(SUM(AM5:AT5))/2 -> 12 | L24: =(COUNTA(M24:AT24)-COUNTIF(M24:AT24,""))/2 -> 0 | M24: =IF(AND(M$3>$J24,M$4<$K24),"-------",IF(M$3=$J24,"<-----",IF(M$4=$K24,"----->",""))) | N24: =IF(AND(N$3>$J24,N$4<$K24),"-------",IF(N$3=$J24,"<-----",IF(N$4=$K24,"----->",""))) | O24: =IF(AND(O$3>$J24,O$4<$K24),"-------",IF(O$3=$J24,"<-----",IF(O$4=$K24,"----->",""))) | P24: =IF(AND(P$3>$J24,P$4<$K24),"-------",IF(P$3=$J24,"<-----",IF(P$4=$K24,"----->",""))) | Q24: =IF(AND(Q$3>$J24,Q$4<$K24),"-------",IF(Q$3=$J24,"<-----",IF(Q$4=$K24,"----->",""))) | R24: =IF(AND(R$3>$J24,R$4<$K24),"-------",IF(R$3=$J24,"<-----",IF(R$4=$K24,"----->",""))) | S24: =IF(AND(S$3>$J24,S$4<$K24),"-------",IF(S$3=$J24,"<-----",IF(S$4=$K24,"----->",""))) | T24: =IF(AND(T$3>$J24,T$4<$K24),"-------",IF(T$3=$J24,"<-----",IF(T$4=$K24,"----->",""))) | ... AT24: =IF(AND(AT$3>$J24,AT$4<$K24),"-------",IF(AT$3=$J24,"<-----",IF(AT$4=$K24,"----->","")))
A25: Grand Total | C25: =SUM(C20:C24) -> 70 | D25: =SUM(D20:D24) -> 70 | E25: =SUM(E20:E24) -> 70 | F25: =SUM(F20:F24) -> 70 | L25: =(COUNTA(M25:AT25)-COUNTIF(M25:AT25,""))/2 -> 0 | M25: =IF(AND(M$3>$J25,M$4<$K25),"-------",IF(M$3=$J25,"<-----",IF(M$4=$K25,"----->",""))) | N25: =IF(AND(N$3>$J25,N$4<$K25),"-------",IF(N$3=$J25,"<-----",IF(N$4=$K25,"----->",""))) | O25: =IF(AND(O$3>$J25,O$4<$K25),"-------",IF(O$3=$J25,"<-----",IF(O$4=$K25,"----->",""))) | P25: =IF(AND(P$3>$J25,P$4<$K25),"-------",IF(P$3=$J25,"<-----",IF(P$4=$K25,"----->",""))) | Q25: =IF(AND(Q$3>$J25,Q$4<$K25),"-------",IF(Q$3=$J25,"<-----",IF(Q$4=$K25,"----->",""))) | R25: =IF(AND(R$3>$J25,R$4<$K25),"-------",IF(R$3=$J25,"<-----",IF(R$4=$K25,"----->",""))) | S25: =IF(AND(S$3>$J25,S$4<$K25),"-------",IF(S$3=$J25,"<-----",IF(S$4=$K25,"----->",""))) | T25: =IF(AND(T$3>$J25,T$4<$K25),"-------",IF(T$3=$J25,"<-----",IF(T$4=$K25,"----->",""))) | ... AT25: =IF(AND(AT$3>$J25,AT$4<$K25),"-------",IF(AT$3=$J25,"<-----",IF(AT$4=$K25,"----->","")))
L26: =(COUNTA(M26:AT26)-COUNTIF(M26:AT26,""))/2 -> 0 | M26: =IF(AND(M$3>$J26,M$4<$K26),"-------",IF(M$3=$J26,"<-----",IF(M$4=$K26,"----->",""))) | N26: =IF(AND(N$3>$J26,N$4<$K26),"-------",IF(N$3=$J26,"<-----",IF(N$4=$K26,"----->",""))) | O26: =IF(AND(O$3>$J26,O$4<$K26),"-------",IF(O$3=$J26,"<-----",IF(O$4=$K26,"----->",""))) | P26: =IF(AND(P$3>$J26,P$4<$K26),"-------",IF(P$3=$J26,"<-----",IF(P$4=$K26,"----->",""))) | Q26: =IF(AND(Q$3>$J26,Q$4<$K26),"-------",IF(Q$3=$J26,"<-----",IF(Q$4=$K26,"----->",""))) | R26: =IF(AND(R$3>$J26,R$4<$K26),"-------",IF(R$3=$J26,"<-----",IF(R$4=$K26,"----->",""))) | S26: =IF(AND(S$3>$J26,S$4<$K26),"-------",IF(S$3=$J26,"<-----",IF(S$4=$K26,"----->",""))) | T26: =IF(AND(T$3>$J26,T$4<$K26),"-------",IF(T$3=$J26,"<-----",IF(T$4=$K26,"----->",""))) | ... AT26: =IF(AND(AT$3>$J26,AT$4<$K26),"-------",IF(AT$3=$J26,"<-----",IF(AT$4=$K26,"----->","")))
H27: FOH | I27: CSR1/Server | J27: 900 | K27: 1300 | L27: =(COUNTA(M27:AT27)-COUNTIF(M27:AT27,""))/2 -> 4 | M27: =IF(AND(M$3>$J27,M$4<$K27),"-------",IF(M$3=$J27,"<-----",IF(M$4=$K27,"----->",""))) | N27: =IF(AND(N$3>$J27,N$4<$K27),"-------",IF(N$3=$J27,"<-----",IF(N$4=$K27,"----->",""))) | O27: =IF(AND(O$3>$J27,O$4<$K27),"-------",IF(O$3=$J27,"<-----",IF(O$4=$K27,"----->",""))) | P27: =IF(AND(P$3>$J27,P$4<$K27),"-------",IF(P$3=$J27,"<-----",IF(P$4=$K27,"----->",""))) | Q27: =IF(AND(Q$3>$J27,Q$4<$K27),"-------",IF(Q$3=$J27,"<-----",IF(Q$4=$K27,"----->",""))) -> <----- | R27: =IF(AND(R$3>$J27,R$4<$K27),"------------",IF(R$3=$J27,"<-----",IF(R$4=$K27,"----->",""))) -> ------------ | S27: =IF(AND(S$3>$J27,S$4<$K27),"-------",IF(S$3=$J27,"<-----",IF(S$4=$K27,"----->",""))) -> ------- | T27: =IF(AND(T$3>$J27,T$4<$K27),"-------",IF(T$3=$J27,"<-----",IF(T$4=$K27,"----->",""))) -> ------- | U27: =IF(AND(U$3>$J27,U$4<$K27),"-------",IF(U$3=$J27,"<-----",IF(U$4=$K27,"----->",""))) -> ------- | V27: =IF(AND(V$3>$J27,V$4<$K27),"-------",IF(V$3=$J27,"<-----",IF(V$4=$K27,"----->",""))) -> ------- | W27: =IF(AND(W$3>$J27,W$4<$K27),"-------",IF(W$3=$J27,"<-----",IF(W$4=$K27,"----->",""))) -> ------- | X27: =IF(AND(X$3>$J27,X$4<$K27),"-------",IF(X$3=$J27,"<-----",IF(X$4=$K27,"--------->",""))) -> ---------> | Y27: =IF(AND(Y$3>$J27,Y$4<$K27),"-------",IF(Y$3=$J27,"<-----",IF(Y$4=$K27,"----->",""))) | Z27: =IF(AND(Z$3>$J27,Z$4<$K27),"-------",IF(Z$3=$J27,"<-----",IF(Z$4=$K27,"----->",""))) | AA27: =IF(AND(AA$3>$J27,AA$4<$K27),"-------",IF(AA$3=$J27,"<-----",IF(AA$4=$K27,"----->",""))) | AB27: =IF(AND(AB$3>$J27,AB$4<$K27),"-------",IF(AB$3=$J27,"<-----",IF(AB$4=$K27,"----->",""))) | AC27: =IF(AND(AC$3>$J27,AC$4<$K27),"-------",IF(AC$3=$J27,"<-----",IF(AC$4=$K27,"----->",""))) | AD27: =IF(AND(AD$3>$J27,AD$4<$K27),"-------",IF(AD$3=$J27,"<-----",IF(AD$4=$K27,"----->",""))) | AE27: =IF(AND(AE$3>$J27,AE$4<$K27),"-------",IF(AE$3=$J27,"<-----",IF(AE$4=$K27,"----->",""))) | AF27: =IF(AND(AF$3>$J27,AF$4<$K27),"-------",IF(AF$3=$J27,"<-----",IF(AF$4=$K27,"----->",""))) | ... AT27: =IF(AND(AT$3>$J27,AT$4<$K27),"-------",IF(AT$3=$J27,"<-----",IF(AT$4=$K27,"----->","")))
I28: CSR2/Server | J28: 1200 | K28: 1700 | L28: =(COUNTA(M28:AT28)-COUNTIF(M28:AT28,""))/2 -> 5 | M28: =IF(AND(M$3>$J28,M$4<$K28),"-------",IF(M$3=$J28,"<-----",IF(M$4=$K28,"----->",""))) | N28: =IF(AND(N$3>$J28,N$4<$K28),"-------",IF(N$3=$J28,"<-----",IF(N$4=$K28,"----->",""))) | O28: =IF(AND(O$3>$J28,O$4<$K28),"-------",IF(O$3=$J28,"<-----",IF(O$4=$K28,"----->",""))) | P28: =IF(AND(P$3>$J28,P$4<$K28),"-------",IF(P$3=$J28,"<-----",IF(P$4=$K28,"----->",""))) | Q28: =IF(AND(Q$3>$J28,Q$4<$K28),"-------",IF(Q$3=$J28,"<-----",IF(Q$4=$K28,"----->",""))) | R28: =IF(AND(R$3>$J28,R$4<$K28),"-------",IF(R$3=$J28,"<-----",IF(R$4=$K28,"----->",""))) | S28: =IF(AND(S$3>$J28,S$4<$K28),"-------",IF(S$3=$J28,"<-----",IF(S$4=$K28,"----->",""))) | T28: =IF(AND(T$3>$J28,T$4<$K28),"-------",IF(T$3=$J28,"<-----",IF(T$4=$K28,"----->",""))) | ... W28: =IF(AND(W$3>$J28,W$4<$K28),"-------",IF(W$3=$J28,"<-----",IF(W$4=$K28,"----->",""))) -> <----- | X28: =IF(AND(X$3>$J28,X$4<$K28),"------------",IF(X$3=$J28,"<-----",IF(X$4=$K28,"----->",""))) -> ------------ | Y28: =IF(AND(Y$3>$J28,Y$4<$K28),"-------",IF(Y$3=$J28,"<-----",IF(Y$4=$K28,"----->",""))) -> ------- | Z28: =IF(AND(Z$3>$J28,Z$4<$K28),"-------",IF(Z$3=$J28,"<-----",IF(Z$4=$K28,"----->",""))) -> ------- | AA28: =IF(AND(AA$3>$J28,AA$4<$K28),"-------",IF(AA$3=$J28,"<-----",IF(AA$4=$K28,"----->",""))) -> ------- | AB28: =IF(AND(AB$3>$J28,AB$4<$K28),"-------",IF(AB$3=$J28,"<-----",IF(AB$4=$K28,"----->",""))) -> ------- | AC28: =IF(AND(AC$3>$J28,AC$4<$K28),"-------",IF(AC$3=$J28,"<-----",IF(AC$4=$K28,"----->",""))) -> ------- | AD28: =IF(AND(AD$3>$J28,AD$4<$K28),"------------",IF(AD$3=$J28,"<-----",IF(AD$4=$K28,"----->",""))) -> ------------ | AE28: =IF(AND(AE$3>$J28,AE$4<$K28),"-------",IF(AE$3=$J28,"<-----",IF(AE$4=$K28,"----->",""))) -> ------- | AF28: =IF(AND(AF$3>$J28,AF$4<$K28),"-------",IF(AF$3=$J28,"<-----",IF(AF$4=$K28,"----->",""))) -> -----> | AG28: =IF(AND(AG$3>$J28,AG$4<$K28),"-------",IF(AG$3=$J28,"<-----",IF(AG$4=$K28,"----->",""))) | AH28: =IF(AND(AH$3>$J28,AH$4<$K28),"-------",IF(AH$3=$J28,"<-----",IF(AH$4=$K28,"----->",""))) | AI28: =IF(AND(AI$3>$J28,AI$4<$K28),"-------",IF(AI$3=$J28,"<-----",IF(AI$4=$K28,"----->",""))) | AJ28: =IF(AND(AJ$3>$J28,AJ$4<$K28),"-------",IF(AJ$3=$J28,"<-----",IF(AJ$4=$K28,"----->",""))) | AK28: =IF(AND(AK$3>$J28,AK$4<$K28),"-------",IF(AK$3=$J28,"<-----",IF(AK$4=$K28,"----->",""))) | AL28: =IF(AND(AL$3>$J28,AL$4<$K28),"-------",IF(AL$3=$J28,"<-----",IF(AL$4=$K28,"----->",""))) | ... AT28: =IF(AND(AT$3>$J28,AT$4<$K28),"-------",IF(AT$3=$J28,"<-----",IF(AT$4=$K28,"----->","")))
I29: CSR3/Server | J29: 1700 | K29: 2200 | L29: =(COUNTA(M29:AT29)-COUNTIF(M29:AT29,""))/2 -> 5 | M29: =IF(AND(M$3>$J29,M$4<$K29),"-------",IF(M$3=$J29,"<-----",IF(M$4=$K29,"----->",""))) | N29: =IF(AND(N$3>$J29,N$4<$K29),"-------",IF(N$3=$J29,"<-----",IF(N$4=$K29,"----->",""))) | O29: =IF(AND(O$3>$J29,O$4<$K29),"-------",IF(O$3=$J29,"<-----",IF(O$4=$K29,"----->",""))) | P29: =IF(AND(P$3>$J29,P$4<$K29),"-------",IF(P$3=$J29,"<-----",IF(P$4=$K29,"----->",""))) | Q29: =IF(AND(Q$3>$J29,Q$4<$K29),"-------",IF(Q$3=$J29,"<-----",IF(Q$4=$K29,"----->",""))) | R29: =IF(AND(R$3>$J29,R$4<$K29),"-------",IF(R$3=$J29,"<-----",IF(R$4=$K29,"----->",""))) | S29: =IF(AND(S$3>$J29,S$4<$K29),"-------",IF(S$3=$J29,"<-----",IF(S$4=$K29,"----->",""))) | T29: =IF(AND(T$3>$J29,T$4<$K29),"-------",IF(T$3=$J29,"<-----",IF(T$4=$K29,"----->",""))) | ... AI29: =IF(AND(AI$3>$J29,AI$4<$K29),"-------",IF(AI$3=$J29,"<-----",IF(AI$4=$K29,"----->",""))) -> ------- | AJ29: =IF(AND(AJ$3>$J29,AJ$4<$K29),"-------------",IF(AJ$3=$J29,"<-----",IF(AJ$4=$K29,"----->",""))) -> ------------- | AK29: =IF(AND(AK$3>$J29,AK$4<$K29),"-------",IF(AK$3=$J29,"<-----",IF(AK$4=$K29,"----->",""))) -> ------- | AL29: =IF(AND(AL$3>$J29,AL$4<$K29),"-------",IF(AL$3=$J29,"<-----",IF(AL$4=$K29,"----->",""))) -> ------- | AM29: =IF(AND(AM$3>$J29,AM$4<$K29),"-------",IF(AM$3=$J29,"<-----",IF(AM$4=$K29,"----->",""))) -> ------- | AN29: =IF(AND(AN$3>$J29,AN$4<$K29),"-------",IF(AN$3=$J29,"<-----",IF(AN$4=$K29,"----->",""))) -> ------- | AO29: =IF(AND(AO$3>$J29,AO$4<$K29),"-------",IF(AO$3=$J29,"<-----",IF(AO$4=$K29,"----->",""))) -> ------- | AP29: =IF(AND(AP$3>$J29,AP$4<$K29),"-------",IF(AP$3=$J29,"<-----",IF(AP$4=$K29,"--------->",""))) -> ---------> | AQ29: =IF(AND(AQ$3>$J29,AQ$4<$K29),"-------",IF(AQ$3=$J29,"<-----",IF(AQ$4=$K29,"----->",""))) | AR29: =IF(AND(AR$3>$J29,AR$4<$K29),"-------",IF(AR$3=$J29,"<-----",IF(AR$4=$K29,"----->",""))) | AS29: =IF(AND(AS$3>$J29,AS$4<$K29),"-------",IF(AS$3=$J29,"<-----",IF(AS$4=$K29,"----->",""))) | AT29: =IF(AND(AT$3>$J29,AT$4<$K29),"-------",IF(AT$3=$J29,"<-----",IF(AT$4=$K29,"----->","")))
I30: CSR4/Server | L30: =(COUNTA(M30:AT30)-COUNTIF(M30:AT30,""))/2 -> 0 | M30: =IF(AND(M$3>$J30,M$4<$K30),"-------",IF(M$3=$J30,"<-----",IF(M$4=$K30,"----->",""))) | N30: =IF(AND(N$3>$J30,N$4<$K30),"-------",IF(N$3=$J30,"<-----",IF(N$4=$K30,"----->",""))) | O30: =IF(AND(O$3>$J30,O$4<$K30),"-------",IF(O$3=$J30,"<-----",IF(O$4=$K30,"----->",""))) | P30: =IF(AND(P$3>$J30,P$4<$K30),"-------",IF(P$3=$J30,"<-----",IF(P$4=$K30,"----->",""))) | Q30: =IF(AND(Q$3>$J30,Q$4<$K30),"-------",IF(Q$3=$J30,"<-----",IF(Q$4=$K30,"----->",""))) | R30: =IF(AND(R$3>$J30,R$4<$K30),"-------",IF(R$3=$J30,"<-----",IF(R$4=$K30,"----->",""))) | S30: =IF(AND(S$3>$J30,S$4<$K30),"-------",IF(S$3=$J30,"<-----",IF(S$4=$K30,"----->",""))) | T30: =IF(AND(T$3>$J30,T$4<$K30),"-------",IF(T$3=$J30,"<-----",IF(T$4=$K30,"----->",""))) | ... AT30: =IF(AND(AT$3>$J30,AT$4<$K30),"-------",IF(AT$3=$J30,"<-----",IF(AT$4=$K30,"----->","")))
I31: Server1/Rider | J31: 1700 | K31: 2100 | L31: =(COUNTA(M31:AT31)-COUNTIF(M31:AT31,""))/2 -> 4 | M31: =IF(AND(M$3>$J31,M$4<$K31),"-------",IF(M$3=$J31,"<-----",IF(M$4=$K31,"----->",""))) | N31: =IF(AND(N$3>$J31,N$4<$K31),"-------",IF(N$3=$J31,"<-----",IF(N$4=$K31,"----->",""))) | O31: =IF(AND(O$3>$J31,O$4<$K31),"-------",IF(O$3=$J31,"<-----",IF(O$4=$K31,"----->",""))) | P31: =IF(AND(P$3>$J31,P$4<$K31),"-------",IF(P$3=$J31,"<-----",IF(P$4=$K31,"----->",""))) | Q31: =IF(AND(Q$3>$J31,Q$4<$K31),"-------",IF(Q$3=$J31,"<-----",IF(Q$4=$K31,"----->",""))) | R31: =IF(AND(R$3>$J31,R$4<$K31),"-------",IF(R$3=$J31,"<-----",IF(R$4=$K31,"----->",""))) | S31: =IF(AND(S$3>$J31,S$4<$K31),"-------",IF(S$3=$J31,"<-----",IF(S$4=$K31,"----->",""))) | T31: =IF(AND(T$3>$J31,T$4<$K31),"-------",IF(T$3=$J31,"<-----",IF(T$4=$K31,"----->",""))) | ... AI31: =IF(AND(AI$3>$J31,AI$4<$K31),"-------",IF(AI$3=$J31,"<-----",IF(AI$4=$K31,"----->",""))) -> ------- | AJ31: =IF(AND(AJ$3>$J31,AJ$4<$K31),"-------------",IF(AJ$3=$J31,"<-----",IF(AJ$4=$K31,"----->",""))) -> ------------- | AK31: =IF(AND(AK$3>$J31,AK$4<$K31),"-------",IF(AK$3=$J31,"<-----",IF(AK$4=$K31,"----->",""))) -> ------- | AL31: =IF(AND(AL$3>$J31,AL$4<$K31),"-------",IF(AL$3=$J31,"<-----",IF(AL$4=$K31,"----->",""))) -> ------- | AM31: =IF(AND(AM$3>$J31,AM$4<$K31),"-------",IF(AM$3=$J31,"<-----",IF(AM$4=$K31,"----->",""))) -> ------- | AN31: =IF(AND(AN$3>$J31,AN$4<$K31),"-------",IF(AN$3=$J31,"<-----",IF(AN$4=$K31,"----->",""))) -> -----> | AO31: =IF(AND(AO$3>$J31,AO$4<$K31),"-------",IF(AO$3=$J31,"<-----",IF(AO$4=$K31,"----->",""))) | AP31: =IF(AND(AP$3>$J31,AP$4<$K31),"-------",IF(AP$3=$J31,"<-----",IF(AP$4=$K31,"----->",""))) | AQ31: =IF(AND(AQ$3>$J31,AQ$4<$K31),"-------",IF(AQ$3=$J31,"<-----",IF(AQ$4=$K31,"----->",""))) | AR31: =IF(AND(AR$3>$J31,AR$4<$K31),"-------",IF(AR$3=$J31,"<-----",IF(AR$4=$K31,"----->",""))) | ... AT31: =IF(AND(AT$3>$J31,AT$4<$K31),"-------",IF(AT$3=$J31,"<-----",IF(AT$4=$K31,"----->","")))
I32: Server2/Rider | J32: 0 | K32: 0 | L32: =(COUNTA(M32:AT32)-COUNTIF(M32:AT32,""))/2 -> 0 | M32: =IF(AND(M$3>$J32,M$4<$K32),"-------",IF(M$3=$J32,"<-----",IF(M$4=$K32,"----->",""))) | N32: =IF(AND(N$3>$J32,N$4<$K32),"-------",IF(N$3=$J32,"<-----",IF(N$4=$K32,"----->",""))) | O32: =IF(AND(O$3>$J32,O$4<$K32),"-------",IF(O$3=$J32,"<-----",IF(O$4=$K32,"----->",""))) | P32: =IF(AND(P$3>$J32,P$4<$K32),"-------",IF(P$3=$J32,"<-----",IF(P$4=$K32,"----->",""))) | Q32: =IF(AND(Q$3>$J32,Q$4<$K32),"-------",IF(Q$3=$J32,"<-----",IF(Q$4=$K32,"----->",""))) | R32: =IF(AND(R$3>$J32,R$4<$K32),"-------",IF(R$3=$J32,"<-----",IF(R$4=$K32,"----->",""))) | S32: =IF(AND(S$3>$J32,S$4<$K32),"-------",IF(S$3=$J32,"<-----",IF(S$4=$K32,"----->",""))) | T32: =IF(AND(T$3>$J32,T$4<$K32),"-------",IF(T$3=$J32,"<-----",IF(T$4=$K32,"----->",""))) | ... AT32: =IF(AND(AT$3>$J32,AT$4<$K32),"-------",IF(AT$3=$J32,"<-----",IF(AT$4=$K32,"----->","")))
I33: Server3/Rider | J33: 1800 | K33: 2200 | L33: =(COUNTA(M33:AT33)-COUNTIF(M33:AT33,""))/2 -> 4 | M33: =IF(AND(M$3>$J33,M$4<$K33),"-------",IF(M$3=$J33,"<-----",IF(M$4=$K33,"----->",""))) | N33: =IF(AND(N$3>$J33,N$4<$K33),"-------",IF(N$3=$J33,"<-----",IF(N$4=$K33,"----->",""))) | O33: =IF(AND(O$3>$J33,O$4<$K33),"-------",IF(O$3=$J33,"<-----",IF(O$4=$K33,"----->",""))) | P33: =IF(AND(P$3>$J33,P$4<$K33),"-------",IF(P$3=$J33,"<-----",IF(P$4=$K33,"----->",""))) | Q33: =IF(AND(Q$3>$J33,Q$4<$K33),"-------",IF(Q$3=$J33,"<-----",IF(Q$4=$K33,"----->",""))) | R33: =IF(AND(R$3>$J33,R$4<$K33),"-------",IF(R$3=$J33,"<-----",IF(R$4=$K33,"----->",""))) | S33: =IF(AND(S$3>$J33,S$4<$K33),"-------",IF(S$3=$J33,"<-----",IF(S$4=$K33,"----->",""))) | T33: =IF(AND(T$3>$J33,T$4<$K33),"-------",IF(T$3=$J33,"<-----",IF(T$4=$K33,"----->",""))) | ... AI33: =IF(AND(AI$3>$J33,AI$4<$K33),"-------",IF(AI$3=$J33,"<-----",IF(AI$4=$K33,"----->",""))) -> <----- | AJ33: =IF(AND(AJ$3>$J33,AJ$4<$K33),"------------",IF(AJ$3=$J33,"<-----",IF(AJ$4=$K33,"----->",""))) -> ------------ | AK33: =IF(AND(AK$3>$J33,AK$4<$K33),"-------",IF(AK$3=$J33,"<-----",IF(AK$4=$K33,"----->",""))) -> ------- | AL33: =IF(AND(AL$3>$J33,AL$4<$K33),"-------",IF(AL$3=$J33,"<-----",IF(AL$4=$K33,"----->",""))) -> ------- | AM33: =IF(AND(AM$3>$J33,AM$4<$K33),"-------",IF(AM$3=$J33,"<-----",IF(AM$4=$K33,"----->",""))) -> ------- | AN33: =IF(AND(AN$3>$J33,AN$4<$K33),"-------",IF(AN$3=$J33,"<-----",IF(AN$4=$K33,"----->",""))) -> ------- | AO33: =IF(AND(AO$3>$J33,AO$4<$K33),"-------",IF(AO$3=$J33,"<-----",IF(AO$4=$K33,"----->",""))) -> ------- | AP33: =IF(AND(AP$3>$J33,AP$4<$K33),"-------",IF(AP$3=$J33,"<-----",IF(AP$4=$K33,"--------->",""))) -> ---------> | AQ33: =IF(AND(AQ$3>$J33,AQ$4<$K33),"-------",IF(AQ$3=$J33,"<-----",IF(AQ$4=$K33,"----->",""))) | AR33: =IF(AND(AR$3>$J33,AR$4<$K33),"-------",IF(AR$3=$J33,"<-----",IF(AR$4=$K33,"----->",""))) | AS33: =IF(AND(AS$3>$J33,AS$4<$K33),"-------",IF(AS$3=$J33,"<-----",IF(AS$4=$K33,"----->",""))) | AT33: =IF(AND(AT$3>$J33,AT$4<$K33),"-------",IF(AT$3=$J33,"<-----",IF(AT$4=$K33,"----->","")))
I34: Server4/Rider | L34: =(COUNTA(M34:AT34)-COUNTIF(M34:AT34,""))/2 -> 0 | M34: =IF(AND(M$3>$J34,M$4<$K34),"-------",IF(M$3=$J34,"<-----",IF(M$4=$K34,"----->",""))) | N34: =IF(AND(N$3>$J34,N$4<$K34),"-------",IF(N$3=$J34,"<-----",IF(N$4=$K34,"----->",""))) | O34: =IF(AND(O$3>$J34,O$4<$K34),"-------",IF(O$3=$J34,"<-----",IF(O$4=$K34,"----->",""))) | P34: =IF(AND(P$3>$J34,P$4<$K34),"-------",IF(P$3=$J34,"<-----",IF(P$4=$K34,"----->",""))) | Q34: =IF(AND(Q$3>$J34,Q$4<$K34),"-------",IF(Q$3=$J34,"<-----",IF(Q$4=$K34,"----->",""))) | R34: =IF(AND(R$3>$J34,R$4<$K34),"-------",IF(R$3=$J34,"<-----",IF(R$4=$K34,"----->",""))) | S34: =IF(AND(S$3>$J34,S$4<$K34),"-------",IF(S$3=$J34,"<-----",IF(S$4=$K34,"----->",""))) | T34: =IF(AND(T$3>$J34,T$4<$K34),"-------",IF(T$3=$J34,"<-----",IF(T$4=$K34,"----->",""))) | ... AT34: =IF(AND(AT$3>$J34,AT$4<$K34),"-------",IF(AT$3=$J34,"<-----",IF(AT$4=$K34,"----->","")))
L35: =(COUNTA(M35:AT35)-COUNTIF(M35:AT35,""))/2 -> 0 | M35: =IF(AND(M$3>$J35,M$4<$K35),"-------",IF(M$3=$J35,"<-----",IF(M$4=$K35,"----->",""))) | N35: =IF(AND(N$3>$J35,N$4<$K35),"-------",IF(N$3=$J35,"<-----",IF(N$4=$K35,"----->",""))) | O35: =IF(AND(O$3>$J35,O$4<$K35),"-------",IF(O$3=$J35,"<-----",IF(O$4=$K35,"----->",""))) | P35: =IF(AND(P$3>$J35,P$4<$K35),"-------",IF(P$3=$J35,"<-----",IF(P$4=$K35,"----->",""))) | Q35: =IF(AND(Q$3>$J35,Q$4<$K35),"-------",IF(Q$3=$J35,"<-----",IF(Q$4=$K35,"----->",""))) | R35: =IF(AND(R$3>$J35,R$4<$K35),"-------",IF(R$3=$J35,"<-----",IF(R$4=$K35,"----->",""))) | S35: =IF(AND(S$3>$J35,S$4<$K35),"-------",IF(S$3=$J35,"<-----",IF(S$4=$K35,"----->",""))) | T35: =IF(AND(T$3>$J35,T$4<$K35),"-------",IF(T$3=$J35,"<-----",IF(T$4=$K35,"----->",""))) | ... AT35: =IF(AND(AT$3>$J35,AT$4<$K35),"-------",IF(AT$3=$J35,"<-----",IF(AT$4=$K35,"----->","")))
L36: =(COUNTA(M36:AT36)-COUNTIF(M36:AT36,""))/2 -> 0 | M36: =IF(AND(M$3>$J36,M$4<$K36),"-------",IF(M$3=$J36,"<-----",IF(M$4=$K36,"----->",""))) | N36: =IF(AND(N$3>$J36,N$4<$K36),"-------",IF(N$3=$J36,"<-----",IF(N$4=$K36,"----->",""))) | O36: =IF(AND(O$3>$J36,O$4<$K36),"-------",IF(O$3=$J36,"<-----",IF(O$4=$K36,"----->",""))) | P36: =IF(AND(P$3>$J36,P$4<$K36),"-------",IF(P$3=$J36,"<-----",IF(P$4=$K36,"----->",""))) | Q36: =IF(AND(Q$3>$J36,Q$4<$K36),"-------",IF(Q$3=$J36,"<-----",IF(Q$4=$K36,"----->",""))) | R36: =IF(AND(R$3>$J36,R$4<$K36),"-------",IF(R$3=$J36,"<-----",IF(R$4=$K36,"----->",""))) | S36: =IF(AND(S$3>$J36,S$4<$K36),"-------",IF(S$3=$J36,"<-----",IF(S$4=$K36,"----->",""))) | T36: =IF(AND(T$3>$J36,T$4<$K36),"-------",IF(T$3=$J36,"<-----",IF(T$4=$K36,"----->",""))) | ... AT36: =IF(AND(AT$3>$J36,AT$4<$K36),"-------",IF(AT$3=$J36,"<-----",IF(AT$4=$K36,"----->","")))

Sheet Prep Plan
C1: Prep Plan (Per Million Usage)
Q2: FROM: | S2: 43430 | V2: TO: | X2: 43436
M3: Notes | O3: Tuesday | T3: Wednesday | Y3: Thursday | AD3: Friday | AI3: Saturday | AN3: Sunday
H4: 10000000 | N4: 22000000 | S4: 25000000 | X4: 27000000 | AC4: 30000000 | AD4: 30000000 | AH4: 50000000 | AI4: 50000000 | AM4: 45000000 | AN4: 50000000
G5: Tồn CN | H5: Số lượng | I5: Thời gian cần chuẩn bị (Phút) | J5: Cách chế biến/chuẩn bị | L5: Số liệu tối thiểu cần chuẩn bị | O5: AM | P5: Tồn | Q5: PM | R5: Tồn | T5: AM | U5: Tồn | V5: PM | W5: Tồn | Y5: AM | Z5: Tồn | AA5: PM | AB5: Tồn | AD5: AM | AE5: Tồn | AF5: PM | AG5: Tồn | AI5: AM | AJ5: Tồn | AK5: PM | AL5: Tồn | AN5: AM | AO5: Tồn | AP5: PM | AQ5: Tồn
A6: 1 | B6: DOUGH | C6: Pan Dough | D6: Batch | E6: 500 | F6: 0.5 | G6: 0 | H6: 1 | I6: 60 | K6: Chuẩn bị nguyên liệu: 5 phút Quay Dough 10 phút Cắt, vò và cán 20 phút/2 người | L6: 1 nửa mẻ | M6: Ca sáng 1 nửa mẻ; Ca chiều 1 nửa mẻ Thời gian 1 nửa mẻ 25p/2 người | N6: =+F6*$N$4/1000000 -> 11 | S6: =+F6*$S$4/1000000 -> 12.5 | X6: =+F6*$X$4/1000000 -> 13.5 | AC6: =+F6*$AC$4/1000000 -> 15 | AD6: 10 | AH6: =+F6*$AH$4/1000000 -> 25 | AM6: =+F6*$AM$4/1000000 -> 22.5
C7: SCP Dough | D7: Batch | H7: 0.5 | I7: 30 | K7: Chuẩn bị nguyên liệu: 5 phút Quay Dough 10 phút Cắt, vò và cán 20 phút/2 người | L7: 1 nửa mẻ | M7: Ca sáng 0.5 mẻ | N7: =+F7*$N$4/1000000 -> 0 | S7: =+F7*$S$4/1000000 -> 0 | X7: =+F7*$X$4/1000000 -> 0 | AC7: =+F7*$AC$4/1000000 -> 0 | AD7: 1.5 | AH7: =+F7*$AH$4/1000000 -> 0 | AM7: =+F7*$AM$4/1000000 -> 0
C8: TnC Dough | D8: Batch | H8: 0.5 | I8: 20 | J8: Thin sau khi trộn xong bảo quản nhiệt độ Phòng 8-18 tiếng sau đó cán ra để được 60 tiếng | K8: Chuẩn bị nguyên liệu: 5 phút Quay Dough 3 phút Chia phần vào túi 5 phút Cán dough 20 phút/2 người | L8: 1 nửa mẻ | M8: Đã chuẩn bị trước Trung bình 4 ngày làm thin 1 lần | N8: =+F8*$N$4/1000000 -> 0 | S8: =+F8*$S$4/1000000 -> 0 | X8: =+F8*$X$4/1000000 -> 0 | AC8: =+F8*$AC$4/1000000 -> 0 | AD8: 1.5 | AH8: =+F8*$AH$4/1000000 -> 0 | AM8: =+F8*$AM$4/1000000 -> 0
C9: HT Dough | D9: Batch | H9: 0.5 | I9: 30 | J9: Dough sau khi làm xong Ủ 45 phút Hãm 16 tiếng Hạn sử dụng 40 tiếng | K9: Chuẩn bị nguyên liệu: 5 phút Quay Dough 8 phút Vò dough + quét dầu: 20 phút/2 người | L9: 1 nửa mẻ | M9: Đã chuẩn bị trước Trung bình 2 ngày làm HT 1 lần | N9: =+F9*$N$4/1000000 -> 0 | S9: =+F9*$S$4/1000000 -> 0 | X9: =+F9*$X$4/1000000 -> 0 | AC9: =+F9*$AC$4/1000000 -> 0 | AD9: 0.5 | AH9: =+F9*$AH$4/1000000 -> 0 | AM9: =+F9*$AM$4/1000000 -> 0
N10: =+F10*$N$4/1000000 -> 0 | S10: =+F10*$S$4/1000000 -> 0 | X10: =+F10*$X$4/1000000 -> 0 | AC10: =+F10*$AC$4/1000000 -> 0 | AD10: 1 | AH10: =+F10*$AH$4/1000000 -> 0 | AM10: =+F10*$AM$4/1000000 -> 0
A11: 2 | B11: CUT | C11: Pizza box_L | D11: Pcs | E11: 500 | F11: 0.5 | G11: 0 | H11: 30 | I11: 5 | J11: 1 Thùng hộp lagre nguyên là 100pcs/ctn | K11: Gấp 1 hộp hết 10s | L11: Không có tối thiểu | M11: Gấp sẵn | N11: =+F11*$N$4/1000000 -> 11 | S11: =+F11*$S$4/1000000 -> 12.5 | X11: =+F11*$X$4/1000000 -> 13.5 | AC11: =+F11*$AC$4/1000000 -> 15 | AD11: 10 | AH11: =+F11*$AH$4/1000000 -> 25 | AM11: =+F11*$AM$4/1000000 -> 22.5
C12: Pizza boox_R | D12: Pcs | H12: 50 | I12: 8 | J12: 1 Thùng hộp Regular nguyên là 200pcs/ctn | K12: Gấp 1 hộp hết 10s | L12: Không có tối thiểu | M12: Gấp sẵn | N12: =+F12*$N$4/1000000 -> 0 | S12: =+F12*$S$4/1000000 -> 0 | X12: =+F12*$X$4/1000000 -> 0 | AC12: =+F12*$AC$4/1000000 -> 0 | AD12: 1.5 | AH12: =+F12*$AH$4/1000000 -> 0 | AM12: =+F12*$AM$4/1000000 -> 0
C13: Pizza box_P | D13: Pcs | H13: 30 | I13: 5 | J13: 1 Thùng hộp Personal nguyên là 200pcs/ctn | K13: Gấp 1 hộp hết 10s | L13: Không có tối thiểu | M13: Gấp sẵn | N13: =+F13*$N$4/1000000 -> 0 | S13: =+F13*$S$4/1000000 -> 0 | X13: =+F13*$X$4/1000000 -> 0 | AC13: =+F13*$AC$4/1000000 -> 0 | AD13: 1.5 | AH13: =+F13*$AH$4/1000000 -> 0 | AM13: =+F13*$AM$4/1000000 -> 0
C14: Parley | D14: Gr | H14: 50 | I14: 5 | J14: Nhặt là rửa sạch và phơi khô sau đó băm nhỏ lá | K14: Chuẩn bị và sơ chế: 3p Băm lá 2p | L14: Không có tối thiểu | M14: Sơ chế, băm nhỏ
N15: =+F15*$N$4/1000000 -> 0 | S15: =+F15*$S$4/1000000 -> 0 | X15: =+F15*$X$4/1000000 -> 0 | AC15: =+F15*$AC$4/1000000 -> 0 | AD15: 1 | AH15: =+F15*$AH$4/1000000 -> 0 | AM15: =+F15*$AM$4/1000000 -> 0
A16: 3 | B16: MAKE | C16: Mozzarella Cheese | D16: Kg | E16: 500 | F16: 0.5 | G16: 0 | H16: =+F16*$H$4/1000000 -> 5 | I16: 0 | J16: Sau khi rã đông, bóp tơi và sử dụng luôn | L16: Không có tối thiểu | M16: Rã đông | N16: =+F16*$N$4/1000000 -> 11 | S16: =+F16*$S$4/1000000 -> 12.5 | X16: =+F16*$X$4/1000000 -> 13.5 | AC16: =+F16*$AC$4/1000000 -> 15 | AD16: 10 | AH16: =+F16*$AH$4/1000000 -> 25 | AM16: =+F16*$AM$4/1000000 -> 22.5
C17: Crab Stick | D17: Kg | E17: 37.5 | F17: 0.0375 | G17: 0 | H17: =+F17*$H$4/1000000 -> 0.375 | I17: 10 | J17: Sau khi rã đông. Bóc bỏ vỏ lilong bên ngoài cắt theo tỉ lệ (cắt xéo 0.5*3 ) | K17: Bóc vỏ : 5phút/0.5kg Cắt : 5 phút / 0.5Kg | L17: 0.5 Kg | M17: Rã đông, cắt theo tỉ lệ | N17: =+F17*$N$4/1000000 -> 0.825 | S17: =+F17*$S$4/1000000 -> 0.9375 | X17: =+F17*$X$4/1000000 -> 1.0125 | AC17: =+F17*$AC$4/1000000 -> 1.125 | AD17: 1.5 | AH17: =+F17*$AH$4/1000000 -> 1.875 | AM17: =+F17*$AM$4/1000000 -> 1.6875
C18: Ham | D18: Kg | E18: 46 | F18: 0.046 | G18: 0 | H18: =+F18*$H$4/1000000 -> 0.46 | I18: 5 | J18: Sau khi rã đông bóc vỏ ép bớt nước và cắt theo tỉ lệ (1*4.5 ) | K18: 5 phút/0.5Kg | L18: 0.5 Kg | M18: Rã đông, cắt theo tỉ lệ | N18: =+F18*$N$4/1000000 -> 1.012 | S18: =+F18*$S$4/1000000 -> 1.15 | X18: =+F18*$X$4/1000000 -> 1.242 | AC18: =+F18*$AC$4/1000000 -> 1.38 | AD18: 1.5 | AH18: =+F18*$AH$4/1000000 -> 2.3 | AM18: =+F18*$AM$4/1000000 -> 2.07
C19: Bacon | D19: Kg | E19: 37 | F19: 0.037 | G19: 0 | H19: =+F19*$H$4/1000000 -> 0.37 | I19: 0 | J19: Sau khi rã đông bóc ra bóp tơi và sử dụng luôn | L19: 1 Kg | M19: Rã đông | N19: =+F19*$N$4/1000000 -> 0.814 | S19: =+F19*$S$4/1000000 -> 0.925 | X19: =+F19*$X$4/1000000 -> 0.999 | AC19: =+F19*$AC$4/1000000 -> 1.11 | AD19: 0.5 | AH19: =+F19*$AH$4/1000000 -> 1.85 | AM19: =+F19*$AM$4/1000000 -> 1.665
C20: Smoked SG Sausage | D20: Kg | E20: 45 | F20: 0.045 | G20: 0 | H20: =+F20*$H$4/1000000 -> 0.45 | I20: 10 | J20: Sau khi rã đông bóc túi và cắt theo tỉ lệ (cắt xéo1*3) | K20: 10 phút/0.5 kg | L20: 0.5 Kg | M20: Rã đông, cắt theo tỉ lệ | N20: =+F20*$N$4/1000000 -> 0.99 | S20: =+F20*$S$4/1000000 -> 1.125 | X20: =+F20*$X$4/1000000 -> 1.215 | AC20: =+F20*$AC$4/1000000 -> 1.35 | AD20: 1 | AH20: =+F20*$AH$4/1000000 -> 2.25 | AM20: =+F20*$AM$4/1000000 -> 2.025
C21: Pepperoni | D21: Kg | E21: 45 | F21: 0.045 | G21: 0 | H21: =+F21*$H$4/1000000 -> 0.45 | I21: 0 | J21: Rã đông, sử dụng luôn | L21: Không có tối thiểu | M21: Rã đông | N21: =+F21*$N$4/1000000 -> 0.99 | S21: =+F21*$S$4/1000000 -> 1.125 | X21: =+F21*$X$4/1000000 -> 1.215 | AC21: =+F21*$AC$4/1000000 -> 1.35 | AD21: 2 | AH21: =+F21*$AH$4/1000000 -> 2.25 | AM21: =+F21*$AM$4/1000000 -> 2.025
C22: Shrimp With Tail (21/30) | D22: Kg | E22: 0 | F22: 0 | G22: 0 | H22: 0.2 | I22: 1 | J22: Rã đông, Đặt nước rồi trần theo tỉ lệ ( 5 lít nước/ 300g tôm ). Sau khi nước sôi bùng lên thả vào trần trong 30s. Vớt ra ngâm trong hỗn hợp nước đá với tỉ lệ( 1*1) trong 5 phút. Vớt ra xóc ráo bảo quản tủ mát trong tủ mát. | K22: 10 phút/ Kg cả thời gian ngâm đá | L22: Tối thiểu 300g | M22: Rã đông | N22: =+F22*$N$4/1000000 -> 0 | S22: =+F22*$S$4/1000000 -> 0 | X22: =+F22*$X$4/1000000 -> 0 | AC22: =+F22*$AC$4/1000000 -> 0 | AD22: 0.1 | AH22: =+F22*$AH$4/1000000 -> 0 | AM22: =+F22*$AM$4/1000000 -> 0
C23: Squid | D23: Kg | E23: 79 | F23: 0.079 | G23: 0 | H23: =+F23*$H$4/1000000 -> 0.79 | I23: 1 | J23: Rã đông, Đặt nước rồi trần theo tỉ lệ ( 5 lít nước/ 300g mực ). Sau khi nước sôi bùng lên thả vào trần trong 7s. Vớt ra ngâm trong hỗn hợp nước đá với tỉ lệ( 1*1) trong 5 phút. Vớt ra xóc ráo bảo quản tủ mát trong tủ mát. | K23: 10 phút/ Kg cả thời gian ngâm đá | L23: Tối thiểu 300g | M23: Rã đông/trần 7 giây | N23: =+F23*$N$4/1000000 -> 1.738 | S23: =+F23*$S$4/1000000 -> 1.975 | X23: =+F23*$X$4/1000000 -> 2.133 | AC23: =+F23*$AC$4/1000000 -> 2.37 | AD23: 3 | AH23: =+F23*$AH$4/1000000 -> 3.95 | AM23: =+F23*$AM$4/1000000 -> 3.555
C24: String Cheese (2 colors) | D24: Kg | E24: 200 | F24: 0.2 | G24: 0 | H24: =+F24*$H$4/1000000 -> 2 | I24: 0 | J24: Rã đông, sử dụng luôn | L24: Không có tối thiểu | M24: Rã đông | N24: =+F24*$N$4/1000000 -> 4.4 | S24: =+F24*$S$4/1000000 -> 5 | X24: =+F24*$X$4/1000000 -> 5.4 | AC24: =+F24*$AC$4/1000000 -> 6 | AD24: 4 | AH24: =+F24*$AH$4/1000000 -> 10 | AM24: =+F24*$AM$4/1000000 -> 9
C25: Beef Topping | D25: Kg | E25: 60 | F25: 0.06 | G25: 0 | H25: =+F25*$H$4/1000000 -> 0.6 | I25: 0 | J25: Sau khi rã đông, bóp tơi và sử dụng luôn | L25: Không có tối thiểu | M25: Rã đông | N25: =+F25*$N$4/1000000 -> 1.32 | S25: =+F25*$S$4/1000000 -> 1.5 | X25: =+F25*$X$4/1000000 -> 1.62 | AC25: =+F25*$AC$4/1000000 -> 1.8 | AD25: 2 | AH25: =+F25*$AH$4/1000000 -> 3 | AM25: =+F25*$AM$4/1000000 -> 2.7
C26: Shirmp Topping | D26: Kg | E26: 90 | F26: 0.09 | G26: 0 | H26: =+F26*$H$4/1000000 -> 0.9 | I26: 0 | J26: Sau khi rã đông đổ ra rổ lỗ xóc ráo rồi sử dụng luôn | L26: Không có tối thiểu | M26: Rã đông | N26: =+F26*$N$4/1000000 -> 1.98 | S26: =+F26*$S$4/1000000 -> 2.25 | X26: =+F26*$X$4/1000000 -> 2.43 | AC26: =+F26*$AC$4/1000000 -> 2.7 | AD26: 3 | AH26: =+F26*$AH$4/1000000 -> 4.5 | AM26: =+F26*$AM$4/1000000 -> 4.05
C27: Green Capsicum 1x4 | D27: Kg | E27: 45 | F27: 0.045 | G27: 0 | H27: =+F27*$H$4/1000000 -> 0.45 | I27: 15 | J27: Rửa sạch dưới vòi nước, cắt đầu trái loại bỏ phần ruột và hạt. Cắt thành từng miến theo tỉ lệ ( 1* 4) | K27: Loại bỏ phần ruột 5phút/1Kg Cắt 15 phút/ 1Kg | L27: Không có tối thiểu | M27: Sơ chế, cắt theo tỉ lệ | N27: =+F27*$N$4/1000000 -> 0.99 | S27: =+F27*$S$4/1000000 -> 1.125 | X27: =+F27*$X$4/1000000 -> 1.215 | AC27: =+F27*$AC$4/1000000 -> 1.35 | AD27: 2 | AH27: =+F27*$AH$4/1000000 -> 2.25 | AM27: =+F27*$AM$4/1000000 -> 2.025
C28: Red Capsicum 1x4 | D28: Kg | E28: 18 | F28: 0.018 | G28: 0 | H28: =+F28*$H$4/1000000 -> 0.18 | I28: 5 | J28: Rửa sạch dưới vòi nước, cắt đầu trái loại bỏ phần ruột và hạt. Cắt thành từng miến theo tỉ lệ ( 1* 4) | K28: Loại bỏ phần ruột 5phút/1Kg Cắt 15 phút/ 1Kg | L28: Không có tối thiểu | M28: Sơ chế, cắt theo tỉ lệ | N28: =+F28*$N$4/1000000 -> 0.396 | S28: =+F28*$S$4/1000000 -> 0.45 | X28: =+F28*$X$4/1000000 -> 0.486 | AC28: =+F28*$AC$4/1000000 -> 0.54 | AD28: 0.5 | AH28: =+F28*$AH$4/1000000 -> 0.9 | AM28: =+F28*$AM$4/1000000 -> 0.81
C29: Onion | D29: Kg | E29: 80 | F29: 0.08 | G29: 0 | H29: =+F29*$H$4/1000000 -> 0.8 | I29: 10 | J29: Bóc bỏ phần gốc và lớp vỏ khô, rửa sạch và khử trùng. Sau đó vớt ra để ráo rồi cắt theo thành từng miếng theo tỉ lệ ( 1* 4) | K29: Loại bỏ phần vỏ: 5phút/1Kg Ngâm:10 phút Cắt: 20 phút/ 1Kg | L29: Không có tối thiểu | M29: Sơ chế, cắt theo tỉ lệ | N29: =+F29*$N$4/1000000 -> 1.76 | S29: =+F29*$S$4/1000000 -> 2 | X29: =+F29*$X$4/1000000 -> 2.16 | AC29: =+F29*$AC$4/1000000 -> 2.4 | AD29: 2 | AH29: =+F29*$AH$4/1000000 -> 4 | AM29: =+F29*$AM$4/1000000 -> 3.6
C30: Olive | D30: Can | E30: 8.5 | F30: 0.0085 | G30: 0 | H30: =+F30*$H$4/1000000 -> 0.085 | I30: 0 | J30: Khui vỏ, đổ ra rổ, bọc kín để ráo 10 tiếng trong tủ mát | K30: 1 phút /Can | L30: 1 Can | M30: Sơ chế, để ráo nước | N30: =+F30*$N$4/1000000 -> 0.187 | S30: =+F30*$S$4/1000000 -> 0.2125 | X30: =+F30*$X$4/1000000 -> 0.2295 | AC30: =+F30*$AC$4/1000000 -> 0.255 | AD30: 0.2 | AH30: =+F30*$AH$4/1000000 -> 0.425 | AM30: =+F30*$AM$4/1000000 -> 0.3825
C31: Zuchinni | D31: Kg | E31: 22 | F31: 0.022 | G31: 0 | H31: =+F31*$H$4/1000000 -> 0.22 | I31: 3 | J31: Rửa sạch, bổ dọc quả làm 4 để được hình cánh quạt. Sau đó cắt thành từng lát mỏng dảy 0.2cm | K31: 5 phút / 0.5Kg | L31: Không có tối thiểu | M31: Sơ chế, cắt theo tỉ lệ | N31: =+F31*$N$4/1000000 -> 0.484 | S31: =+F31*$S$4/1000000 -> 0.55 | X31: =+F31*$X$4/1000000 -> 0.594 | AC31: =+F31*$AC$4/1000000 -> 0.66 | AD31: 0.1 | AH31: =+F31*$AH$4/1000000 -> 1.1 | AM31: =+F31*$AM$4/1000000 -> 0.99
C32: Mushroom | D32: Can | E32: 90 | F32: 0.09 | G32: 0 | H32: =+F32*$H$4/1000000 -> 0.9 | I32: 2 | J32: Khui vỏ, đổ ra rổ, bọc kín để ráo 10 tiếng trong tủ mát | K32: 2 phút /Can | L32: 1 Can | M32: Sơ chế, để ráo nước | N32: =+F32*$N$4/1000000 -> 1.98 | S32: =+F32*$S$4/1000000 -> 2.25 | X32: =+F32*$X$4/1000000 -> 2.43 | AC32: =+F32*$AC$4/1000000 -> 2.7 | AD32: 2 | AH32: =+F32*$AH$4/1000000 -> 4.5 | AM32: =+F32*$AM$4/1000000 -> 4.05
C33: Pineapple | D33: Can | E33: 85 | F33: 0.085 | G33: 0 | H33: =+F33*$H$4/1000000 -> 0.85 | I33: 2 | J33: Khui vỏ, đổ ra rổ, bọc kín để ráo 10 tiếng trong tủ mát | K33: 2 phút /Can | L33: 1 Can | M33: Sơ chế, để ráo nước | N33: =+F33*$N$4/1000000 -> 1.87 | S33: =+F33*$S$4/1000000 -> 2.125 | X33: =+F33*$X$4/1000000 -> 2.295 | AC33: =+F33*$AC$4/1000000 -> 2.55 | AD33: 2 | AH33: =+F33*$AH$4/1000000 -> 4.25 | AM33: =+F33*$AM$4/1000000 -> 3.825
C34: Cá ngừ ráo dầu | D34: Can | E34: 105 | F34: 0.05 | G34: 0 | H34: 0.5 | I34: 5 | J34: Khui vỏ, đổ ra rổ, bọc kín để ráo 10 tiếng trong tủ mát | K34: 5 phút /Can | L34: 1 Can | M34: Sơ chế, để ráo dầu | N34: =+F34*$N$4/1000000 -> 1.1 | S34: =+F34*$S$4/1000000 -> 1.25 | X34: =+F34*$X$4/1000000 -> 1.35 | AC34: =+F34*$AC$4/1000000 -> 1.5 | AH34: =+F34*$AH$4/1000000 -> 2.5 | AM34: =+F34*$AM$4/1000000 -> 2.25
C35: Wing Drumlet | D35: Kg | E35: 35 | F35: 0.033333333 | G35: 0 | H35: =+F35*$H$4/1000000 -> 0.33333333 | I35: 0 | J35: Rã đông, sử dụng luôn | L35: Không có tối thiểu | M35: Rã đông | S35: =+F35*$S$4/1000000 -> 0.83333333 | X35: =+F35*$X$4/1000000 -> 0.9 | AC35: =+F35*$AC$4/1000000 -> 1 | AH35: =+F35*$AH$4/1000000 -> 1.6666667 | AM35: =+F35*$AM$4/1000000 -> 1.5
C36: Wing Mid-wing | D36: Kg | E36: 15 | F36: 0.014285714 | G36: 0 | H36: =+F36*$H$4/1000000 -> 0.14285714 | I36: 0 | J36: Rã đông, sử dụng luôn | L36: Không có tối thiểu | M36: Rã đông | S36: =+F36*$S$4/1000000 -> 0.35714286 | X36: =+F36*$X$4/1000000 -> 0.38571429 | AC36: =+F36*$AC$4/1000000 -> 0.42857143 | AH36: =+F36*$AH$4/1000000 -> 0.71428571 | AM36: =+F36*$AM$4/1000000 -> 0.64285714
C37: Mince Meat | D37: Kg | E37: 21 | F37: 0.02 | G37: 0 | H37: =+F37*$H$4/1000000 -> 0.2 | I37: 0 | J37: Sau khi rã đông bóc ra bóp tơi và sử dụng luôn | L37: 0.5 Kg | M37: Rã đông | S37: =+F37*$S$4/1000000 -> 0.5 | X37: =+F37*$X$4/1000000 -> 0.54 | AC37: =+F37*$AC$4/1000000 -> 0.6 | AH37: =+F37*$AH$4/1000000 -> 1 | AM37: =+F37*$AM$4/1000000 -> 0.9
C38: Pesto sauce (3,3kg/phần) | D38: Kg | E38: 200 | F38: 0.09 | G38: 0 | H38: =+F38*$H$4/1000000 -> 0.9 | I38: 10 | J38: Chuẩn bị nguyên liệu: basil đã rã đông, đường, bột thịt gà, sốt mayonaise, dầu nành, công đựng. Sau đó cân theo tỉ lệ và trộn đều với nhau. | K38: Chuẩn bị nguyên liệu: 5 phút Trộn đều nguyên liệu: 5 phút | L38: 1Phần | M38: Đã chuẩn bị trước
C39: Sweet ups(5.2kg/phần) | D39: Kg | E39: 220 | F39: 0.1 | G39: 0 | H39: =+F39*$H$4/1000000 -> 1 | I39: 10 | J39: Chuẩn bị nguyên liệu: sốt tomato sweet, nước, công đựng. Sau đó cân theo tỉ lệ và trộn đều với nhau. | K39: Chuẩn bị nguyên liệu: 5 phút Trộn đều nguyên liệu: 5 phút | L39: 1Phần | M39: Đã chuẩn bị trước
C40: Cheesy mayo (0.2kg/phần) | D40: Kg | E40: 50 | F40: 0.04 | G40: 0 | H40: =+F40*$H$4/1000000 -> 0.4 | I40: 10 | J40: Chuẩn bị nguyên liệu: sốt spicy, mayonaise,đường, bột thịt gà, công đựng. Sau đó cân theo tỉ lệ và trộn đều với nhau. | K40: Chuẩn bị nguyên liệu: 5 phút Trộn đều nguyên liệu: 5 phút | L40: 1Phần | M40: Đã chuẩn bị trước
C41: Black Mayo | D41: Kg | E41: 40 | F41: 0.02 | G41: 0 | H41: =+F41*$H$4/1000000 -> 0.2 | I41: 10 | J41: Chuẩn bị nguyên liệu: sốt black, mayonaise, công đựng. Sau đó cân theo tỉ lệ và trộn đều với nhau. | K41: Chuẩn bị nguyên liệu: 5 phút Trộn đều nguyên liệu: 5 phút | L41: 1Phần | M41: Đã chuẩn bị trước
A43: 4 | B43: Auxi | C43: Italian Sausage | D43: Kg | E43: 5 | F43: 0.0067674902 | G43: 0 | H43: =+F43*$H$4/1000000 -> 0.067674902 | I43: 0 | J43: Rã đông, sử dụng luôn | L43: 0.5Kg | M43: Rã đông | S43: =+F43*$S$4/1000000 -> 0.16918726 | X43: =+F43*$X$4/1000000 -> 0.18272224 | AC43: =+F43*$AC$4/1000000 -> 0.20302471 | AH43: =+F43*$AH$4/1000000 -> 0.33837451 | AM43: =+F43*$AM$4/1000000 -> 0.30453706
C44: Bacon (Aux) | D44: Kg | E44: 20 | F44: 0.019047619 | G44: 0 | H44: =+F44*$H$4/1000000 -> 0.19047619 | I44: 10 | J44: Bacon sau khi rã đông bóp tơi và rải đều lên chảo thin. Sau đó đặt chảo thin lên chảo pan nướng 2/3 lò. Tiếp theo đảo mặt dưới củ bacon lên nướng thêm 1/3 lò. | K44: Chuẩn bị nguyên liệu: 1 phút Qua lò: 9 phút Làm nguội: 20 phút | L44: Không có tối thiểu | M44: Rã đông, qua lò
C45: Corn | D45: Kg | E45: 36 | F45: 0.034285714 | G45: 0 | H45: =+F45*$H$4/1000000 -> 0.34285714 | I45: 0 | J45: Rã đông, sử dụng luôn | L45: Không có tối thiểu | M45: Rã đông
C46: Green Bean | D46: Kg | E46: 1.5 | F46: 0.0014285714 | G46: 0 | H46: =+F46*$H$4/1000000 -> 0.014285714 | I46: 0 | J46: Rã đông, sử dụng luôn | L46: Không có tối thiểu | M46: Rã đông
C47: French Bean | D47: Kg | E47: 15 | F47: 0.014285714 | G47: 0 | H47: =+F47*$H$4/1000000 -> 0.14285714 | I47: 10 | J47: Rửa sạch, loại bỏ phần đầu quả rồi cắt theo tỉ lệ ( cắt xéo 1*3 ). Sau đó luộc trong nước sôi 2 phút. Vớt ra ngâm đá ngay để kìm hãm độ chín và giữ được màu sác của quả | K47: Sơ chế : 2 phút Cắt theo tỉ lệ 10 phút/0.5Kg Trần: 2 phút Làm nguội : 5 phút | L47: Không có tối thiểu | M47: Sơ chế, cắt theo tỉ lệ/ trần 2 phút
C48: Carrot | D48: Kg | E48: 14 | F48: 0.013333333 | G48: 0 | H48: =+F48*$H$4/1000000 -> 0.13333333 | I48: 12 | J48: Loại bỏ phần vỏ rồi cắt theo tỉ lệ (hạt lựu 1*1). Sau đó luộc trong nước sôi 7 phút. Vớt ra ngâm đá ngay để kìm hãm độ chín và giữ được màu sác của quả | K48: Sơ chế : 5 phút Cắt theo tỉ lệ 10 phút/0.5Kg Trần: 5 phút Làm nguội : 5 phút | L48: Không có tối thiểu | M48: Sơ chế, cắt theo tỉ lệ/ trần 7 phút
C49: Cherry Tomato | D49: Kg | E49: 20 | F49: 0.019047619 | G49: 0 | H49: =+F49*$H$4/1000000 -> 0.19047619 | I49: 10 | J49: Rửa sạch, nhặt bỏ phần cuống. Bổ dọc đôi quả cà chua. | K49: Sơ chế: 5 phút Cắt: 5 phút/ 0.5 Kg | L49: Không có tối thiểu | M49: Sơ chế
C50: Onions (Aux) | D50: Kg | E50: 3 | F50: 0.0028571429 | G50: 0 | H50: =+F50*$H$4/1000000 -> 0.028571429 | I50: 2 | J50: Bóc bỏ phần gốc và lớp vỏ khô, rửa sạch và khử trùng. Sau đó vớt ra để ráo rồi cắt theo thành từng miếng theo tỉ lệ ( 1*1 ). Sau đó lấy chảo pan đã quét dầu cho hành vào quét thêm 1 lớp dầu lên rồi qua 1/3 lò | K50: Loại bỏ phần vỏ: 5phút/1Kg Ngâm:10 phút Cắt: 20 phút/ 1Kg Qua lò 5 phút Làm nguội: 20 phút | L50: Không có tối thiểu | M50: Sơ chế, cắt theo tỉ lệ và cho qua lò
C51: Green Capsicum (Aux) | D51: Kg | E51: 3 | F51: 0.0028571429 | G51: 0 | H51: =+F51*$H$4/1000000 -> 0.028571429 | I51: 2 | J51: Rửa sạch dưới vòi nước, cắt đầu trái loại bỏ phần ruột và hạt. Cắt thành từng miến theo tỉ lệ ( cắt xéo 1*3).Sau đó lấy chảo pan đã quét dầu cho ớt vào quét thêm 1 lớp dầu lên rồi qua 1/3 lò | K51: Sơ chế: 2phút/1Kg Cắt: 15 phút/ 1Kg Qua lò 5 phút Làm nguội: 20 phút | L51: Không có tối thiểu | M51: Sơ chế, cắt theo tỉ lệ và cho qua lò
C52: Mushroom (Aux) | D52: Kg | E52: 3 | F52: 0.0028571429 | G52: 0 | H52: =+F52*$H$4/1000000 -> 0.028571429 | I52: 2 | J52: Khui vỏ, đổ ra rổ, bọc kín để ráo 10 tiếng trong tủ mát. Sau đó lấy chảo pan đã quét dầu cho ớt vào quét thêm 1 lớp dầu lên rồi qua 1/3 lò | K52: Chuẩn bị nguyên liệu: 2 phút Qua lò: 5 phút Làm nguội: 20 phút | L52: Không có tối thiểu | M52: Sơ chế, cắt theo tỉ lệ và cho qua lò
C53: Peach | D53: CAN | E53: 50 | F53: 0.047619048 | G53: 0 | H53: 1 | I53: 5 | J53: Khui hộp cắt chia làm 4 miếng nhỏ trên nửa quả | K53: 1 hôp 8-10 miếng cắt trong 5p | L53: 1 can | M53: Sơ chế
C54: Sơ chế Salad (Lola) | D54: Kg | H54: 0.5 | I54: 20 | J54: Nhặt bỏ phần gốc và các phần rau hỏng. Tách riêng từng lá sau đó rửa sạch dưới vòi nước. Cho rau vào ngâm khử trùng khoảng 10-15 phút. Vớt ra làm ráo và cắt ngang theo tỉ lệ ( 3*5 ). Rồi đóng gói. | K54: Sơ chế : 15 phút / 1 Kg Ngâm khử trùng : 10 phút Cắt : 5 phút Đóng gói: 5 phút | L54: Không có tối thiểu | M54: Sơ chế, cắt theo tỉ lệ, đóng bịch
C55: Đóng gói salad (Lola) | D55: Portion | H55: 8 | I55: 5 | K55: Đóng gói: 5p/kg | L55: Không có tối thiểu | M55: Sơ chế, cắt theo tỉ lệ, đóng bịch
C56: Luộc mỳ Spaghetty | D56: kg | E56: 350 | F56: 0.33333333 | G56: 0 | H56: 0.5 | I56: 15 | J56: Cho nước vào nồi rồi cho thêm muối. Nước sôi trải đều mỳ vào, đợi nước sôi trở lại để mỳ luộc thêm 7 phút. Kiểm tra xem mỳ đã chín chưa rồi đổ ra. Cho nước đá lạnh vào khuấy đều ngâm trong 10s. Làm ráo, bọc kín để trong tủ mát 30 phút. Sau đó đem ra trộn đều với dầu cho tơ sợi mỳ và đóng thành từng gói. | K56: Chuẩn bị nguyên liệu: 1 phút Luộc : 20 phút Làm nguội:30 phút Trộn dầu: 5 phút Đóng gói 10 phút | L56: 0.5Kg | M56: Sơ chế, luộc, đóng bịch
C57: Đóng gói Spaghetty | D57: Portion | E57: 350 | F57: 0.33333333 | G57: 0 | H57: 10 | I57: 10 | K57: Đóng gói 10p/0.5kg | L57: 0.5Kg | M57: Sơ chế, luộc, đóng bịch
C58: Khoai tây chiên | D58: Portion | H58: 5 | I58: 5 | J58: Lấy khoai trong tủ đông ra đóng thành từng gói | K58: 5 phút / 2Kg | L58: 2Kg | M58: Rã đông, đóng bịch
C59: Sốt Bơ tỏi ( 0.25kg/phần) | D59: Kg | H59: 1.2 | I59: 0 | J59: Chuẩn bị nguyên liệu:Bơ lạt đã xả ở nhiệt độ phòng 12 tiếng, hạt nêm nấm, tỏi, ngò, công đựng. Ngò nhặt lấy phần nhánh, rửa sạch, quay khô rồi bằm nhuyễn. Tỏi cắt bỏ phần cuống thâm, rửa sạch rồi đem say. Sau đó đem trộn đều với bơ đã xả mềm và hạt nêm nấm. | K59: Sơ chế rau củ: 5 phút/phần Băm ngò : 5 phút / phần Say tỏi : 3 phút/ phần Trộn : 3 phút/ phần | L59: 1Phần | M59: Đã chuẩn bị trước
C60: Cơm trắng (7 gói/ phần) | D60: Portion | H60: 4 | I60: 5 | K60: Chuẩn bị nguyên liệu 5p Đóng gói 1 phần (7 xuất): 5p | L60: 1Phần | M60: Đã chuẩn bị trước
C61: Sốt Creamy ( 0,9kg/ phần) | D61: Kg | H61: 0.5 | I61: 15 | J61: Chuẩn bị nguyên liệu:sốt bơ tỏi, hành tây xay, dầu nành,bột mỳ, nước,sữa tươi, kem béo, phô mai bột, aromat.Cho hành tây đã xay, bơ tỏi, dầu và 1 nửa bột mỳ vào chảo pan, khuấy đều rồi đậy chảo thi lên nướng full lò.đổ hỗn hợp và nước vào nồi đun khoảng 2 phút.Trộn đều bột mỳ còn lại cùng aromat, kem béo và sữa tươi. Sau đó cho vào nồi khuấy đều đun sôi. | K61: Chuần bi nguyên liệu :5 phút Nướng hỗn hợp: 8 phút Nấu sốt: 10 phút Làm nguội: 30 phút | L61: 1Phần | M61: Đã chuẩn bị trước
C62: Sốt Bolenese (2,4kg/ phần) | D62: Kg | H62: 1.1 | I62: 15 | J62: Chuẩn bị nguyên liệu:hành tây, cà rốt, cần tây, bột mỳ, sốt bơ tỏi, dầu ăn, sốt cà chua divella, tomato sweet, sốt black, nước, đường, aromat. Xay nhỏ rau củ rồi trộn ới bột mỳ, dầu và bơ tỏi cho vào chảo pan,đậy chảo thin lên rồi nướng full lò. Cho hỗn hợp và các nguyên liệu còn lại vào nồi khuấy đều đun sôi rồi đun thêm 10 phút. Đổ ra làm lạnh. bảo quản tủ mát | K62: Chuần bi nguyên liệu :5phút Nướng hỗn hợp: 8 phút Nấu sốt: 20 phút Làm nguội: 30 phút | L62: 1Phần | M62: Đã chuẩn bị trước
C63: Sốt tiêu đen (0.4kg/ phần) | D63: Kg | H63: 0.1 | I63: 10 | J63: Chuẩn bị nguyên liệu: Sốt black, nước,kem béo. Cho tất cả nguên liệu vào chảo. Khuấy đều đun 7 phút, đến khi sôi lăn tăn. Tắt bếp, làm nguội | K63: Chuần bi nguyên liệu :5phút Nấu sốt: 7 phút Làm nguội: 15 phút | L63: 1Phần | M63: Đã chuẩn bị trước
C64: Total | I64: =SUM(I16:I63) -> 262
